Workbook
Name MF_SchemeList: MF_Master!$B$4:INDEX(MF_Master!$B:$B,COUNTA(MF_Master!$B:$B)+2)
Name Stock_NameList: Stock_Master!$B$4:INDEX(Stock_Master!$B:$B,COUNTA(Stock_Master!$B:$B)+2)

Sheet Dashboard
A1: FAMILY PORTFOLIO — NET WORTH TRACKER
A2: As on | B2: =TODAY() -> 46217
A3: Family net worth | B3: =G16 -> 3259060.4 | D3: Inflation % p.a. | E3: 7
A4: Portfolio XIRR | B4: 0.067620969 | D4: Real return | E4: =IF(B4="","",(1+B4)/(1+E3/100)-1) -> -0.0022233931 | F4: =IF(B4="","",IF(B4>E3/100,"Beats inflation ✓","Below inflation ✗")) -> Below inflation ✗
A5: Person | B5: Equity | C5: Mutual Funds | D5: Fixed Deposits | E5: PPF | F5: Bonds | G5: Total
A6: Amit | B6: =IF($A6="","",SUMIFS(Equity!$I:$I,Equity!$A:$A,$A6)) -> 283200 | C6: =IF($A6="","",SUMIFS(MutualFunds!$I:$I,MutualFunds!$A:$A,$A6)) -> 65680.226 | D6: =IF($A6="","",SUMIFS(FixedDeposits!$I:$I,FixedDeposits!$A:$A,$A6)) -> 587277.98 | E6: =IF($A6="","",SUMIFS(PPF!$D:$D,PPF!$A:$A,$A6)) -> 425000 | F6: =IF($A6="","",SUMIFS(Bonds!$K:$K,Bonds!$A:$A,$A6)) -> 0 | G6: =IF($A6="","",SUM(B6:F6)) -> 1361158.2
A7: Priya | B7: =IF($A7="","",SUMIFS(Equity!$I:$I,Equity!$A:$A,$A7)) -> 222950 | C7: =IF($A7="","",SUMIFS(MutualFunds!$I:$I,MutualFunds!$A:$A,$A7)) -> 171733.97 | D7: =IF($A7="","",SUMIFS(FixedDeposits!$I:$I,FixedDeposits!$A:$A,$A7)) -> 0 | E7: =IF($A7="","",SUMIFS(PPF!$D:$D,PPF!$A:$A,$A7)) -> 860000 | F7: =IF($A7="","",SUMIFS(Bonds!$K:$K,Bonds!$A:$A,$A7)) -> 0 | G7: =IF($A7="","",SUM(B7:F7)) -> 1254684
A8: Rahul | B8: =IF($A8="","",SUMIFS(Equity!$I:$I,Equity!$A:$A,$A8)) -> 260600 | C8: =IF($A8="","",SUMIFS(MutualFunds!$I:$I,MutualFunds!$A:$A,$A8)) -> 0 | D8: =IF($A8="","",SUMIFS(FixedDeposits!$I:$I,FixedDeposits!$A:$A,$A8)) -> 331868.19 | E8: =IF($A8="","",SUMIFS(PPF!$D:$D,PPF!$A:$A,$A8)) -> 0 | F8: =IF($A8="","",SUMIFS(Bonds!$K:$K,Bonds!$A:$A,$A8)) -> 50750 | G8: =IF($A8="","",SUM(B8:F8)) -> 643218.19
B9: =IF($A9="","",SUMIFS(Equity!$I:$I,Equity!$A:$A,$A9)) | C9: =IF($A9="","",SUMIFS(MutualFunds!$I:$I,MutualFunds!$A:$A,$A9)) | D9: =IF($A9="","",SUMIFS(FixedDeposits!$I:$I,FixedDeposits!$A:$A,$A9)) | E9: =IF($A9="","",SUMIFS(PPF!$D:$D,PPF!$A:$A,$A9)) | F9: =IF($A9="","",SUMIFS(Bonds!$K:$K,Bonds!$A:$A,$A9)) | G9: =IF($A9="","",SUM(B9:F9))
B10: =IF($A10="","",SUMIFS(Equity!$I:$I,Equity!$A:$A,$A10)) | C10: =IF($A10="","",SUMIFS(MutualFunds!$I:$I,MutualFunds!$A:$A,$A10)) | D10: =IF($A10="","",SUMIFS(FixedDeposits!$I:$I,FixedDeposits!$A:$A,$A10)) | E10: =IF($A10="","",SUMIFS(PPF!$D:$D,PPF!$A:$A,$A10)) | F10: =IF($A10="","",SUMIFS(Bonds!$K:$K,Bonds!$A:$A,$A10)) | G10: =IF($A10="","",SUM(B10:F10))
B11: =IF($A11="","",SUMIFS(Equity!$I:$I,Equity!$A:$A,$A11)) | C11: =IF($A11="","",SUMIFS(MutualFunds!$I:$I,MutualFunds!$A:$A,$A11)) | D11: =IF($A11="","",SUMIFS(FixedDeposits!$I:$I,FixedDeposits!$A:$A,$A11)) | E11: =IF($A11="","",SUMIFS(PPF!$D:$D,PPF!$A:$A,$A11)) | F11: =IF($A11="","",SUMIFS(Bonds!$K:$K,Bonds!$A:$A,$A11)) | G11: =IF($A11="","",SUM(B11:F11))
B12: =IF($A12="","",SUMIFS(Equity!$I:$I,Equity!$A:$A,$A12)) | C12: =IF($A12="","",SUMIFS(MutualFunds!$I:$I,MutualFunds!$A:$A,$A12)) | D12: =IF($A12="","",SUMIFS(FixedDeposits!$I:$I,FixedDeposits!$A:$A,$A12)) | E12: =IF($A12="","",SUMIFS(PPF!$D:$D,PPF!$A:$A,$A12)) | F12: =IF($A12="","",SUMIFS(Bonds!$K:$K,Bonds!$A:$A,$A12)) | G12: =IF($A12="","",SUM(B12:F12))
B13: =IF($A13="","",SUMIFS(Equity!$I:$I,Equity!$A:$A,$A13)) | C13: =IF($A13="","",SUMIFS(MutualFunds!$I:$I,MutualFunds!$A:$A,$A13)) | D13: =IF($A13="","",SUMIFS(FixedDeposits!$I:$I,FixedDeposits!$A:$A,$A13)) | E13: =IF($A13="","",SUMIFS(PPF!$D:$D,PPF!$A:$A,$A13)) | F13: =IF($A13="","",SUMIFS(Bonds!$K:$K,Bonds!$A:$A,$A13)) | G13: =IF($A13="","",SUM(B13:F13))
B14: =IF($A14="","",SUMIFS(Equity!$I:$I,Equity!$A:$A,$A14)) | C14: =IF($A14="","",SUMIFS(MutualFunds!$I:$I,MutualFunds!$A:$A,$A14)) | D14: =IF($A14="","",SUMIFS(FixedDeposits!$I:$I,FixedDeposits!$A:$A,$A14)) | E14: =IF($A14="","",SUMIFS(PPF!$D:$D,PPF!$A:$A,$A14)) | F14: =IF($A14="","",SUMIFS(Bonds!$K:$K,Bonds!$A:$A,$A14)) | G14: =IF($A14="","",SUM(B14:F14))
B15: =IF($A15="","",SUMIFS(Equity!$I:$I,Equity!$A:$A,$A15)) | C15: =IF($A15="","",SUMIFS(MutualFunds!$I:$I,MutualFunds!$A:$A,$A15)) | D15: =IF($A15="","",SUMIFS(FixedDeposits!$I:$I,FixedDeposits!$A:$A,$A15)) | E15: =IF($A15="","",SUMIFS(PPF!$D:$D,PPF!$A:$A,$A15)) | F15: =IF($A15="","",SUMIFS(Bonds!$K:$K,Bonds!$A:$A,$A15)) | G15: =IF($A15="","",SUM(B15:F15))
A16: TOTAL | B16: =SUM(B6:B15) -> 766750 | C16: =SUM(C6:C15) -> 237414.19 | D16: =SUM(D6:D15) -> 919146.17 | E16: =SUM(E6:E15) -> 1285000 | F16: =SUM(F6:F15) -> 50750 | G16: =SUM(G6:G15) -> 3259060.4
A18: Allocation by asset class
A19: Asset class | B19: Value | C19: XIRR
A20: Equity | B20: =B16 -> 766750 | C20: 0.066436552
A21: Mutual Funds | B21: =C16 -> 237414.19 | C21: 0.087670606
A22: Fixed Deposits | B22: =D16 -> 919146.17 | C22: 0.072140147
A23: PPF | B23: =E16 -> 1285000 | C23: 0.071
A24: Bonds | B24: =F16 -> 50750 | C24: 0.0059830784

Sheet Projection
A1: CORPUS PROJECTION — NEXT 20 YEARS
A2: Today's corpus compounding at the portfolio XIRR vs plain inflation. Assumes a constant return and no future contributions. Edit inflation on the Dashboard (yellow cell); the updaters refresh the XIRR.
A3: Year | B3: Corpus @ portfolio XIRR | C3: Corpus growing at inflation | D3: Real corpus (today's money)
A4: =YEAR(TODAY())+0 -> 2026 | B4: =Dashboard!$B$3*(1+Dashboard!$B$4)^0 -> 3259060.4 | C4: =Dashboard!$B$3*(1+Dashboard!$E$3/100)^0 -> 3259060.4 | D4: =B4/(1+Dashboard!$E$3/100)^0 -> 3259060.4
A5: =YEAR(TODAY())+1 -> 2027 | B5: =Dashboard!$B$3*(1+Dashboard!$B$4)^1 -> 3479441.2 | C5: =Dashboard!$B$3*(1+Dashboard!$E$3/100)^1 -> 3487194.6 | D5: =B5/(1+Dashboard!$E$3/100)^1 -> 3251814.2
A6: =YEAR(TODAY())+2 -> 2028 | B6: =Dashboard!$B$3*(1+Dashboard!$B$4)^2 -> 3714724.4 | C6: =Dashboard!$B$3*(1+Dashboard!$E$3/100)^2 -> 3731298.2 | D6: =B6/(1+Dashboard!$E$3/100)^2 -> 3244584.1
A7: =YEAR(TODAY())+3 -> 2029 | B7: =Dashboard!$B$3*(1+Dashboard!$B$4)^3 -> 3965917.6 | C7: =Dashboard!$B$3*(1+Dashboard!$E$3/100)^3 -> 3992489.1 | D7: =B7/(1+Dashboard!$E$3/100)^3 -> 3237370.1
A8: =YEAR(TODAY())+4 -> 2030 | B8: =Dashboard!$B$3*(1+Dashboard!$B$4)^4 -> 4234096.8 | C8: =Dashboard!$B$3*(1+Dashboard!$E$3/100)^4 -> 4271963.3 | D8: =B8/(1+Dashboard!$E$3/100)^4 -> 3230172.2
A9: =YEAR(TODAY())+5 -> 2031 | B9: =Dashboard!$B$3*(1+Dashboard!$B$4)^5 -> 4520410.6 | C9: =Dashboard!$B$3*(1+Dashboard!$E$3/100)^5 -> 4571000.8 | D9: =B9/(1+Dashboard!$E$3/100)^5 -> 3222990.3
A10: =YEAR(TODAY())+6 -> 2032 | B10: =Dashboard!$B$3*(1+Dashboard!$B$4)^6 -> 4826085.1 | C10: =Dashboard!$B$3*(1+Dashboard!$E$3/100)^6 -> 4890970.8 | D10: =B10/(1+Dashboard!$E$3/100)^6 -> 3215824.3
A11: =YEAR(TODAY())+7 -> 2033 | B11: =Dashboard!$B$3*(1+Dashboard!$B$4)^7 -> 5152429.7 | C11: =Dashboard!$B$3*(1+Dashboard!$E$3/100)^7 -> 5233338.8 | D11: =B11/(1+Dashboard!$E$3/100)^7 -> 3208674.2
A12: =YEAR(TODAY())+8 -> 2034 | B12: =Dashboard!$B$3*(1+Dashboard!$B$4)^8 -> 5500842 | C12: =Dashboard!$B$3*(1+Dashboard!$E$3/100)^8 -> 5599672.5 | D12: =B12/(1+Dashboard!$E$3/100)^8 -> 3201540.1
A13: =YEAR(TODAY())+9 -> 2035 | B13: =Dashboard!$B$3*(1+Dashboard!$B$4)^9 -> 5872814.2 | C13: =Dashboard!$B$3*(1+Dashboard!$E$3/100)^9 -> 5991649.6 | D13: =B13/(1+Dashboard!$E$3/100)^9 -> 3194421.8
A14: =YEAR(TODAY())+10 -> 2036 | B14: =Dashboard!$B$3*(1+Dashboard!$B$4)^10 -> 6269939.6 | C14: =Dashboard!$B$3*(1+Dashboard!$E$3/100)^10 -> 6411065 | D14: =B14/(1+Dashboard!$E$3/100)^10 -> 3187319.4
A15: =YEAR(TODAY())+11 -> 2037 | B15: =Dashboard!$B$3*(1+Dashboard!$B$4)^11 -> 6693919 | C15: =Dashboard!$B$3*(1+Dashboard!$E$3/100)^11 -> 6859839.6 | D15: =B15/(1+Dashboard!$E$3/100)^11 -> 3180232.7
A16: =YEAR(TODAY())+12 -> 2038 | B16: =Dashboard!$B$3*(1+Dashboard!$B$4)^12 -> 7146568.3 | C16: =Dashboard!$B$3*(1+Dashboard!$E$3/100)^12 -> 7340028.3 | D16: =B16/(1+Dashboard!$E$3/100)^12 -> 3173161.8
A17: =YEAR(TODAY())+13 -> 2039 | B17: =Dashboard!$B$3*(1+Dashboard!$B$4)^13 -> 7629826.2 | C17: =Dashboard!$B$3*(1+Dashboard!$E$3/100)^13 -> 7853830.3 | D17: =B17/(1+Dashboard!$E$3/100)^13 -> 3166106.6
A18: =YEAR(TODAY())+14 -> 2040 | B18: =Dashboard!$B$3*(1+Dashboard!$B$4)^14 -> 8145762.4 | C18: =Dashboard!$B$3*(1+Dashboard!$E$3/100)^14 -> 8403598.5 | D18: =B18/(1+Dashboard!$E$3/100)^14 -> 3159067.1
A19: =YEAR(TODAY())+15 -> 2041 | B19: =Dashboard!$B$3*(1+Dashboard!$B$4)^15 -> 8696586.8 | C19: =Dashboard!$B$3*(1+Dashboard!$E$3/100)^15 -> 8991850.3 | D19: =B19/(1+Dashboard!$E$3/100)^15 -> 3152043.3
A20: =YEAR(TODAY())+16 -> 2042 | B20: =Dashboard!$B$3*(1+Dashboard!$B$4)^16 -> 9284658.4 | C20: =Dashboard!$B$3*(1+Dashboard!$E$3/100)^16 -> 9621279.9 | D20: =B20/(1+Dashboard!$E$3/100)^16 -> 3145035
A21: =YEAR(TODAY())+17 -> 2043 | B21: =Dashboard!$B$3*(1+Dashboard!$B$4)^17 -> 9912496 | C21: =Dashboard!$B$3*(1+Dashboard!$E$3/100)^17 -> 10294769 | D21: =B21/(1+Dashboard!$E$3/100)^17 -> 3138042.4
A22: =YEAR(TODAY())+18 -> 2044 | B22: =Dashboard!$B$3*(1+Dashboard!$B$4)^18 -> 10582789 | C22: =Dashboard!$B$3*(1+Dashboard!$E$3/100)^18 -> 11015403 | D22: =B22/(1+Dashboard!$E$3/100)^18 -> 3131065.3
A23: =YEAR(TODAY())+19 -> 2045 | B23: =Dashboard!$B$3*(1+Dashboard!$B$4)^19 -> 11298407 | C23: =Dashboard!$B$3*(1+Dashboard!$E$3/100)^19 -> 11786482 | D23: =B23/(1+Dashboard!$E$3/100)^19 -> 3124103.7
A24: =YEAR(TODAY())+20 -> 2046 | B24: =Dashboard!$B$3*(1+Dashboard!$B$4)^20 -> 12062416 | C24: =Dashboard!$B$3*(1+Dashboard!$E$3/100)^20 -> 12611535 | D24: =B24/(1+Dashboard!$E$3/100)^20 -> 3117157.6
A27: HOW TO READ THIS SHEET (in plain words)
A28: Your family's money today (the Dashboard net worth) is shown on three paths:
A29: 1. Corpus @ portfolio XIRR — what your money can GROW TO if it keeps earning the
A30: same yearly return it earns today (the 'Portfolio XIRR' on the Dashboard).
A31: 2. Corpus growing at inflation — what the same money must become JUST TO KEEP UP
A32: with rising prices (the yellow 'Inflation %' cell on the Dashboard, normally 7).
A33: 3. Real corpus (today’s money) — the first path converted back into today’s prices:
A34: what that future amount will actually feel like when you spend it.
A35: Simple rule: if the BLUE line (your portfolio) stays above the RED line (inflation),
A36: you are beating inflation and getting richer in real terms. If it dips below, your
A37: money is still growing but it quietly buys less every year.
A38: Example: at 7% inflation, 1 crore received 20 years from now buys only what roughly
... A40: Try it: change the yellow inflation cell on the Dashboard — the lines move instantly.

Sheet Amit
A1: Amit — PORTFOLIO
A2: Owner | B2: Amit
A3: Net worth | B3: =B11 -> 1361158.2
A5: Asset class | B5: Value | C5: # holdings
A6: Equity | B6: =SUMIFS(Equity!$I:$I,Equity!$A:$A,$B$2) -> 283200 | C6: =COUNTIF(Equity!$A:$A,$B$2) -> 4
A7: Mutual Funds | B7: =SUMIFS(MutualFunds!$I:$I,MutualFunds!$A:$A,$B$2) -> 65680.226 | C7: =COUNTIF(MutualFunds!$A:$A,$B$2) -> 1
A8: Fixed Deposits | B8: =SUMIFS(FixedDeposits!$I:$I,FixedDeposits!$A:$A,$B$2) -> 587277.98 | C8: =COUNTIF(FixedDeposits!$A:$A,$B$2) -> 1
A9: PPF | B9: =SUMIFS(PPF!$D:$D,PPF!$A:$A,$B$2) -> 425000 | C9: =COUNTIF(PPF!$A:$A,$B$2) -> 1
A10: Bonds | B10: =SUMIFS(Bonds!$K:$K,Bonds!$A:$A,$B$2) -> 0 | C10: =COUNTIF(Bonds!$A:$A,$B$2) -> 0
A11: Total | B11: =SUM(B6:B10) -> 1361158.2 | C11: =SUM(C6:C10) -> 7
A14: EQUITY
A15: ISIN | B15: Scrip | C15: Qty | D15: Avg cost | E15: Cur. val | F15: Net chg. | G15: XIRR
A16: =IFERROR(INDEX(Equity!$B:$B,MATCH($B$2&"#"&1,Equity!$P:$P,0)),"") -> INE002A01018 | B16: =IFERROR(INDEX(Equity!$C:$C,MATCH($B$2&"#"&1,Equity!$P:$P,0)),"") -> RELIANCE INDUSTRIES LIMITED EQ | C16: =IFERROR(INDEX(Equity!$D:$D,MATCH($B$2&"#"&1,Equity!$P:$P,0)),"") -> 50 | D16: =IFERROR(INDEX(Equity!$E:$E,MATCH($B$2&"#"&1,Equity!$P:$P,0)),"") -> 964.9 | E16: =IFERROR(INDEX(Equity!$I:$I,MATCH($B$2&"#"&1,Equity!$P:$P,0)),"") -> 76000 | F16: =IFERROR(INDEX(Equity!$K:$K,MATCH($B$2&"#"&1,Equity!$P:$P,0)),"") -> 27755 | G16: =IFERROR(INDEX(Equity!$N:$N,MATCH($B$2&"#"&1,Equity!$P:$P,0)),"") -> 0.055220257
A17: =IFERROR(INDEX(Equity!$B:$B,MATCH($B$2&"#"&2,Equity!$P:$P,0)),"") -> INE467B01029 | B17: =IFERROR(INDEX(Equity!$C:$C,MATCH($B$2&"#"&2,Equity!$P:$P,0)),"") -> TATA CONSULTANCY SERVICES LIMITED EQ | C17: =IFERROR(INDEX(Equity!$D:$D,MATCH($B$2&"#"&2,Equity!$P:$P,0)),"") -> 12 | D17: =IFERROR(INDEX(Equity!$E:$E,MATCH($B$2&"#"&2,Equity!$P:$P,0)),"") -> 2916.05 | E17: =IFERROR(INDEX(Equity!$I:$I,MATCH($B$2&"#"&2,Equity!$P:$P,0)),"") -> 41400 | F17: =IFERROR(INDEX(Equity!$K:$K,MATCH($B$2&"#"&2,Equity!$P:$P,0)),"") -> 6407.4 | G17: =IFERROR(INDEX(Equity!$N:$N,MATCH($B$2&"#"&2,Equity!$P:$P,0)),"") -> 0.020086519
A18: =IFERROR(INDEX(Equity!$B:$B,MATCH($B$2&"#"&3,Equity!$P:$P,0)),"") -> INE009A01021 | B18: =IFERROR(INDEX(Equity!$C:$C,MATCH($B$2&"#"&3,Equity!$P:$P,0)),"") -> INFOSYS LIMITED EQ | C18: =IFERROR(INDEX(Equity!$D:$D,MATCH($B$2&"#"&3,Equity!$P:$P,0)),"") -> 40 | D18: =IFERROR(INDEX(Equity!$E:$E,MATCH($B$2&"#"&3,Equity!$P:$P,0)),"") -> 1173.85 | E18: =IFERROR(INDEX(Equity!$I:$I,MATCH($B$2&"#"&3,Equity!$P:$P,0)),"") -> 64400 | F18: =IFERROR(INDEX(Equity!$K:$K,MATCH($B$2&"#"&3,Equity!$P:$P,0)),"") -> 17446 | G18: =IFERROR(INDEX(Equity!$N:$N,MATCH($B$2&"#"&3,Equity!$P:$P,0)),"") -> 0.038075757
A19: =IFERROR(INDEX(Equity!$B:$B,MATCH($B$2&"#"&4,Equity!$P:$P,0)),"") -> INE040A01034 | B19: =IFERROR(INDEX(Equity!$C:$C,MATCH($B$2&"#"&4,Equity!$P:$P,0)),"") -> HDFC BANK LIMITED EQ | C19: =IFERROR(INDEX(Equity!$D:$D,MATCH($B$2&"#"&4,Equity!$P:$P,0)),"") -> 60 | D19: =IFERROR(INDEX(Equity!$E:$E,MATCH($B$2&"#"&4,Equity!$P:$P,0)),"") -> 1076 | E19: =IFERROR(INDEX(Equity!$I:$I,MATCH($B$2&"#"&4,Equity!$P:$P,0)),"") -> 101400 | F19: =IFERROR(INDEX(Equity!$K:$K,MATCH($B$2&"#"&4,Equity!$P:$P,0)),"") -> 36840 | G19: =IFERROR(INDEX(Equity!$N:$N,MATCH($B$2&"#"&4,Equity!$P:$P,0)),"") -> 0.054850508
A20: =IFERROR(INDEX(Equity!$B:$B,MATCH($B$2&"#"&5,Equity!$P:$P,0)),"") | B20: =IFERROR(INDEX(Equity!$C:$C,MATCH($B$2&"#"&5,Equity!$P:$P,0)),"") | C20: =IFERROR(INDEX(Equity!$D:$D,MATCH($B$2&"#"&5,Equity!$P:$P,0)),"") | D20: =IFERROR(INDEX(Equity!$E:$E,MATCH($B$2&"#"&5,Equity!$P:$P,0)),"") | E20: =IFERROR(INDEX(Equity!$I:$I,MATCH($B$2&"#"&5,Equity!$P:$P,0)),"") | F20: =IFERROR(INDEX(Equity!$K:$K,MATCH($B$2&"#"&5,Equity!$P:$P,0)),"") | G20: =IFERROR(INDEX(Equity!$N:$N,MATCH($B$2&"#"&5,Equity!$P:$P,0)),"")
A21: =IFERROR(INDEX(Equity!$B:$B,MATCH($B$2&"#"&6,Equity!$P:$P,0)),"") | B21: =IFERROR(INDEX(Equity!$C:$C,MATCH($B$2&"#"&6,Equity!$P:$P,0)),"") | C21: =IFERROR(INDEX(Equity!$D:$D,MATCH($B$2&"#"&6,Equity!$P:$P,0)),"") | D21: =IFERROR(INDEX(Equity!$E:$E,MATCH($B$2&"#"&6,Equity!$P:$P,0)),"") | E21: =IFERROR(INDEX(Equity!$I:$I,MATCH($B$2&"#"&6,Equity!$P:$P,0)),"") | F21: =IFERROR(INDEX(Equity!$K:$K,MATCH($B$2&"#"&6,Equity!$P:$P,0)),"") | G21: =IFERROR(INDEX(Equity!$N:$N,MATCH($B$2&"#"&6,Equity!$P:$P,0)),"")
A22: =IFERROR(INDEX(Equity!$B:$B,MATCH($B$2&"#"&7,Equity!$P:$P,0)),"") | B22: =IFERROR(INDEX(Equity!$C:$C,MATCH($B$2&"#"&7,Equity!$P:$P,0)),"") | C22: =IFERROR(INDEX(Equity!$D:$D,MATCH($B$2&"#"&7,Equity!$P:$P,0)),"") | D22: =IFERROR(INDEX(Equity!$E:$E,MATCH($B$2&"#"&7,Equity!$P:$P,0)),"") | E22: =IFERROR(INDEX(Equity!$I:$I,MATCH($B$2&"#"&7,Equity!$P:$P,0)),"") | F22: =IFERROR(INDEX(Equity!$K:$K,MATCH($B$2&"#"&7,Equity!$P:$P,0)),"") | G22: =IFERROR(INDEX(Equity!$N:$N,MATCH($B$2&"#"&7,Equity!$P:$P,0)),"")
A23: =IFERROR(INDEX(Equity!$B:$B,MATCH($B$2&"#"&8,Equity!$P:$P,0)),"") | B23: =IFERROR(INDEX(Equity!$C:$C,MATCH($B$2&"#"&8,Equity!$P:$P,0)),"") | C23: =IFERROR(INDEX(Equity!$D:$D,MATCH($B$2&"#"&8,Equity!$P:$P,0)),"") | D23: =IFERROR(INDEX(Equity!$E:$E,MATCH($B$2&"#"&8,Equity!$P:$P,0)),"") | E23: =IFERROR(INDEX(Equity!$I:$I,MATCH($B$2&"#"&8,Equity!$P:$P,0)),"") | F23: =IFERROR(INDEX(Equity!$K:$K,MATCH($B$2&"#"&8,Equity!$P:$P,0)),"") | G23: =IFERROR(INDEX(Equity!$N:$N,MATCH($B$2&"#"&8,Equity!$P:$P,0)),"")
A24: =IFERROR(INDEX(Equity!$B:$B,MATCH($B$2&"#"&9,Equity!$P:$P,0)),"") | B24: =IFERROR(INDEX(Equity!$C:$C,MATCH($B$2&"#"&9,Equity!$P:$P,0)),"") | C24: =IFERROR(INDEX(Equity!$D:$D,MATCH($B$2&"#"&9,Equity!$P:$P,0)),"") | D24: =IFERROR(INDEX(Equity!$E:$E,MATCH($B$2&"#"&9,Equity!$P:$P,0)),"") | E24: =IFERROR(INDEX(Equity!$I:$I,MATCH($B$2&"#"&9,Equity!$P:$P,0)),"") | F24: =IFERROR(INDEX(Equity!$K:$K,MATCH($B$2&"#"&9,Equity!$P:$P,0)),"") | G24: =IFERROR(INDEX(Equity!$N:$N,MATCH($B$2&"#"&9,Equity!$P:$P,0)),"")
A25: =IFERROR(INDEX(Equity!$B:$B,MATCH($B$2&"#"&10,Equity!$P:$P,0)),"") | B25: =IFERROR(INDEX(Equity!$C:$C,MATCH($B$2&"#"&10,Equity!$P:$P,0)),"") | C25: =IFERROR(INDEX(Equity!$D:$D,MATCH($B$2&"#"&10,Equity!$P:$P,0)),"") | D25: =IFERROR(INDEX(Equity!$E:$E,MATCH($B$2&"#"&10,Equity!$P:$P,0)),"") | E25: =IFERROR(INDEX(Equity!$I:$I,MATCH($B$2&"#"&10,Equity!$P:$P,0)),"") | F25: =IFERROR(INDEX(Equity!$K:$K,MATCH($B$2&"#"&10,Equity!$P:$P,0)),"") | G25: =IFERROR(INDEX(Equity!$N:$N,MATCH($B$2&"#"&10,Equity!$P:$P,0)),"")
A26: =IFERROR(INDEX(Equity!$B:$B,MATCH($B$2&"#"&11,Equity!$P:$P,0)),"") | B26: =IFERROR(INDEX(Equity!$C:$C,MATCH($B$2&"#"&11,Equity!$P:$P,0)),"") | C26: =IFERROR(INDEX(Equity!$D:$D,MATCH($B$2&"#"&11,Equity!$P:$P,0)),"") | D26: =IFERROR(INDEX(Equity!$E:$E,MATCH($B$2&"#"&11,Equity!$P:$P,0)),"") | E26: =IFERROR(INDEX(Equity!$I:$I,MATCH($B$2&"#"&11,Equity!$P:$P,0)),"") | F26: =IFERROR(INDEX(Equity!$K:$K,MATCH($B$2&"#"&11,Equity!$P:$P,0)),"") | G26: =IFERROR(INDEX(Equity!$N:$N,MATCH($B$2&"#"&11,Equity!$P:$P,0)),"")
A27: =IFERROR(INDEX(Equity!$B:$B,MATCH($B$2&"#"&12,Equity!$P:$P,0)),"") | B27: =IFERROR(INDEX(Equity!$C:$C,MATCH($B$2&"#"&12,Equity!$P:$P,0)),"") | C27: =IFERROR(INDEX(Equity!$D:$D,MATCH($B$2&"#"&12,Equity!$P:$P,0)),"") | D27: =IFERROR(INDEX(Equity!$E:$E,MATCH($B$2&"#"&12,Equity!$P:$P,0)),"") | E27: =IFERROR(INDEX(Equity!$I:$I,MATCH($B$2&"#"&12,Equity!$P:$P,0)),"") | F27: =IFERROR(INDEX(Equity!$K:$K,MATCH($B$2&"#"&12,Equity!$P:$P,0)),"") | G27: =IFERROR(INDEX(Equity!$N:$N,MATCH($B$2&"#"&12,Equity!$P:$P,0)),"")
A28: =IFERROR(INDEX(Equity!$B:$B,MATCH($B$2&"#"&13,Equity!$P:$P,0)),"") | B28: =IFERROR(INDEX(Equity!$C:$C,MATCH($B$2&"#"&13,Equity!$P:$P,0)),"") | C28: =IFERROR(INDEX(Equity!$D:$D,MATCH($B$2&"#"&13,Equity!$P:$P,0)),"") | D28: =IFERROR(INDEX(Equity!$E:$E,MATCH($B$2&"#"&13,Equity!$P:$P,0)),"") | E28: =IFERROR(INDEX(Equity!$I:$I,MATCH($B$2&"#"&13,Equity!$P:$P,0)),"") | F28: =IFERROR(INDEX(Equity!$K:$K,MATCH($B$2&"#"&13,Equity!$P:$P,0)),"") | G28: =IFERROR(INDEX(Equity!$N:$N,MATCH($B$2&"#"&13,Equity!$P:$P,0)),"")
A29: =IFERROR(INDEX(Equity!$B:$B,MATCH($B$2&"#"&14,Equity!$P:$P,0)),"") | B29: =IFERROR(INDEX(Equity!$C:$C,MATCH($B$2&"#"&14,Equity!$P:$P,0)),"") | C29: =IFERROR(INDEX(Equity!$D:$D,MATCH($B$2&"#"&14,Equity!$P:$P,0)),"") | D29: =IFERROR(INDEX(Equity!$E:$E,MATCH($B$2&"#"&14,Equity!$P:$P,0)),"") | E29: =IFERROR(INDEX(Equity!$I:$I,MATCH($B$2&"#"&14,Equity!$P:$P,0)),"") | F29: =IFERROR(INDEX(Equity!$K:$K,MATCH($B$2&"#"&14,Equity!$P:$P,0)),"") | G29: =IFERROR(INDEX(Equity!$N:$N,MATCH($B$2&"#"&14,Equity!$P:$P,0)),"")
A30: =IFERROR(INDEX(Equity!$B:$B,MATCH($B$2&"#"&15,Equity!$P:$P,0)),"") | B30: =IFERROR(INDEX(Equity!$C:$C,MATCH($B$2&"#"&15,Equity!$P:$P,0)),"") | C30: =IFERROR(INDEX(Equity!$D:$D,MATCH($B$2&"#"&15,Equity!$P:$P,0)),"") | D30: =IFERROR(INDEX(Equity!$E:$E,MATCH($B$2&"#"&15,Equity!$P:$P,0)),"") | E30: =IFERROR(INDEX(Equity!$I:$I,MATCH($B$2&"#"&15,Equity!$P:$P,0)),"") | F30: =IFERROR(INDEX(Equity!$K:$K,MATCH($B$2&"#"&15,Equity!$P:$P,0)),"") | G30: =IFERROR(INDEX(Equity!$N:$N,MATCH($B$2&"#"&15,Equity!$P:$P,0)),"")
A31: =IFERROR(INDEX(Equity!$B:$B,MATCH($B$2&"#"&16,Equity!$P:$P,0)),"") | B31: =IFERROR(INDEX(Equity!$C:$C,MATCH($B$2&"#"&16,Equity!$P:$P,0)),"") | C31: =IFERROR(INDEX(Equity!$D:$D,MATCH($B$2&"#"&16,Equity!$P:$P,0)),"") | D31: =IFERROR(INDEX(Equity!$E:$E,MATCH($B$2&"#"&16,Equity!$P:$P,0)),"") | E31: =IFERROR(INDEX(Equity!$I:$I,MATCH($B$2&"#"&16,Equity!$P:$P,0)),"") | F31: =IFERROR(INDEX(Equity!$K:$K,MATCH($B$2&"#"&16,Equity!$P:$P,0)),"") | G31: =IFERROR(INDEX(Equity!$N:$N,MATCH($B$2&"#"&16,Equity!$P:$P,0)),"")
A32: =IFERROR(INDEX(Equity!$B:$B,MATCH($B$2&"#"&17,Equity!$P:$P,0)),"") | B32: =IFERROR(INDEX(Equity!$C:$C,MATCH($B$2&"#"&17,Equity!$P:$P,0)),"") | C32: =IFERROR(INDEX(Equity!$D:$D,MATCH($B$2&"#"&17,Equity!$P:$P,0)),"") | D32: =IFERROR(INDEX(Equity!$E:$E,MATCH($B$2&"#"&17,Equity!$P:$P,0)),"") | E32: =IFERROR(INDEX(Equity!$I:$I,MATCH($B$2&"#"&17,Equity!$P:$P,0)),"") | F32: =IFERROR(INDEX(Equity!$K:$K,MATCH($B$2&"#"&17,Equity!$P:$P,0)),"") | G32: =IFERROR(INDEX(Equity!$N:$N,MATCH($B$2&"#"&17,Equity!$P:$P,0)),"")
A33: =IFERROR(INDEX(Equity!$B:$B,MATCH($B$2&"#"&18,Equity!$P:$P,0)),"") | B33: =IFERROR(INDEX(Equity!$C:$C,MATCH($B$2&"#"&18,Equity!$P:$P,0)),"") | C33: =IFERROR(INDEX(Equity!$D:$D,MATCH($B$2&"#"&18,Equity!$P:$P,0)),"") | D33: =IFERROR(INDEX(Equity!$E:$E,MATCH($B$2&"#"&18,Equity!$P:$P,0)),"") | E33: =IFERROR(INDEX(Equity!$I:$I,MATCH($B$2&"#"&18,Equity!$P:$P,0)),"") | F33: =IFERROR(INDEX(Equity!$K:$K,MATCH($B$2&"#"&18,Equity!$P:$P,0)),"") | G33: =IFERROR(INDEX(Equity!$N:$N,MATCH($B$2&"#"&18,Equity!$P:$P,0)),"")
A34: =IFERROR(INDEX(Equity!$B:$B,MATCH($B$2&"#"&19,Equity!$P:$P,0)),"") | B34: =IFERROR(INDEX(Equity!$C:$C,MATCH($B$2&"#"&19,Equity!$P:$P,0)),"") | C34: =IFERROR(INDEX(Equity!$D:$D,MATCH($B$2&"#"&19,Equity!$P:$P,0)),"") | D34: =IFERROR(INDEX(Equity!$E:$E,MATCH($B$2&"#"&19,Equity!$P:$P,0)),"") | E34: =IFERROR(INDEX(Equity!$I:$I,MATCH($B$2&"#"&19,Equity!$P:$P,0)),"") | F34: =IFERROR(INDEX(Equity!$K:$K,MATCH($B$2&"#"&19,Equity!$P:$P,0)),"") | G34: =IFERROR(INDEX(Equity!$N:$N,MATCH($B$2&"#"&19,Equity!$P:$P,0)),"")
A35: =IFERROR(INDEX(Equity!$B:$B,MATCH($B$2&"#"&20,Equity!$P:$P,0)),"") | B35: =IFERROR(INDEX(Equity!$C:$C,MATCH($B$2&"#"&20,Equity!$P:$P,0)),"") | C35: =IFERROR(INDEX(Equity!$D:$D,MATCH($B$2&"#"&20,Equity!$P:$P,0)),"") | D35: =IFERROR(INDEX(Equity!$E:$E,MATCH($B$2&"#"&20,Equity!$P:$P,0)),"") | E35: =IFERROR(INDEX(Equity!$I:$I,MATCH($B$2&"#"&20,Equity!$P:$P,0)),"") | F35: =IFERROR(INDEX(Equity!$K:$K,MATCH($B$2&"#"&20,Equity!$P:$P,0)),"") | G35: =IFERROR(INDEX(Equity!$N:$N,MATCH($B$2&"#"&20,Equity!$P:$P,0)),"")
A36: =IFERROR(INDEX(Equity!$B:$B,MATCH($B$2&"#"&21,Equity!$P:$P,0)),"") | B36: =IFERROR(INDEX(Equity!$C:$C,MATCH($B$2&"#"&21,Equity!$P:$P,0)),"") | C36: =IFERROR(INDEX(Equity!$D:$D,MATCH($B$2&"#"&21,Equity!$P:$P,0)),"") | D36: =IFERROR(INDEX(Equity!$E:$E,MATCH($B$2&"#"&21,Equity!$P:$P,0)),"") | E36: =IFERROR(INDEX(Equity!$I:$I,MATCH($B$2&"#"&21,Equity!$P:$P,0)),"") | F36: =IFERROR(INDEX(Equity!$K:$K,MATCH($B$2&"#"&21,Equity!$P:$P,0)),"") | G36: =IFERROR(INDEX(Equity!$N:$N,MATCH($B$2&"#"&21,Equity!$P:$P,0)),"")
A37: =IFERROR(INDEX(Equity!$B:$B,MATCH($B$2&"#"&22,Equity!$P:$P,0)),"") | B37: =IFERROR(INDEX(Equity!$C:$C,MATCH($B$2&"#"&22,Equity!$P:$P,0)),"") | C37: =IFERROR(INDEX(Equity!$D:$D,MATCH($B$2&"#"&22,Equity!$P:$P,0)),"") | D37: =IFERROR(INDEX(Equity!$E:$E,MATCH($B$2&"#"&22,Equity!$P:$P,0)),"") | E37: =IFERROR(INDEX(Equity!$I:$I,MATCH($B$2&"#"&22,Equity!$P:$P,0)),"") | F37: =IFERROR(INDEX(Equity!$K:$K,MATCH($B$2&"#"&22,Equity!$P:$P,0)),"") | G37: =IFERROR(INDEX(Equity!$N:$N,MATCH($B$2&"#"&22,Equity!$P:$P,0)),"")
A38: =IFERROR(INDEX(Equity!$B:$B,MATCH($B$2&"#"&23,Equity!$P:$P,0)),"") | B38: =IFERROR(INDEX(Equity!$C:$C,MATCH($B$2&"#"&23,Equity!$P:$P,0)),"") | C38: =IFERROR(INDEX(Equity!$D:$D,MATCH($B$2&"#"&23,Equity!$P:$P,0)),"") | D38: =IFERROR(INDEX(Equity!$E:$E,MATCH($B$2&"#"&23,Equity!$P:$P,0)),"") | E38: =IFERROR(INDEX(Equity!$I:$I,MATCH($B$2&"#"&23,Equity!$P:$P,0)),"") | F38: =IFERROR(INDEX(Equity!$K:$K,MATCH($B$2&"#"&23,Equity!$P:$P,0)),"") | G38: =IFERROR(INDEX(Equity!$N:$N,MATCH($B$2&"#"&23,Equity!$P:$P,0)),"")
A39: =IFERROR(INDEX(Equity!$B:$B,MATCH($B$2&"#"&24,Equity!$P:$P,0)),"") | B39: =IFERROR(INDEX(Equity!$C:$C,MATCH($B$2&"#"&24,Equity!$P:$P,0)),"") | C39: =IFERROR(INDEX(Equity!$D:$D,MATCH($B$2&"#"&24,Equity!$P:$P,0)),"") | D39: =IFERROR(INDEX(Equity!$E:$E,MATCH($B$2&"#"&24,Equity!$P:$P,0)),"") | E39: =IFERROR(INDEX(Equity!$I:$I,MATCH($B$2&"#"&24,Equity!$P:$P,0)),"") | F39: =IFERROR(INDEX(Equity!$K:$K,MATCH($B$2&"#"&24,Equity!$P:$P,0)),"") | G39: =IFERROR(INDEX(Equity!$N:$N,MATCH($B$2&"#"&24,Equity!$P:$P,0)),"")
A40: =IFERROR(INDEX(Equity!$B:$B,MATCH($B$2&"#"&25,Equity!$P:$P,0)),"") | B40: =IFERROR(INDEX(Equity!$C:$C,MATCH($B$2&"#"&25,Equity!$P:$P,0)),"") | C40: =IFERROR(INDEX(Equity!$D:$D,MATCH($B$2&"#"&25,Equity!$P:$P,0)),"") | D40: =IFERROR(INDEX(Equity!$E:$E,MATCH($B$2&"#"&25,Equity!$P:$P,0)),"") | E40: =IFERROR(INDEX(Equity!$I:$I,MATCH($B$2&"#"&25,Equity!$P:$P,0)),"") | F40: =IFERROR(INDEX(Equity!$K:$K,MATCH($B$2&"#"&25,Equity!$P:$P,0)),"") | G40: =IFERROR(INDEX(Equity!$N:$N,MATCH($B$2&"#"&25,Equity!$P:$P,0)),"")
A41: =IFERROR(INDEX(Equity!$B:$B,MATCH($B$2&"#"&26,Equity!$P:$P,0)),"") | B41: =IFERROR(INDEX(Equity!$C:$C,MATCH($B$2&"#"&26,Equity!$P:$P,0)),"") | C41: =IFERROR(INDEX(Equity!$D:$D,MATCH($B$2&"#"&26,Equity!$P:$P,0)),"") | D41: =IFERROR(INDEX(Equity!$E:$E,MATCH($B$2&"#"&26,Equity!$P:$P,0)),"") | E41: =IFERROR(INDEX(Equity!$I:$I,MATCH($B$2&"#"&26,Equity!$P:$P,0)),"") | F41: =IFERROR(INDEX(Equity!$K:$K,MATCH($B$2&"#"&26,Equity!$P:$P,0)),"") | G41: =IFERROR(INDEX(Equity!$N:$N,MATCH($B$2&"#"&26,Equity!$P:$P,0)),"")
A42: =IFERROR(INDEX(Equity!$B:$B,MATCH($B$2&"#"&27,Equity!$P:$P,0)),"") | B42: =IFERROR(INDEX(Equity!$C:$C,MATCH($B$2&"#"&27,Equity!$P:$P,0)),"") | C42: =IFERROR(INDEX(Equity!$D:$D,MATCH($B$2&"#"&27,Equity!$P:$P,0)),"") | D42: =IFERROR(INDEX(Equity!$E:$E,MATCH($B$2&"#"&27,Equity!$P:$P,0)),"") | E42: =IFERROR(INDEX(Equity!$I:$I,MATCH($B$2&"#"&27,Equity!$P:$P,0)),"") | F42: =IFERROR(INDEX(Equity!$K:$K,MATCH($B$2&"#"&27,Equity!$P:$P,0)),"") | G42: =IFERROR(INDEX(Equity!$N:$N,MATCH($B$2&"#"&27,Equity!$P:$P,0)),"")
A43: =IFERROR(INDEX(Equity!$B:$B,MATCH($B$2&"#"&28,Equity!$P:$P,0)),"") | B43: =IFERROR(INDEX(Equity!$C:$C,MATCH($B$2&"#"&28,Equity!$P:$P,0)),"") | C43: =IFERROR(INDEX(Equity!$D:$D,MATCH($B$2&"#"&28,Equity!$P:$P,0)),"") | D43: =IFERROR(INDEX(Equity!$E:$E,MATCH($B$2&"#"&28,Equity!$P:$P,0)),"") | E43: =IFERROR(INDEX(Equity!$I:$I,MATCH($B$2&"#"&28,Equity!$P:$P,0)),"") | F43: =IFERROR(INDEX(Equity!$K:$K,MATCH($B$2&"#"&28,Equity!$P:$P,0)),"") | G43: =IFERROR(INDEX(Equity!$N:$N,MATCH($B$2&"#"&28,Equity!$P:$P,0)),"")
A44: =IFERROR(INDEX(Equity!$B:$B,MATCH($B$2&"#"&29,Equity!$P:$P,0)),"") | B44: =IFERROR(INDEX(Equity!$C:$C,MATCH($B$2&"#"&29,Equity!$P:$P,0)),"") | C44: =IFERROR(INDEX(Equity!$D:$D,MATCH($B$2&"#"&29,Equity!$P:$P,0)),"") | D44: =IFERROR(INDEX(Equity!$E:$E,MATCH($B$2&"#"&29,Equity!$P:$P,0)),"") | E44: =IFERROR(INDEX(Equity!$I:$I,MATCH($B$2&"#"&29,Equity!$P:$P,0)),"") | F44: =IFERROR(INDEX(Equity!$K:$K,MATCH($B$2&"#"&29,Equity!$P:$P,0)),"") | G44: =IFERROR(INDEX(Equity!$N:$N,MATCH($B$2&"#"&29,Equity!$P:$P,0)),"")
A45: =IFERROR(INDEX(Equity!$B:$B,MATCH($B$2&"#"&30,Equity!$P:$P,0)),"") | B45: =IFERROR(INDEX(Equity!$C:$C,MATCH($B$2&"#"&30,Equity!$P:$P,0)),"") | C45: =IFERROR(INDEX(Equity!$D:$D,MATCH($B$2&"#"&30,Equity!$P:$P,0)),"") | D45: =IFERROR(INDEX(Equity!$E:$E,MATCH($B$2&"#"&30,Equity!$P:$P,0)),"") | E45: =IFERROR(INDEX(Equity!$I:$I,MATCH($B$2&"#"&30,Equity!$P:$P,0)),"") | F45: =IFERROR(INDEX(Equity!$K:$K,MATCH($B$2&"#"&30,Equity!$P:$P,0)),"") | G45: =IFERROR(INDEX(Equity!$N:$N,MATCH($B$2&"#"&30,Equity!$P:$P,0)),"")
A46: =IFERROR(INDEX(Equity!$B:$B,MATCH($B$2&"#"&31,Equity!$P:$P,0)),"") | B46: =IFERROR(INDEX(Equity!$C:$C,MATCH($B$2&"#"&31,Equity!$P:$P,0)),"") | C46: =IFERROR(INDEX(Equity!$D:$D,MATCH($B$2&"#"&31,Equity!$P:$P,0)),"") | D46: =IFERROR(INDEX(Equity!$E:$E,MATCH($B$2&"#"&31,Equity!$P:$P,0)),"") | E46: =IFERROR(INDEX(Equity!$I:$I,MATCH($B$2&"#"&31,Equity!$P:$P,0)),"") | F46: =IFERROR(INDEX(Equity!$K:$K,MATCH($B$2&"#"&31,Equity!$P:$P,0)),"") | G46: =IFERROR(INDEX(Equity!$N:$N,MATCH($B$2&"#"&31,Equity!$P:$P,0)),"")
A47: =IFERROR(INDEX(Equity!$B:$B,MATCH($B$2&"#"&32,Equity!$P:$P,0)),"") | B47: =IFERROR(INDEX(Equity!$C:$C,MATCH($B$2&"#"&32,Equity!$P:$P,0)),"") | C47: =IFERROR(INDEX(Equity!$D:$D,MATCH($B$2&"#"&32,Equity!$P:$P,0)),"") | D47: =IFERROR(INDEX(Equity!$E:$E,MATCH($B$2&"#"&32,Equity!$P:$P,0)),"") | E47: =IFERROR(INDEX(Equity!$I:$I,MATCH($B$2&"#"&32,Equity!$P:$P,0)),"") | F47: =IFERROR(INDEX(Equity!$K:$K,MATCH($B$2&"#"&32,Equity!$P:$P,0)),"") | G47: =IFERROR(INDEX(Equity!$N:$N,MATCH($B$2&"#"&32,Equity!$P:$P,0)),"")
A48: =IFERROR(INDEX(Equity!$B:$B,MATCH($B$2&"#"&33,Equity!$P:$P,0)),"") | B48: =IFERROR(INDEX(Equity!$C:$C,MATCH($B$2&"#"&33,Equity!$P:$P,0)),"") | C48: =IFERROR(INDEX(Equity!$D:$D,MATCH($B$2&"#"&33,Equity!$P:$P,0)),"") | D48: =IFERROR(INDEX(Equity!$E:$E,MATCH($B$2&"#"&33,Equity!$P:$P,0)),"") | E48: =IFERROR(INDEX(Equity!$I:$I,MATCH($B$2&"#"&33,Equity!$P:$P,0)),"") | F48: =IFERROR(INDEX(Equity!$K:$K,MATCH($B$2&"#"&33,Equity!$P:$P,0)),"") | G48: =IFERROR(INDEX(Equity!$N:$N,MATCH($B$2&"#"&33,Equity!$P:$P,0)),"")
A49: =IFERROR(INDEX(Equity!$B:$B,MATCH($B$2&"#"&34,Equity!$P:$P,0)),"") | B49: =IFERROR(INDEX(Equity!$C:$C,MATCH($B$2&"#"&34,Equity!$P:$P,0)),"") | C49: =IFERROR(INDEX(Equity!$D:$D,MATCH($B$2&"#"&34,Equity!$P:$P,0)),"") | D49: =IFERROR(INDEX(Equity!$E:$E,MATCH($B$2&"#"&34,Equity!$P:$P,0)),"") | E49: =IFERROR(INDEX(Equity!$I:$I,MATCH($B$2&"#"&34,Equity!$P:$P,0)),"") | F49: =IFERROR(INDEX(Equity!$K:$K,MATCH($B$2&"#"&34,Equity!$P:$P,0)),"") | G49: =IFERROR(INDEX(Equity!$N:$N,MATCH($B$2&"#"&34,Equity!$P:$P,0)),"")
A50: =IFERROR(INDEX(Equity!$B:$B,MATCH($B$2&"#"&35,Equity!$P:$P,0)),"") | B50: =IFERROR(INDEX(Equity!$C:$C,MATCH($B$2&"#"&35,Equity!$P:$P,0)),"") | C50: =IFERROR(INDEX(Equity!$D:$D,MATCH($B$2&"#"&35,Equity!$P:$P,0)),"") | D50: =IFERROR(INDEX(Equity!$E:$E,MATCH($B$2&"#"&35,Equity!$P:$P,0)),"") | E50: =IFERROR(INDEX(Equity!$I:$I,MATCH($B$2&"#"&35,Equity!$P:$P,0)),"") | F50: =IFERROR(INDEX(Equity!$K:$K,MATCH($B$2&"#"&35,Equity!$P:$P,0)),"") | G50: =IFERROR(INDEX(Equity!$N:$N,MATCH($B$2&"#"&35,Equity!$P:$P,0)),"")
A51: =IFERROR(INDEX(Equity!$B:$B,MATCH($B$2&"#"&36,Equity!$P:$P,0)),"") | B51: =IFERROR(INDEX(Equity!$C:$C,MATCH($B$2&"#"&36,Equity!$P:$P,0)),"") | C51: =IFERROR(INDEX(Equity!$D:$D,MATCH($B$2&"#"&36,Equity!$P:$P,0)),"") | D51: =IFERROR(INDEX(Equity!$E:$E,MATCH($B$2&"#"&36,Equity!$P:$P,0)),"") | E51: =IFERROR(INDEX(Equity!$I:$I,MATCH($B$2&"#"&36,Equity!$P:$P,0)),"") | F51: =IFERROR(INDEX(Equity!$K:$K,MATCH($B$2&"#"&36,Equity!$P:$P,0)),"") | G51: =IFERROR(INDEX(Equity!$N:$N,MATCH($B$2&"#"&36,Equity!$P:$P,0)),"")
A52: =IFERROR(INDEX(Equity!$B:$B,MATCH($B$2&"#"&37,Equity!$P:$P,0)),"") | B52: =IFERROR(INDEX(Equity!$C:$C,MATCH($B$2&"#"&37,Equity!$P:$P,0)),"") | C52: =IFERROR(INDEX(Equity!$D:$D,MATCH($B$2&"#"&37,Equity!$P:$P,0)),"") | D52: =IFERROR(INDEX(Equity!$E:$E,MATCH($B$2&"#"&37,Equity!$P:$P,0)),"") | E52: =IFERROR(INDEX(Equity!$I:$I,MATCH($B$2&"#"&37,Equity!$P:$P,0)),"") | F52: =IFERROR(INDEX(Equity!$K:$K,MATCH($B$2&"#"&37,Equity!$P:$P,0)),"") | G52: =IFERROR(INDEX(Equity!$N:$N,MATCH($B$2&"#"&37,Equity!$P:$P,0)),"")
A53: =IFERROR(INDEX(Equity!$B:$B,MATCH($B$2&"#"&38,Equity!$P:$P,0)),"") | B53: =IFERROR(INDEX(Equity!$C:$C,MATCH($B$2&"#"&38,Equity!$P:$P,0)),"") | C53: =IFERROR(INDEX(Equity!$D:$D,MATCH($B$2&"#"&38,Equity!$P:$P,0)),"") | D53: =IFERROR(INDEX(Equity!$E:$E,MATCH($B$2&"#"&38,Equity!$P:$P,0)),"") | E53: =IFERROR(INDEX(Equity!$I:$I,MATCH($B$2&"#"&38,Equity!$P:$P,0)),"") | F53: =IFERROR(INDEX(Equity!$K:$K,MATCH($B$2&"#"&38,Equity!$P:$P,0)),"") | G53: =IFERROR(INDEX(Equity!$N:$N,MATCH($B$2&"#"&38,Equity!$P:$P,0)),"")
A54: =IFERROR(INDEX(Equity!$B:$B,MATCH($B$2&"#"&39,Equity!$P:$P,0)),"") | B54: =IFERROR(INDEX(Equity!$C:$C,MATCH($B$2&"#"&39,Equity!$P:$P,0)),"") | C54: =IFERROR(INDEX(Equity!$D:$D,MATCH($B$2&"#"&39,Equity!$P:$P,0)),"") | D54: =IFERROR(INDEX(Equity!$E:$E,MATCH($B$2&"#"&39,Equity!$P:$P,0)),"") | E54: =IFERROR(INDEX(Equity!$I:$I,MATCH($B$2&"#"&39,Equity!$P:$P,0)),"") | F54: =IFERROR(INDEX(Equity!$K:$K,MATCH($B$2&"#"&39,Equity!$P:$P,0)),"") | G54: =IFERROR(INDEX(Equity!$N:$N,MATCH($B$2&"#"&39,Equity!$P:$P,0)),"")
A55: =IFERROR(INDEX(Equity!$B:$B,MATCH($B$2&"#"&40,Equity!$P:$P,0)),"") | B55: =IFERROR(INDEX(Equity!$C:$C,MATCH($B$2&"#"&40,Equity!$P:$P,0)),"") | C55: =IFERROR(INDEX(Equity!$D:$D,MATCH($B$2&"#"&40,Equity!$P:$P,0)),"") | D55: =IFERROR(INDEX(Equity!$E:$E,MATCH($B$2&"#"&40,Equity!$P:$P,0)),"") | E55: =IFERROR(INDEX(Equity!$I:$I,MATCH($B$2&"#"&40,Equity!$P:$P,0)),"") | F55: =IFERROR(INDEX(Equity!$K:$K,MATCH($B$2&"#"&40,Equity!$P:$P,0)),"") | G55: =IFERROR(INDEX(Equity!$N:$N,MATCH($B$2&"#"&40,Equity!$P:$P,0)),"")
A57: MUTUAL FUNDS
A58: Fund House | B58: Scheme | C58: Units | D58: Cur NAV | E58: Cur. val | F58: Net chg. | G58: XIRR
A59: =IFERROR(INDEX(MutualFunds!$B:$B,MATCH($B$2&"#"&1,MutualFunds!$N:$N,0)),"") -> Parag Parikh Mutual Fund | B59: =IFERROR(INDEX(MutualFunds!$C:$C,MATCH($B$2&"#"&1,MutualFunds!$N:$N,0)),"") -> Parag Parikh Flexi Cap Fund - Direct Plan | C59: =IFERROR(INDEX(MutualFunds!$E:$E,MATCH($B$2&"#"&1,MutualFunds!$N:$N,0)),"") -> 720.17792 | D59: =IFERROR(INDEX(MutualFunds!$G:$G,MATCH($B$2&"#"&1,MutualFunds!$N:$N,0)),"") -> 91.2 | E59: =IFERROR(INDEX(MutualFunds!$I:$I,MATCH($B$2&"#"&1,MutualFunds!$N:$N,0)),"") -> 65680.226 | F59: =IFERROR(INDEX(MutualFunds!$J:$J,MATCH($B$2&"#"&1,MutualFunds!$N:$N,0)),"") -> 5680.2263 | G59: =IFERROR(INDEX(MutualFunds!$L:$L,MATCH($B$2&"#"&1,MutualFunds!$N:$N,0)),"") -> 0.36695
A60: =IFERROR(INDEX(MutualFunds!$B:$B,MATCH($B$2&"#"&2,MutualFunds!$N:$N,0)),"") | B60: =IFERROR(INDEX(MutualFunds!$C:$C,MATCH($B$2&"#"&2,MutualFunds!$N:$N,0)),"") | C60: =IFERROR(INDEX(MutualFunds!$E:$E,MATCH($B$2&"#"&2,MutualFunds!$N:$N,0)),"") | D60: =IFERROR(INDEX(MutualFunds!$G:$G,MATCH($B$2&"#"&2,MutualFunds!$N:$N,0)),"") | E60: =IFERROR(INDEX(MutualFunds!$I:$I,MATCH($B$2&"#"&2,MutualFunds!$N:$N,0)),"") | F60: =IFERROR(INDEX(MutualFunds!$J:$J,MATCH($B$2&"#"&2,MutualFunds!$N:$N,0)),"") | G60: =IFERROR(INDEX(MutualFunds!$L:$L,MATCH($B$2&"#"&2,MutualFunds!$N:$N,0)),"")
A61: =IFERROR(INDEX(MutualFunds!$B:$B,MATCH($B$2&"#"&3,MutualFunds!$N:$N,0)),"") | B61: =IFERROR(INDEX(MutualFunds!$C:$C,MATCH($B$2&"#"&3,MutualFunds!$N:$N,0)),"") | C61: =IFERROR(INDEX(MutualFunds!$E:$E,MATCH($B$2&"#"&3,MutualFunds!$N:$N,0)),"") | D61: =IFERROR(INDEX(MutualFunds!$G:$G,MATCH($B$2&"#"&3,MutualFunds!$N:$N,0)),"") | E61: =IFERROR(INDEX(MutualFunds!$I:$I,MATCH($B$2&"#"&3,MutualFunds!$N:$N,0)),"") | F61: =IFERROR(INDEX(MutualFunds!$J:$J,MATCH($B$2&"#"&3,MutualFunds!$N:$N,0)),"") | G61: =IFERROR(INDEX(MutualFunds!$L:$L,MATCH($B$2&"#"&3,MutualFunds!$N:$N,0)),"")
A62: =IFERROR(INDEX(MutualFunds!$B:$B,MATCH($B$2&"#"&4,MutualFunds!$N:$N,0)),"") | B62: =IFERROR(INDEX(MutualFunds!$C:$C,MATCH($B$2&"#"&4,MutualFunds!$N:$N,0)),"") | C62: =IFERROR(INDEX(MutualFunds!$E:$E,MATCH($B$2&"#"&4,MutualFunds!$N:$N,0)),"") | D62: =IFERROR(INDEX(MutualFunds!$G:$G,MATCH($B$2&"#"&4,MutualFunds!$N:$N,0)),"") | E62: =IFERROR(INDEX(MutualFunds!$I:$I,MATCH($B$2&"#"&4,MutualFunds!$N:$N,0)),"") | F62: =IFERROR(INDEX(MutualFunds!$J:$J,MATCH($B$2&"#"&4,MutualFunds!$N:$N,0)),"") | G62: =IFERROR(INDEX(MutualFunds!$L:$L,MATCH($B$2&"#"&4,MutualFunds!$N:$N,0)),"")
A63: =IFERROR(INDEX(MutualFunds!$B:$B,MATCH($B$2&"#"&5,MutualFunds!$N:$N,0)),"") | B63: =IFERROR(INDEX(MutualFunds!$C:$C,MATCH($B$2&"#"&5,MutualFunds!$N:$N,0)),"") | C63: =IFERROR(INDEX(MutualFunds!$E:$E,MATCH($B$2&"#"&5,MutualFunds!$N:$N,0)),"") | D63: =IFERROR(INDEX(MutualFunds!$G:$G,MATCH($B$2&"#"&5,MutualFunds!$N:$N,0)),"") | E63: =IFERROR(INDEX(MutualFunds!$I:$I,MATCH($B$2&"#"&5,MutualFunds!$N:$N,0)),"") | F63: =IFERROR(INDEX(MutualFunds!$J:$J,MATCH($B$2&"#"&5,MutualFunds!$N:$N,0)),"") | G63: =IFERROR(INDEX(MutualFunds!$L:$L,MATCH($B$2&"#"&5,MutualFunds!$N:$N,0)),"")
A64: =IFERROR(INDEX(MutualFunds!$B:$B,MATCH($B$2&"#"&6,MutualFunds!$N:$N,0)),"") | B64: =IFERROR(INDEX(MutualFunds!$C:$C,MATCH($B$2&"#"&6,MutualFunds!$N:$N,0)),"") | C64: =IFERROR(INDEX(MutualFunds!$E:$E,MATCH($B$2&"#"&6,MutualFunds!$N:$N,0)),"") | D64: =IFERROR(INDEX(MutualFunds!$G:$G,MATCH($B$2&"#"&6,MutualFunds!$N:$N,0)),"") | E64: =IFERROR(INDEX(MutualFunds!$I:$I,MATCH($B$2&"#"&6,MutualFunds!$N:$N,0)),"") | F64: =IFERROR(INDEX(MutualFunds!$J:$J,MATCH($B$2&"#"&6,MutualFunds!$N:$N,0)),"") | G64: =IFERROR(INDEX(MutualFunds!$L:$L,MATCH($B$2&"#"&6,MutualFunds!$N:$N,0)),"")
A65: =IFERROR(INDEX(MutualFunds!$B:$B,MATCH($B$2&"#"&7,MutualFunds!$N:$N,0)),"") | B65: =IFERROR(INDEX(MutualFunds!$C:$C,MATCH($B$2&"#"&7,MutualFunds!$N:$N,0)),"") | C65: =IFERROR(INDEX(MutualFunds!$E:$E,MATCH($B$2&"#"&7,MutualFunds!$N:$N,0)),"") | D65: =IFERROR(INDEX(MutualFunds!$G:$G,MATCH($B$2&"#"&7,MutualFunds!$N:$N,0)),"") | E65: =IFERROR(INDEX(MutualFunds!$I:$I,MATCH($B$2&"#"&7,MutualFunds!$N:$N,0)),"") | F65: =IFERROR(INDEX(MutualFunds!$J:$J,MATCH($B$2&"#"&7,MutualFunds!$N:$N,0)),"") | G65: =IFERROR(INDEX(MutualFunds!$L:$L,MATCH($B$2&"#"&7,MutualFunds!$N:$N,0)),"")
A66: =IFERROR(INDEX(MutualFunds!$B:$B,MATCH($B$2&"#"&8,MutualFunds!$N:$N,0)),"") | B66: =IFERROR(INDEX(MutualFunds!$C:$C,MATCH($B$2&"#"&8,MutualFunds!$N:$N,0)),"") | C66: =IFERROR(INDEX(MutualFunds!$E:$E,MATCH($B$2&"#"&8,MutualFunds!$N:$N,0)),"") | D66: =IFERROR(INDEX(MutualFunds!$G:$G,MATCH($B$2&"#"&8,MutualFunds!$N:$N,0)),"") | E66: =IFERROR(INDEX(MutualFunds!$I:$I,MATCH($B$2&"#"&8,MutualFunds!$N:$N,0)),"") | F66: =IFERROR(INDEX(MutualFunds!$J:$J,MATCH($B$2&"#"&8,MutualFunds!$N:$N,0)),"") | G66: =IFERROR(INDEX(MutualFunds!$L:$L,MATCH($B$2&"#"&8,MutualFunds!$N:$N,0)),"")
A67: =IFERROR(INDEX(MutualFunds!$B:$B,MATCH($B$2&"#"&9,MutualFunds!$N:$N,0)),"") | B67: =IFERROR(INDEX(MutualFunds!$C:$C,MATCH($B$2&"#"&9,MutualFunds!$N:$N,0)),"") | C67: =IFERROR(INDEX(MutualFunds!$E:$E,MATCH($B$2&"#"&9,MutualFunds!$N:$N,0)),"") | D67: =IFERROR(INDEX(MutualFunds!$G:$G,MATCH($B$2&"#"&9,MutualFunds!$N:$N,0)),"") | E67: =IFERROR(INDEX(MutualFunds!$I:$I,MATCH($B$2&"#"&9,MutualFunds!$N:$N,0)),"") | F67: =IFERROR(INDEX(MutualFunds!$J:$J,MATCH($B$2&"#"&9,MutualFunds!$N:$N,0)),"") | G67: =IFERROR(INDEX(MutualFunds!$L:$L,MATCH($B$2&"#"&9,MutualFunds!$N:$N,0)),"")
A68: =IFERROR(INDEX(MutualFunds!$B:$B,MATCH($B$2&"#"&10,MutualFunds!$N:$N,0)),"") | B68: =IFERROR(INDEX(MutualFunds!$C:$C,MATCH($B$2&"#"&10,MutualFunds!$N:$N,0)),"") | C68: =IFERROR(INDEX(MutualFunds!$E:$E,MATCH($B$2&"#"&10,MutualFunds!$N:$N,0)),"") | D68: =IFERROR(INDEX(MutualFunds!$G:$G,MATCH($B$2&"#"&10,MutualFunds!$N:$N,0)),"") | E68: =IFERROR(INDEX(MutualFunds!$I:$I,MATCH($B$2&"#"&10,MutualFunds!$N:$N,0)),"") | F68: =IFERROR(INDEX(MutualFunds!$J:$J,MATCH($B$2&"#"&10,MutualFunds!$N:$N,0)),"") | G68: =IFERROR(INDEX(MutualFunds!$L:$L,MATCH($B$2&"#"&10,MutualFunds!$N:$N,0)),"")
A69: =IFERROR(INDEX(MutualFunds!$B:$B,MATCH($B$2&"#"&11,MutualFunds!$N:$N,0)),"") | B69: =IFERROR(INDEX(MutualFunds!$C:$C,MATCH($B$2&"#"&11,MutualFunds!$N:$N,0)),"") | C69: =IFERROR(INDEX(MutualFunds!$E:$E,MATCH($B$2&"#"&11,MutualFunds!$N:$N,0)),"") | D69: =IFERROR(INDEX(MutualFunds!$G:$G,MATCH($B$2&"#"&11,MutualFunds!$N:$N,0)),"") | E69: =IFERROR(INDEX(MutualFunds!$I:$I,MATCH($B$2&"#"&11,MutualFunds!$N:$N,0)),"") | F69: =IFERROR(INDEX(MutualFunds!$J:$J,MATCH($B$2&"#"&11,MutualFunds!$N:$N,0)),"") | G69: =IFERROR(INDEX(MutualFunds!$L:$L,MATCH($B$2&"#"&11,MutualFunds!$N:$N,0)),"")
A70: =IFERROR(INDEX(MutualFunds!$B:$B,MATCH($B$2&"#"&12,MutualFunds!$N:$N,0)),"") | B70: =IFERROR(INDEX(MutualFunds!$C:$C,MATCH($B$2&"#"&12,MutualFunds!$N:$N,0)),"") | C70: =IFERROR(INDEX(MutualFunds!$E:$E,MATCH($B$2&"#"&12,MutualFunds!$N:$N,0)),"") | D70: =IFERROR(INDEX(MutualFunds!$G:$G,MATCH($B$2&"#"&12,MutualFunds!$N:$N,0)),"") | E70: =IFERROR(INDEX(MutualFunds!$I:$I,MATCH($B$2&"#"&12,MutualFunds!$N:$N,0)),"") | F70: =IFERROR(INDEX(MutualFunds!$J:$J,MATCH($B$2&"#"&12,MutualFunds!$N:$N,0)),"") | G70: =IFERROR(INDEX(MutualFunds!$L:$L,MATCH($B$2&"#"&12,MutualFunds!$N:$N,0)),"")
A71: =IFERROR(INDEX(MutualFunds!$B:$B,MATCH($B$2&"#"&13,MutualFunds!$N:$N,0)),"") | B71: =IFERROR(INDEX(MutualFunds!$C:$C,MATCH($B$2&"#"&13,MutualFunds!$N:$N,0)),"") | C71: =IFERROR(INDEX(MutualFunds!$E:$E,MATCH($B$2&"#"&13,MutualFunds!$N:$N,0)),"") | D71: =IFERROR(INDEX(MutualFunds!$G:$G,MATCH($B$2&"#"&13,MutualFunds!$N:$N,0)),"") | E71: =IFERROR(INDEX(MutualFunds!$I:$I,MATCH($B$2&"#"&13,MutualFunds!$N:$N,0)),"") | F71: =IFERROR(INDEX(MutualFunds!$J:$J,MATCH($B$2&"#"&13,MutualFunds!$N:$N,0)),"") | G71: =IFERROR(INDEX(MutualFunds!$L:$L,MATCH($B$2&"#"&13,MutualFunds!$N:$N,0)),"")
A72: =IFERROR(INDEX(MutualFunds!$B:$B,MATCH($B$2&"#"&14,MutualFunds!$N:$N,0)),"") | B72: =IFERROR(INDEX(MutualFunds!$C:$C,MATCH($B$2&"#"&14,MutualFunds!$N:$N,0)),"") | C72: =IFERROR(INDEX(MutualFunds!$E:$E,MATCH($B$2&"#"&14,MutualFunds!$N:$N,0)),"") | D72: =IFERROR(INDEX(MutualFunds!$G:$G,MATCH($B$2&"#"&14,MutualFunds!$N:$N,0)),"") | E72: =IFERROR(INDEX(MutualFunds!$I:$I,MATCH($B$2&"#"&14,MutualFunds!$N:$N,0)),"") | F72: =IFERROR(INDEX(MutualFunds!$J:$J,MATCH($B$2&"#"&14,MutualFunds!$N:$N,0)),"") | G72: =IFERROR(INDEX(MutualFunds!$L:$L,MATCH($B$2&"#"&14,MutualFunds!$N:$N,0)),"")
A73: =IFERROR(INDEX(MutualFunds!$B:$B,MATCH($B$2&"#"&15,MutualFunds!$N:$N,0)),"") | B73: =IFERROR(INDEX(MutualFunds!$C:$C,MATCH($B$2&"#"&15,MutualFunds!$N:$N,0)),"") | C73: =IFERROR(INDEX(MutualFunds!$E:$E,MATCH($B$2&"#"&15,MutualFunds!$N:$N,0)),"") | D73: =IFERROR(INDEX(MutualFunds!$G:$G,MATCH($B$2&"#"&15,MutualFunds!$N:$N,0)),"") | E73: =IFERROR(INDEX(MutualFunds!$I:$I,MATCH($B$2&"#"&15,MutualFunds!$N:$N,0)),"") | F73: =IFERROR(INDEX(MutualFunds!$J:$J,MATCH($B$2&"#"&15,MutualFunds!$N:$N,0)),"") | G73: =IFERROR(INDEX(MutualFunds!$L:$L,MATCH($B$2&"#"&15,MutualFunds!$N:$N,0)),"")
A74: =IFERROR(INDEX(MutualFunds!$B:$B,MATCH($B$2&"#"&16,MutualFunds!$N:$N,0)),"") | B74: =IFERROR(INDEX(MutualFunds!$C:$C,MATCH($B$2&"#"&16,MutualFunds!$N:$N,0)),"") | C74: =IFERROR(INDEX(MutualFunds!$E:$E,MATCH($B$2&"#"&16,MutualFunds!$N:$N,0)),"") | D74: =IFERROR(INDEX(MutualFunds!$G:$G,MATCH($B$2&"#"&16,MutualFunds!$N:$N,0)),"") | E74: =IFERROR(INDEX(MutualFunds!$I:$I,MATCH($B$2&"#"&16,MutualFunds!$N:$N,0)),"") | F74: =IFERROR(INDEX(MutualFunds!$J:$J,MATCH($B$2&"#"&16,MutualFunds!$N:$N,0)),"") | G74: =IFERROR(INDEX(MutualFunds!$L:$L,MATCH($B$2&"#"&16,MutualFunds!$N:$N,0)),"")
A75: =IFERROR(INDEX(MutualFunds!$B:$B,MATCH($B$2&"#"&17,MutualFunds!$N:$N,0)),"") | B75: =IFERROR(INDEX(MutualFunds!$C:$C,MATCH($B$2&"#"&17,MutualFunds!$N:$N,0)),"") | C75: =IFERROR(INDEX(MutualFunds!$E:$E,MATCH($B$2&"#"&17,MutualFunds!$N:$N,0)),"") | D75: =IFERROR(INDEX(MutualFunds!$G:$G,MATCH($B$2&"#"&17,MutualFunds!$N:$N,0)),"") | E75: =IFERROR(INDEX(MutualFunds!$I:$I,MATCH($B$2&"#"&17,MutualFunds!$N:$N,0)),"") | F75: =IFERROR(INDEX(MutualFunds!$J:$J,MATCH($B$2&"#"&17,MutualFunds!$N:$N,0)),"") | G75: =IFERROR(INDEX(MutualFunds!$L:$L,MATCH($B$2&"#"&17,MutualFunds!$N:$N,0)),"")
A76: =IFERROR(INDEX(MutualFunds!$B:$B,MATCH($B$2&"#"&18,MutualFunds!$N:$N,0)),"") | B76: =IFERROR(INDEX(MutualFunds!$C:$C,MATCH($B$2&"#"&18,MutualFunds!$N:$N,0)),"") | C76: =IFERROR(INDEX(MutualFunds!$E:$E,MATCH($B$2&"#"&18,MutualFunds!$N:$N,0)),"") | D76: =IFERROR(INDEX(MutualFunds!$G:$G,MATCH($B$2&"#"&18,MutualFunds!$N:$N,0)),"") | E76: =IFERROR(INDEX(MutualFunds!$I:$I,MATCH($B$2&"#"&18,MutualFunds!$N:$N,0)),"") | F76: =IFERROR(INDEX(MutualFunds!$J:$J,MATCH($B$2&"#"&18,MutualFunds!$N:$N,0)),"") | G76: =IFERROR(INDEX(MutualFunds!$L:$L,MATCH($B$2&"#"&18,MutualFunds!$N:$N,0)),"")
A77: =IFERROR(INDEX(MutualFunds!$B:$B,MATCH($B$2&"#"&19,MutualFunds!$N:$N,0)),"") | B77: =IFERROR(INDEX(MutualFunds!$C:$C,MATCH($B$2&"#"&19,MutualFunds!$N:$N,0)),"") | C77: =IFERROR(INDEX(MutualFunds!$E:$E,MATCH($B$2&"#"&19,MutualFunds!$N:$N,0)),"") | D77: =IFERROR(INDEX(MutualFunds!$G:$G,MATCH($B$2&"#"&19,MutualFunds!$N:$N,0)),"") | E77: =IFERROR(INDEX(MutualFunds!$I:$I,MATCH($B$2&"#"&19,MutualFunds!$N:$N,0)),"") | F77: =IFERROR(INDEX(MutualFunds!$J:$J,MATCH($B$2&"#"&19,MutualFunds!$N:$N,0)),"") | G77: =IFERROR(INDEX(MutualFunds!$L:$L,MATCH($B$2&"#"&19,MutualFunds!$N:$N,0)),"")
A78: =IFERROR(INDEX(MutualFunds!$B:$B,MATCH($B$2&"#"&20,MutualFunds!$N:$N,0)),"") | B78: =IFERROR(INDEX(MutualFunds!$C:$C,MATCH($B$2&"#"&20,MutualFunds!$N:$N,0)),"") | C78: =IFERROR(INDEX(MutualFunds!$E:$E,MATCH($B$2&"#"&20,MutualFunds!$N:$N,0)),"") | D78: =IFERROR(INDEX(MutualFunds!$G:$G,MATCH($B$2&"#"&20,MutualFunds!$N:$N,0)),"") | E78: =IFERROR(INDEX(MutualFunds!$I:$I,MATCH($B$2&"#"&20,MutualFunds!$N:$N,0)),"") | F78: =IFERROR(INDEX(MutualFunds!$J:$J,MATCH($B$2&"#"&20,MutualFunds!$N:$N,0)),"") | G78: =IFERROR(INDEX(MutualFunds!$L:$L,MATCH($B$2&"#"&20,MutualFunds!$N:$N,0)),"")
A80: FIXED DEPOSITS
A81: Bank | B81: Principal | C81: Rate % | D81: Maturity | E81: Value today
A82: =IFERROR(INDEX(FixedDeposits!$B:$B,MATCH($B$2&"#"&1,FixedDeposits!$L:$L,0)),"") -> HDFC Bank | B82: =IFERROR(INDEX(FixedDeposits!$D:$D,MATCH($B$2&"#"&1,FixedDeposits!$L:$L,0)),"") -> 500000 | C82: =IFERROR(INDEX(FixedDeposits!$E:$E,MATCH($B$2&"#"&1,FixedDeposits!$L:$L,0)),"") -> 7.1 | D82: =IFERROR(INDEX(FixedDeposits!$G:$G,MATCH($B$2&"#"&1,FixedDeposits!$L:$L,0)),"") -> 46478 | E82: =IFERROR(INDEX(FixedDeposits!$I:$I,MATCH($B$2&"#"&1,FixedDeposits!$L:$L,0)),"") -> 587277.98
A83: =IFERROR(INDEX(FixedDeposits!$B:$B,MATCH($B$2&"#"&2,FixedDeposits!$L:$L,0)),"") | B83: =IFERROR(INDEX(FixedDeposits!$D:$D,MATCH($B$2&"#"&2,FixedDeposits!$L:$L,0)),"") | C83: =IFERROR(INDEX(FixedDeposits!$E:$E,MATCH($B$2&"#"&2,FixedDeposits!$L:$L,0)),"") | D83: =IFERROR(INDEX(FixedDeposits!$G:$G,MATCH($B$2&"#"&2,FixedDeposits!$L:$L,0)),"") | E83: =IFERROR(INDEX(FixedDeposits!$I:$I,MATCH($B$2&"#"&2,FixedDeposits!$L:$L,0)),"")
A84: =IFERROR(INDEX(FixedDeposits!$B:$B,MATCH($B$2&"#"&3,FixedDeposits!$L:$L,0)),"") | B84: =IFERROR(INDEX(FixedDeposits!$D:$D,MATCH($B$2&"#"&3,FixedDeposits!$L:$L,0)),"") | C84: =IFERROR(INDEX(FixedDeposits!$E:$E,MATCH($B$2&"#"&3,FixedDeposits!$L:$L,0)),"") | D84: =IFERROR(INDEX(FixedDeposits!$G:$G,MATCH($B$2&"#"&3,FixedDeposits!$L:$L,0)),"") | E84: =IFERROR(INDEX(FixedDeposits!$I:$I,MATCH($B$2&"#"&3,FixedDeposits!$L:$L,0)),"")
A85: =IFERROR(INDEX(FixedDeposits!$B:$B,MATCH($B$2&"#"&4,FixedDeposits!$L:$L,0)),"") | B85: =IFERROR(INDEX(FixedDeposits!$D:$D,MATCH($B$2&"#"&4,FixedDeposits!$L:$L,0)),"") | C85: =IFERROR(INDEX(FixedDeposits!$E:$E,MATCH($B$2&"#"&4,FixedDeposits!$L:$L,0)),"") | D85: =IFERROR(INDEX(FixedDeposits!$G:$G,MATCH($B$2&"#"&4,FixedDeposits!$L:$L,0)),"") | E85: =IFERROR(INDEX(FixedDeposits!$I:$I,MATCH($B$2&"#"&4,FixedDeposits!$L:$L,0)),"")
A86: =IFERROR(INDEX(FixedDeposits!$B:$B,MATCH($B$2&"#"&5,FixedDeposits!$L:$L,0)),"") | B86: =IFERROR(INDEX(FixedDeposits!$D:$D,MATCH($B$2&"#"&5,FixedDeposits!$L:$L,0)),"") | C86: =IFERROR(INDEX(FixedDeposits!$E:$E,MATCH($B$2&"#"&5,FixedDeposits!$L:$L,0)),"") | D86: =IFERROR(INDEX(FixedDeposits!$G:$G,MATCH($B$2&"#"&5,FixedDeposits!$L:$L,0)),"") | E86: =IFERROR(INDEX(FixedDeposits!$I:$I,MATCH($B$2&"#"&5,FixedDeposits!$L:$L,0)),"")
A87: =IFERROR(INDEX(FixedDeposits!$B:$B,MATCH($B$2&"#"&6,FixedDeposits!$L:$L,0)),"") | B87: =IFERROR(INDEX(FixedDeposits!$D:$D,MATCH($B$2&"#"&6,FixedDeposits!$L:$L,0)),"") | C87: =IFERROR(INDEX(FixedDeposits!$E:$E,MATCH($B$2&"#"&6,FixedDeposits!$L:$L,0)),"") | D87: =IFERROR(INDEX(FixedDeposits!$G:$G,MATCH($B$2&"#"&6,FixedDeposits!$L:$L,0)),"") | E87: =IFERROR(INDEX(FixedDeposits!$I:$I,MATCH($B$2&"#"&6,FixedDeposits!$L:$L,0)),"")
A88: =IFERROR(INDEX(FixedDeposits!$B:$B,MATCH($B$2&"#"&7,FixedDeposits!$L:$L,0)),"") | B88: =IFERROR(INDEX(FixedDeposits!$D:$D,MATCH($B$2&"#"&7,FixedDeposits!$L:$L,0)),"") | C88: =IFERROR(INDEX(FixedDeposits!$E:$E,MATCH($B$2&"#"&7,FixedDeposits!$L:$L,0)),"") | D88: =IFERROR(INDEX(FixedDeposits!$G:$G,MATCH($B$2&"#"&7,FixedDeposits!$L:$L,0)),"") | E88: =IFERROR(INDEX(FixedDeposits!$I:$I,MATCH($B$2&"#"&7,FixedDeposits!$L:$L,0)),"")
A89: =IFERROR(INDEX(FixedDeposits!$B:$B,MATCH($B$2&"#"&8,FixedDeposits!$L:$L,0)),"") | B89: =IFERROR(INDEX(FixedDeposits!$D:$D,MATCH($B$2&"#"&8,FixedDeposits!$L:$L,0)),"") | C89: =IFERROR(INDEX(FixedDeposits!$E:$E,MATCH($B$2&"#"&8,FixedDeposits!$L:$L,0)),"") | D89: =IFERROR(INDEX(FixedDeposits!$G:$G,MATCH($B$2&"#"&8,FixedDeposits!$L:$L,0)),"") | E89: =IFERROR(INDEX(FixedDeposits!$I:$I,MATCH($B$2&"#"&8,FixedDeposits!$L:$L,0)),"")
A90: =IFERROR(INDEX(FixedDeposits!$B:$B,MATCH($B$2&"#"&9,FixedDeposits!$L:$L,0)),"") | B90: =IFERROR(INDEX(FixedDeposits!$D:$D,MATCH($B$2&"#"&9,FixedDeposits!$L:$L,0)),"") | C90: =IFERROR(INDEX(FixedDeposits!$E:$E,MATCH($B$2&"#"&9,FixedDeposits!$L:$L,0)),"") | D90: =IFERROR(INDEX(FixedDeposits!$G:$G,MATCH($B$2&"#"&9,FixedDeposits!$L:$L,0)),"") | E90: =IFERROR(INDEX(FixedDeposits!$I:$I,MATCH($B$2&"#"&9,FixedDeposits!$L:$L,0)),"")
A91: =IFERROR(INDEX(FixedDeposits!$B:$B,MATCH($B$2&"#"&10,FixedDeposits!$L:$L,0)),"") | B91: =IFERROR(INDEX(FixedDeposits!$D:$D,MATCH($B$2&"#"&10,FixedDeposits!$L:$L,0)),"") | C91: =IFERROR(INDEX(FixedDeposits!$E:$E,MATCH($B$2&"#"&10,FixedDeposits!$L:$L,0)),"") | D91: =IFERROR(INDEX(FixedDeposits!$G:$G,MATCH($B$2&"#"&10,FixedDeposits!$L:$L,0)),"") | E91: =IFERROR(INDEX(FixedDeposits!$I:$I,MATCH($B$2&"#"&10,FixedDeposits!$L:$L,0)),"")
A92: =IFERROR(INDEX(FixedDeposits!$B:$B,MATCH($B$2&"#"&11,FixedDeposits!$L:$L,0)),"") | B92: =IFERROR(INDEX(FixedDeposits!$D:$D,MATCH($B$2&"#"&11,FixedDeposits!$L:$L,0)),"") | C92: =IFERROR(INDEX(FixedDeposits!$E:$E,MATCH($B$2&"#"&11,FixedDeposits!$L:$L,0)),"") | D92: =IFERROR(INDEX(FixedDeposits!$G:$G,MATCH($B$2&"#"&11,FixedDeposits!$L:$L,0)),"") | E92: =IFERROR(INDEX(FixedDeposits!$I:$I,MATCH($B$2&"#"&11,FixedDeposits!$L:$L,0)),"")
A93: =IFERROR(INDEX(FixedDeposits!$B:$B,MATCH($B$2&"#"&12,FixedDeposits!$L:$L,0)),"") | B93: =IFERROR(INDEX(FixedDeposits!$D:$D,MATCH($B$2&"#"&12,FixedDeposits!$L:$L,0)),"") | C93: =IFERROR(INDEX(FixedDeposits!$E:$E,MATCH($B$2&"#"&12,FixedDeposits!$L:$L,0)),"") | D93: =IFERROR(INDEX(FixedDeposits!$G:$G,MATCH($B$2&"#"&12,FixedDeposits!$L:$L,0)),"") | E93: =IFERROR(INDEX(FixedDeposits!$I:$I,MATCH($B$2&"#"&12,FixedDeposits!$L:$L,0)),"")
A94: =IFERROR(INDEX(FixedDeposits!$B:$B,MATCH($B$2&"#"&13,FixedDeposits!$L:$L,0)),"") | B94: =IFERROR(INDEX(FixedDeposits!$D:$D,MATCH($B$2&"#"&13,FixedDeposits!$L:$L,0)),"") | C94: =IFERROR(INDEX(FixedDeposits!$E:$E,MATCH($B$2&"#"&13,FixedDeposits!$L:$L,0)),"") | D94: =IFERROR(INDEX(FixedDeposits!$G:$G,MATCH($B$2&"#"&13,FixedDeposits!$L:$L,0)),"") | E94: =IFERROR(INDEX(FixedDeposits!$I:$I,MATCH($B$2&"#"&13,FixedDeposits!$L:$L,0)),"")
A95: =IFERROR(INDEX(FixedDeposits!$B:$B,MATCH($B$2&"#"&14,FixedDeposits!$L:$L,0)),"") | B95: =IFERROR(INDEX(FixedDeposits!$D:$D,MATCH($B$2&"#"&14,FixedDeposits!$L:$L,0)),"") | C95: =IFERROR(INDEX(FixedDeposits!$E:$E,MATCH($B$2&"#"&14,FixedDeposits!$L:$L,0)),"") | D95: =IFERROR(INDEX(FixedDeposits!$G:$G,MATCH($B$2&"#"&14,FixedDeposits!$L:$L,0)),"") | E95: =IFERROR(INDEX(FixedDeposits!$I:$I,MATCH($B$2&"#"&14,FixedDeposits!$L:$L,0)),"")
A96: =IFERROR(INDEX(FixedDeposits!$B:$B,MATCH($B$2&"#"&15,FixedDeposits!$L:$L,0)),"") | B96: =IFERROR(INDEX(FixedDeposits!$D:$D,MATCH($B$2&"#"&15,FixedDeposits!$L:$L,0)),"") | C96: =IFERROR(INDEX(FixedDeposits!$E:$E,MATCH($B$2&"#"&15,FixedDeposits!$L:$L,0)),"") | D96: =IFERROR(INDEX(FixedDeposits!$G:$G,MATCH($B$2&"#"&15,FixedDeposits!$L:$L,0)),"") | E96: =IFERROR(INDEX(FixedDeposits!$I:$I,MATCH($B$2&"#"&15,FixedDeposits!$L:$L,0)),"")
A98: PPF
A99: Institution | B99: Balance | C99: As-on
A100: =IFERROR(INDEX(PPF!$B:$B,MATCH($B$2&"#"&1,PPF!$I:$I,0)),"") -> SBI | B100: =IFERROR(INDEX(PPF!$D:$D,MATCH($B$2&"#"&1,PPF!$I:$I,0)),"") -> 425000 | C100: =IFERROR(INDEX(PPF!$E:$E,MATCH($B$2&"#"&1,PPF!$I:$I,0)),"") -> 46112
A101: =IFERROR(INDEX(PPF!$B:$B,MATCH($B$2&"#"&2,PPF!$I:$I,0)),"") | B101: =IFERROR(INDEX(PPF!$D:$D,MATCH($B$2&"#"&2,PPF!$I:$I,0)),"") | C101: =IFERROR(INDEX(PPF!$E:$E,MATCH($B$2&"#"&2,PPF!$I:$I,0)),"")
A102: =IFERROR(INDEX(PPF!$B:$B,MATCH($B$2&"#"&3,PPF!$I:$I,0)),"") | B102: =IFERROR(INDEX(PPF!$D:$D,MATCH($B$2&"#"&3,PPF!$I:$I,0)),"") | C102: =IFERROR(INDEX(PPF!$E:$E,MATCH($B$2&"#"&3,PPF!$I:$I,0)),"")
A103: =IFERROR(INDEX(PPF!$B:$B,MATCH($B$2&"#"&4,PPF!$I:$I,0)),"") | B103: =IFERROR(INDEX(PPF!$D:$D,MATCH($B$2&"#"&4,PPF!$I:$I,0)),"") | C103: =IFERROR(INDEX(PPF!$E:$E,MATCH($B$2&"#"&4,PPF!$I:$I,0)),"")
A104: =IFERROR(INDEX(PPF!$B:$B,MATCH($B$2&"#"&5,PPF!$I:$I,0)),"") | B104: =IFERROR(INDEX(PPF!$D:$D,MATCH($B$2&"#"&5,PPF!$I:$I,0)),"") | C104: =IFERROR(INDEX(PPF!$E:$E,MATCH($B$2&"#"&5,PPF!$I:$I,0)),"")
A105: =IFERROR(INDEX(PPF!$B:$B,MATCH($B$2&"#"&6,PPF!$I:$I,0)),"") | B105: =IFERROR(INDEX(PPF!$D:$D,MATCH($B$2&"#"&6,PPF!$I:$I,0)),"") | C105: =IFERROR(INDEX(PPF!$E:$E,MATCH($B$2&"#"&6,PPF!$I:$I,0)),"")
A106: =IFERROR(INDEX(PPF!$B:$B,MATCH($B$2&"#"&7,PPF!$I:$I,0)),"") | B106: =IFERROR(INDEX(PPF!$D:$D,MATCH($B$2&"#"&7,PPF!$I:$I,0)),"") | C106: =IFERROR(INDEX(PPF!$E:$E,MATCH($B$2&"#"&7,PPF!$I:$I,0)),"")
...

Sheet Priya
A1: Priya — PORTFOLIO
A2: Owner | B2: Priya
A3: Net worth | B3: =B11 -> 1254684
A5: Asset class | B5: Value | C5: # holdings
A6: Equity | B6: =SUMIFS(Equity!$I:$I,Equity!$A:$A,$B$2) -> 222950 | C6: =COUNTIF(Equity!$A:$A,$B$2) -> 3
A7: Mutual Funds | B7: =SUMIFS(MutualFunds!$I:$I,MutualFunds!$A:$A,$B$2) -> 171733.97 | C7: =COUNTIF(MutualFunds!$A:$A,$B$2) -> 1
A8: Fixed Deposits | B8: =SUMIFS(FixedDeposits!$I:$I,FixedDeposits!$A:$A,$B$2) -> 0 | C8: =COUNTIF(FixedDeposits!$A:$A,$B$2) -> 0
A9: PPF | B9: =SUMIFS(PPF!$D:$D,PPF!$A:$A,$B$2) -> 860000 | C9: =COUNTIF(PPF!$A:$A,$B$2) -> 1
A10: Bonds | B10: =SUMIFS(Bonds!$K:$K,Bonds!$A:$A,$B$2) -> 0 | C10: =COUNTIF(Bonds!$A:$A,$B$2) -> 0
A11: Total | B11: =SUM(B6:B10) -> 1254684 | C11: =SUM(C6:C10) -> 5
A14: EQUITY
A15: ISIN | B15: Scrip | C15: Qty | D15: Avg cost | E15: Cur. val | F15: Net chg. | G15: XIRR
A16: =IFERROR(INDEX(Equity!$B:$B,MATCH($B$2&"#"&1,Equity!$P:$P,0)),"") -> INE154A01025 | B16: =IFERROR(INDEX(Equity!$C:$C,MATCH($B$2&"#"&1,Equity!$P:$P,0)),"") -> ITC LIMITED EQ | C16: =IFERROR(INDEX(Equity!$D:$D,MATCH($B$2&"#"&1,Equity!$P:$P,0)),"") -> 200 | D16: =IFERROR(INDEX(Equity!$E:$E,MATCH($B$2&"#"&1,Equity!$P:$P,0)),"") -> 282.6 | E16: =IFERROR(INDEX(Equity!$I:$I,MATCH($B$2&"#"&1,Equity!$P:$P,0)),"") -> 87000 | F16: =IFERROR(INDEX(Equity!$K:$K,MATCH($B$2&"#"&1,Equity!$P:$P,0)),"") -> 30480 | G16: =IFERROR(INDEX(Equity!$N:$N,MATCH($B$2&"#"&1,Equity!$P:$P,0)),"") -> 0.05233771
A17: =IFERROR(INDEX(Equity!$B:$B,MATCH($B$2&"#"&2,Equity!$P:$P,0)),"") -> INE090A01021 | B17: =IFERROR(INDEX(Equity!$C:$C,MATCH($B$2&"#"&2,Equity!$P:$P,0)),"") -> ICICI BANK LIMITED EQ | C17: =IFERROR(INDEX(Equity!$D:$D,MATCH($B$2&"#"&2,Equity!$P:$P,0)),"") -> 80 | D17: =IFERROR(INDEX(Equity!$E:$E,MATCH($B$2&"#"&2,Equity!$P:$P,0)),"") -> 365 | E17: =IFERROR(INDEX(Equity!$I:$I,MATCH($B$2&"#"&2,Equity!$P:$P,0)),"") -> 99200 | F17: =IFERROR(INDEX(Equity!$K:$K,MATCH($B$2&"#"&2,Equity!$P:$P,0)),"") -> 70000 | G17: =IFERROR(INDEX(Equity!$N:$N,MATCH($B$2&"#"&2,Equity!$P:$P,0)),"") -> 0.15563274
A18: =IFERROR(INDEX(Equity!$B:$B,MATCH($B$2&"#"&3,Equity!$P:$P,0)),"") -> INE075A01022 | B18: =IFERROR(INDEX(Equity!$C:$C,MATCH($B$2&"#"&3,Equity!$P:$P,0)),"") -> WIPRO LIMITED EQ | C18: =IFERROR(INDEX(Equity!$D:$D,MATCH($B$2&"#"&3,Equity!$P:$P,0)),"") -> 150 | D18: =IFERROR(INDEX(Equity!$E:$E,MATCH($B$2&"#"&3,Equity!$P:$P,0)),"") -> 317 | E18: =IFERROR(INDEX(Equity!$I:$I,MATCH($B$2&"#"&3,Equity!$P:$P,0)),"") -> 36750 | F18: =IFERROR(INDEX(Equity!$K:$K,MATCH($B$2&"#"&3,Equity!$P:$P,0)),"") -> -10800 | G18: =IFERROR(INDEX(Equity!$N:$N,MATCH($B$2&"#"&3,Equity!$P:$P,0)),"") -> -0.030013449
A19: =IFERROR(INDEX(Equity!$B:$B,MATCH($B$2&"#"&4,Equity!$P:$P,0)),"") | B19: =IFERROR(INDEX(Equity!$C:$C,MATCH($B$2&"#"&4,Equity!$P:$P,0)),"") | C19: =IFERROR(INDEX(Equity!$D:$D,MATCH($B$2&"#"&4,Equity!$P:$P,0)),"") | D19: =IFERROR(INDEX(Equity!$E:$E,MATCH($B$2&"#"&4,Equity!$P:$P,0)),"") | E19: =IFERROR(INDEX(Equity!$I:$I,MATCH($B$2&"#"&4,Equity!$P:$P,0)),"") | F19: =IFERROR(INDEX(Equity!$K:$K,MATCH($B$2&"#"&4,Equity!$P:$P,0)),"") | G19: =IFERROR(INDEX(Equity!$N:$N,MATCH($B$2&"#"&4,Equity!$P:$P,0)),"")
A20: =IFERROR(INDEX(Equity!$B:$B,MATCH($B$2&"#"&5,Equity!$P:$P,0)),"") | B20: =IFERROR(INDEX(Equity!$C:$C,MATCH($B$2&"#"&5,Equity!$P:$P,0)),"") | C20: =IFERROR(INDEX(Equity!$D:$D,MATCH($B$2&"#"&5,Equity!$P:$P,0)),"") | D20: =IFERROR(INDEX(Equity!$E:$E,MATCH($B$2&"#"&5,Equity!$P:$P,0)),"") | E20: =IFERROR(INDEX(Equity!$I:$I,MATCH($B$2&"#"&5,Equity!$P:$P,0)),"") | F20: =IFERROR(INDEX(Equity!$K:$K,MATCH($B$2&"#"&5,Equity!$P:$P,0)),"") | G20: =IFERROR(INDEX(Equity!$N:$N,MATCH($B$2&"#"&5,Equity!$P:$P,0)),"")
A21: =IFERROR(INDEX(Equity!$B:$B,MATCH($B$2&"#"&6,Equity!$P:$P,0)),"") | B21: =IFERROR(INDEX(Equity!$C:$C,MATCH($B$2&"#"&6,Equity!$P:$P,0)),"") | C21: =IFERROR(INDEX(Equity!$D:$D,MATCH($B$2&"#"&6,Equity!$P:$P,0)),"") | D21: =IFERROR(INDEX(Equity!$E:$E,MATCH($B$2&"#"&6,Equity!$P:$P,0)),"") | E21: =IFERROR(INDEX(Equity!$I:$I,MATCH($B$2&"#"&6,Equity!$P:$P,0)),"") | F21: =IFERROR(INDEX(Equity!$K:$K,MATCH($B$2&"#"&6,Equity!$P:$P,0)),"") | G21: =IFERROR(INDEX(Equity!$N:$N,MATCH($B$2&"#"&6,Equity!$P:$P,0)),"")
A22: =IFERROR(INDEX(Equity!$B:$B,MATCH($B$2&"#"&7,Equity!$P:$P,0)),"") | B22: =IFERROR(INDEX(Equity!$C:$C,MATCH($B$2&"#"&7,Equity!$P:$P,0)),"") | C22: =IFERROR(INDEX(Equity!$D:$D,MATCH($B$2&"#"&7,Equity!$P:$P,0)),"") | D22: =IFERROR(INDEX(Equity!$E:$E,MATCH($B$2&"#"&7,Equity!$P:$P,0)),"") | E22: =IFERROR(INDEX(Equity!$I:$I,MATCH($B$2&"#"&7,Equity!$P:$P,0)),"") | F22: =IFERROR(INDEX(Equity!$K:$K,MATCH($B$2&"#"&7,Equity!$P:$P,0)),"") | G22: =IFERROR(INDEX(Equity!$N:$N,MATCH($B$2&"#"&7,Equity!$P:$P,0)),"")
A23: =IFERROR(INDEX(Equity!$B:$B,MATCH($B$2&"#"&8,Equity!$P:$P,0)),"") | B23: =IFERROR(INDEX(Equity!$C:$C,MATCH($B$2&"#"&8,Equity!$P:$P,0)),"") | C23: =IFERROR(INDEX(Equity!$D:$D,MATCH($B$2&"#"&8,Equity!$P:$P,0)),"") | D23: =IFERROR(INDEX(Equity!$E:$E,MATCH($B$2&"#"&8,Equity!$P:$P,0)),"") | E23: =IFERROR(INDEX(Equity!$I:$I,MATCH($B$2&"#"&8,Equity!$P:$P,0)),"") | F23: =IFERROR(INDEX(Equity!$K:$K,MATCH($B$2&"#"&8,Equity!$P:$P,0)),"") | G23: =IFERROR(INDEX(Equity!$N:$N,MATCH($B$2&"#"&8,Equity!$P:$P,0)),"")
A24: =IFERROR(INDEX(Equity!$B:$B,MATCH($B$2&"#"&9,Equity!$P:$P,0)),"") | B24: =IFERROR(INDEX(Equity!$C:$C,MATCH($B$2&"#"&9,Equity!$P:$P,0)),"") | C24: =IFERROR(INDEX(Equity!$D:$D,MATCH($B$2&"#"&9,Equity!$P:$P,0)),"") | D24: =IFERROR(INDEX(Equity!$E:$E,MATCH($B$2&"#"&9,Equity!$P:$P,0)),"") | E24: =IFERROR(INDEX(Equity!$I:$I,MATCH($B$2&"#"&9,Equity!$P:$P,0)),"") | F24: =IFERROR(INDEX(Equity!$K:$K,MATCH($B$2&"#"&9,Equity!$P:$P,0)),"") | G24: =IFERROR(INDEX(Equity!$N:$N,MATCH($B$2&"#"&9,Equity!$P:$P,0)),"")
A25: =IFERROR(INDEX(Equity!$B:$B,MATCH($B$2&"#"&10,Equity!$P:$P,0)),"") | B25: =IFERROR(INDEX(Equity!$C:$C,MATCH($B$2&"#"&10,Equity!$P:$P,0)),"") | C25: =IFERROR(INDEX(Equity!$D:$D,MATCH($B$2&"#"&10,Equity!$P:$P,0)),"") | D25: =IFERROR(INDEX(Equity!$E:$E,MATCH($B$2&"#"&10,Equity!$P:$P,0)),"") | E25: =IFERROR(INDEX(Equity!$I:$I,MATCH($B$2&"#"&10,Equity!$P:$P,0)),"") | F25: =IFERROR(INDEX(Equity!$K:$K,MATCH($B$2&"#"&10,Equity!$P:$P,0)),"") | G25: =IFERROR(INDEX(Equity!$N:$N,MATCH($B$2&"#"&10,Equity!$P:$P,0)),"")
A26: =IFERROR(INDEX(Equity!$B:$B,MATCH($B$2&"#"&11,Equity!$P:$P,0)),"") | B26: =IFERROR(INDEX(Equity!$C:$C,MATCH($B$2&"#"&11,Equity!$P:$P,0)),"") | C26: =IFERROR(INDEX(Equity!$D:$D,MATCH($B$2&"#"&11,Equity!$P:$P,0)),"") | D26: =IFERROR(INDEX(Equity!$E:$E,MATCH($B$2&"#"&11,Equity!$P:$P,0)),"") | E26: =IFERROR(INDEX(Equity!$I:$I,MATCH($B$2&"#"&11,Equity!$P:$P,0)),"") | F26: =IFERROR(INDEX(Equity!$K:$K,MATCH($B$2&"#"&11,Equity!$P:$P,0)),"") | G26: =IFERROR(INDEX(Equity!$N:$N,MATCH($B$2&"#"&11,Equity!$P:$P,0)),"")
A27: =IFERROR(INDEX(Equity!$B:$B,MATCH($B$2&"#"&12,Equity!$P:$P,0)),"") | B27: =IFERROR(INDEX(Equity!$C:$C,MATCH($B$2&"#"&12,Equity!$P:$P,0)),"") | C27: =IFERROR(INDEX(Equity!$D:$D,MATCH($B$2&"#"&12,Equity!$P:$P,0)),"") | D27: =IFERROR(INDEX(Equity!$E:$E,MATCH($B$2&"#"&12,Equity!$P:$P,0)),"") | E27: =IFERROR(INDEX(Equity!$I:$I,MATCH($B$2&"#"&12,Equity!$P:$P,0)),"") | F27: =IFERROR(INDEX(Equity!$K:$K,MATCH($B$2&"#"&12,Equity!$P:$P,0)),"") | G27: =IFERROR(INDEX(Equity!$N:$N,MATCH($B$2&"#"&12,Equity!$P:$P,0)),"")
A28: =IFERROR(INDEX(Equity!$B:$B,MATCH($B$2&"#"&13,Equity!$P:$P,0)),"") | B28: =IFERROR(INDEX(Equity!$C:$C,MATCH($B$2&"#"&13,Equity!$P:$P,0)),"") | C28: =IFERROR(INDEX(Equity!$D:$D,MATCH($B$2&"#"&13,Equity!$P:$P,0)),"") | D28: =IFERROR(INDEX(Equity!$E:$E,MATCH($B$2&"#"&13,Equity!$P:$P,0)),"") | E28: =IFERROR(INDEX(Equity!$I:$I,MATCH($B$2&"#"&13,Equity!$P:$P,0)),"") | F28: =IFERROR(INDEX(Equity!$K:$K,MATCH($B$2&"#"&13,Equity!$P:$P,0)),"") | G28: =IFERROR(INDEX(Equity!$N:$N,MATCH($B$2&"#"&13,Equity!$P:$P,0)),"")
A29: =IFERROR(INDEX(Equity!$B:$B,MATCH($B$2&"#"&14,Equity!$P:$P,0)),"") | B29: =IFERROR(INDEX(Equity!$C:$C,MATCH($B$2&"#"&14,Equity!$P:$P,0)),"") | C29: =IFERROR(INDEX(Equity!$D:$D,MATCH($B$2&"#"&14,Equity!$P:$P,0)),"") | D29: =IFERROR(INDEX(Equity!$E:$E,MATCH($B$2&"#"&14,Equity!$P:$P,0)),"") | E29: =IFERROR(INDEX(Equity!$I:$I,MATCH($B$2&"#"&14,Equity!$P:$P,0)),"") | F29: =IFERROR(INDEX(Equity!$K:$K,MATCH($B$2&"#"&14,Equity!$P:$P,0)),"") | G29: =IFERROR(INDEX(Equity!$N:$N,MATCH($B$2&"#"&14,Equity!$P:$P,0)),"")
A30: =IFERROR(INDEX(Equity!$B:$B,MATCH($B$2&"#"&15,Equity!$P:$P,0)),"") | B30: =IFERROR(INDEX(Equity!$C:$C,MATCH($B$2&"#"&15,Equity!$P:$P,0)),"") | C30: =IFERROR(INDEX(Equity!$D:$D,MATCH($B$2&"#"&15,Equity!$P:$P,0)),"") | D30: =IFERROR(INDEX(Equity!$E:$E,MATCH($B$2&"#"&15,Equity!$P:$P,0)),"") | E30: =IFERROR(INDEX(Equity!$I:$I,MATCH($B$2&"#"&15,Equity!$P:$P,0)),"") | F30: =IFERROR(INDEX(Equity!$K:$K,MATCH($B$2&"#"&15,Equity!$P:$P,0)),"") | G30: =IFERROR(INDEX(Equity!$N:$N,MATCH($B$2&"#"&15,Equity!$P:$P,0)),"")
A31: =IFERROR(INDEX(Equity!$B:$B,MATCH($B$2&"#"&16,Equity!$P:$P,0)),"") | B31: =IFERROR(INDEX(Equity!$C:$C,MATCH($B$2&"#"&16,Equity!$P:$P,0)),"") | C31: =IFERROR(INDEX(Equity!$D:$D,MATCH($B$2&"#"&16,Equity!$P:$P,0)),"") | D31: =IFERROR(INDEX(Equity!$E:$E,MATCH($B$2&"#"&16,Equity!$P:$P,0)),"") | E31: =IFERROR(INDEX(Equity!$I:$I,MATCH($B$2&"#"&16,Equity!$P:$P,0)),"") | F31: =IFERROR(INDEX(Equity!$K:$K,MATCH($B$2&"#"&16,Equity!$P:$P,0)),"") | G31: =IFERROR(INDEX(Equity!$N:$N,MATCH($B$2&"#"&16,Equity!$P:$P,0)),"")
A32: =IFERROR(INDEX(Equity!$B:$B,MATCH($B$2&"#"&17,Equity!$P:$P,0)),"") | B32: =IFERROR(INDEX(Equity!$C:$C,MATCH($B$2&"#"&17,Equity!$P:$P,0)),"") | C32: =IFERROR(INDEX(Equity!$D:$D,MATCH($B$2&"#"&17,Equity!$P:$P,0)),"") | D32: =IFERROR(INDEX(Equity!$E:$E,MATCH($B$2&"#"&17,Equity!$P:$P,0)),"") | E32: =IFERROR(INDEX(Equity!$I:$I,MATCH($B$2&"#"&17,Equity!$P:$P,0)),"") | F32: =IFERROR(INDEX(Equity!$K:$K,MATCH($B$2&"#"&17,Equity!$P:$P,0)),"") | G32: =IFERROR(INDEX(Equity!$N:$N,MATCH($B$2&"#"&17,Equity!$P:$P,0)),"")
A33: =IFERROR(INDEX(Equity!$B:$B,MATCH($B$2&"#"&18,Equity!$P:$P,0)),"") | B33: =IFERROR(INDEX(Equity!$C:$C,MATCH($B$2&"#"&18,Equity!$P:$P,0)),"") | C33: =IFERROR(INDEX(Equity!$D:$D,MATCH($B$2&"#"&18,Equity!$P:$P,0)),"") | D33: =IFERROR(INDEX(Equity!$E:$E,MATCH($B$2&"#"&18,Equity!$P:$P,0)),"") | E33: =IFERROR(INDEX(Equity!$I:$I,MATCH($B$2&"#"&18,Equity!$P:$P,0)),"") | F33: =IFERROR(INDEX(Equity!$K:$K,MATCH($B$2&"#"&18,Equity!$P:$P,0)),"") | G33: =IFERROR(INDEX(Equity!$N:$N,MATCH($B$2&"#"&18,Equity!$P:$P,0)),"")
A34: =IFERROR(INDEX(Equity!$B:$B,MATCH($B$2&"#"&19,Equity!$P:$P,0)),"") | B34: =IFERROR(INDEX(Equity!$C:$C,MATCH($B$2&"#"&19,Equity!$P:$P,0)),"") | C34: =IFERROR(INDEX(Equity!$D:$D,MATCH($B$2&"#"&19,Equity!$P:$P,0)),"") | D34: =IFERROR(INDEX(Equity!$E:$E,MATCH($B$2&"#"&19,Equity!$P:$P,0)),"") | E34: =IFERROR(INDEX(Equity!$I:$I,MATCH($B$2&"#"&19,Equity!$P:$P,0)),"") | F34: =IFERROR(INDEX(Equity!$K:$K,MATCH($B$2&"#"&19,Equity!$P:$P,0)),"") | G34: =IFERROR(INDEX(Equity!$N:$N,MATCH($B$2&"#"&19,Equity!$P:$P,0)),"")
A35: =IFERROR(INDEX(Equity!$B:$B,MATCH($B$2&"#"&20,Equity!$P:$P,0)),"") | B35: =IFERROR(INDEX(Equity!$C:$C,MATCH($B$2&"#"&20,Equity!$P:$P,0)),"") | C35: =IFERROR(INDEX(Equity!$D:$D,MATCH($B$2&"#"&20,Equity!$P:$P,0)),"") | D35: =IFERROR(INDEX(Equity!$E:$E,MATCH($B$2&"#"&20,Equity!$P:$P,0)),"") | E35: =IFERROR(INDEX(Equity!$I:$I,MATCH($B$2&"#"&20,Equity!$P:$P,0)),"") | F35: =IFERROR(INDEX(Equity!$K:$K,MATCH($B$2&"#"&20,Equity!$P:$P,0)),"") | G35: =IFERROR(INDEX(Equity!$N:$N,MATCH($B$2&"#"&20,Equity!$P:$P,0)),"")
A36: =IFERROR(INDEX(Equity!$B:$B,MATCH($B$2&"#"&21,Equity!$P:$P,0)),"") | B36: =IFERROR(INDEX(Equity!$C:$C,MATCH($B$2&"#"&21,Equity!$P:$P,0)),"") | C36: =IFERROR(INDEX(Equity!$D:$D,MATCH($B$2&"#"&21,Equity!$P:$P,0)),"") | D36: =IFERROR(INDEX(Equity!$E:$E,MATCH($B$2&"#"&21,Equity!$P:$P,0)),"") | E36: =IFERROR(INDEX(Equity!$I:$I,MATCH($B$2&"#"&21,Equity!$P:$P,0)),"") | F36: =IFERROR(INDEX(Equity!$K:$K,MATCH($B$2&"#"&21,Equity!$P:$P,0)),"") | G36: =IFERROR(INDEX(Equity!$N:$N,MATCH($B$2&"#"&21,Equity!$P:$P,0)),"")
A37: =IFERROR(INDEX(Equity!$B:$B,MATCH($B$2&"#"&22,Equity!$P:$P,0)),"") | B37: =IFERROR(INDEX(Equity!$C:$C,MATCH($B$2&"#"&22,Equity!$P:$P,0)),"") | C37: =IFERROR(INDEX(Equity!$D:$D,MATCH($B$2&"#"&22,Equity!$P:$P,0)),"") | D37: =IFERROR(INDEX(Equity!$E:$E,MATCH($B$2&"#"&22,Equity!$P:$P,0)),"") | E37: =IFERROR(INDEX(Equity!$I:$I,MATCH($B$2&"#"&22,Equity!$P:$P,0)),"") | F37: =IFERROR(INDEX(Equity!$K:$K,MATCH($B$2&"#"&22,Equity!$P:$P,0)),"") | G37: =IFERROR(INDEX(Equity!$N:$N,MATCH($B$2&"#"&22,Equity!$P:$P,0)),"")
A38: =IFERROR(INDEX(Equity!$B:$B,MATCH($B$2&"#"&23,Equity!$P:$P,0)),"") | B38: =IFERROR(INDEX(Equity!$C:$C,MATCH($B$2&"#"&23,Equity!$P:$P,0)),"") | C38: =IFERROR(INDEX(Equity!$D:$D,MATCH($B$2&"#"&23,Equity!$P:$P,0)),"") | D38: =IFERROR(INDEX(Equity!$E:$E,MATCH($B$2&"#"&23,Equity!$P:$P,0)),"") | E38: =IFERROR(INDEX(Equity!$I:$I,MATCH($B$2&"#"&23,Equity!$P:$P,0)),"") | F38: =IFERROR(INDEX(Equity!$K:$K,MATCH($B$2&"#"&23,Equity!$P:$P,0)),"") | G38: =IFERROR(INDEX(Equity!$N:$N,MATCH($B$2&"#"&23,Equity!$P:$P,0)),"")
A39: =IFERROR(INDEX(Equity!$B:$B,MATCH($B$2&"#"&24,Equity!$P:$P,0)),"") | B39: =IFERROR(INDEX(Equity!$C:$C,MATCH($B$2&"#"&24,Equity!$P:$P,0)),"") | C39: =IFERROR(INDEX(Equity!$D:$D,MATCH($B$2&"#"&24,Equity!$P:$P,0)),"") | D39: =IFERROR(INDEX(Equity!$E:$E,MATCH($B$2&"#"&24,Equity!$P:$P,0)),"") | E39: =IFERROR(INDEX(Equity!$I:$I,MATCH($B$2&"#"&24,Equity!$P:$P,0)),"") | F39: =IFERROR(INDEX(Equity!$K:$K,MATCH($B$2&"#"&24,Equity!$P:$P,0)),"") | G39: =IFERROR(INDEX(Equity!$N:$N,MATCH($B$2&"#"&24,Equity!$P:$P,0)),"")
A40: =IFERROR(INDEX(Equity!$B:$B,MATCH($B$2&"#"&25,Equity!$P:$P,0)),"") | B40: =IFERROR(INDEX(Equity!$C:$C,MATCH($B$2&"#"&25,Equity!$P:$P,0)),"") | C40: =IFERROR(INDEX(Equity!$D:$D,MATCH($B$2&"#"&25,Equity!$P:$P,0)),"") | D40: =IFERROR(INDEX(Equity!$E:$E,MATCH($B$2&"#"&25,Equity!$P:$P,0)),"") | E40: =IFERROR(INDEX(Equity!$I:$I,MATCH($B$2&"#"&25,Equity!$P:$P,0)),"") | F40: =IFERROR(INDEX(Equity!$K:$K,MATCH($B$2&"#"&25,Equity!$P:$P,0)),"") | G40: =IFERROR(INDEX(Equity!$N:$N,MATCH($B$2&"#"&25,Equity!$P:$P,0)),"")
A41: =IFERROR(INDEX(Equity!$B:$B,MATCH($B$2&"#"&26,Equity!$P:$P,0)),"") | B41: =IFERROR(INDEX(Equity!$C:$C,MATCH($B$2&"#"&26,Equity!$P:$P,0)),"") | C41: =IFERROR(INDEX(Equity!$D:$D,MATCH($B$2&"#"&26,Equity!$P:$P,0)),"") | D41: =IFERROR(INDEX(Equity!$E:$E,MATCH($B$2&"#"&26,Equity!$P:$P,0)),"") | E41: =IFERROR(INDEX(Equity!$I:$I,MATCH($B$2&"#"&26,Equity!$P:$P,0)),"") | F41: =IFERROR(INDEX(Equity!$K:$K,MATCH($B$2&"#"&26,Equity!$P:$P,0)),"") | G41: =IFERROR(INDEX(Equity!$N:$N,MATCH($B$2&"#"&26,Equity!$P:$P,0)),"")
A42: =IFERROR(INDEX(Equity!$B:$B,MATCH($B$2&"#"&27,Equity!$P:$P,0)),"") | B42: =IFERROR(INDEX(Equity!$C:$C,MATCH($B$2&"#"&27,Equity!$P:$P,0)),"") | C42: =IFERROR(INDEX(Equity!$D:$D,MATCH($B$2&"#"&27,Equity!$P:$P,0)),"") | D42: =IFERROR(INDEX(Equity!$E:$E,MATCH($B$2&"#"&27,Equity!$P:$P,0)),"") | E42: =IFERROR(INDEX(Equity!$I:$I,MATCH($B$2&"#"&27,Equity!$P:$P,0)),"") | F42: =IFERROR(INDEX(Equity!$K:$K,MATCH($B$2&"#"&27,Equity!$P:$P,0)),"") | G42: =IFERROR(INDEX(Equity!$N:$N,MATCH($B$2&"#"&27,Equity!$P:$P,0)),"")
A43: =IFERROR(INDEX(Equity!$B:$B,MATCH($B$2&"#"&28,Equity!$P:$P,0)),"") | B43: =IFERROR(INDEX(Equity!$C:$C,MATCH($B$2&"#"&28,Equity!$P:$P,0)),"") | C43: =IFERROR(INDEX(Equity!$D:$D,MATCH($B$2&"#"&28,Equity!$P:$P,0)),"") | D43: =IFERROR(INDEX(Equity!$E:$E,MATCH($B$2&"#"&28,Equity!$P:$P,0)),"") | E43: =IFERROR(INDEX(Equity!$I:$I,MATCH($B$2&"#"&28,Equity!$P:$P,0)),"") | F43: =IFERROR(INDEX(Equity!$K:$K,MATCH($B$2&"#"&28,Equity!$P:$P,0)),"") | G43: =IFERROR(INDEX(Equity!$N:$N,MATCH($B$2&"#"&28,Equity!$P:$P,0)),"")
A44: =IFERROR(INDEX(Equity!$B:$B,MATCH($B$2&"#"&29,Equity!$P:$P,0)),"") | B44: =IFERROR(INDEX(Equity!$C:$C,MATCH($B$2&"#"&29,Equity!$P:$P,0)),"") | C44: =IFERROR(INDEX(Equity!$D:$D,MATCH($B$2&"#"&29,Equity!$P:$P,0)),"") | D44: =IFERROR(INDEX(Equity!$E:$E,MATCH($B$2&"#"&29,Equity!$P:$P,0)),"") | E44: =IFERROR(INDEX(Equity!$I:$I,MATCH($B$2&"#"&29,Equity!$P:$P,0)),"") | F44: =IFERROR(INDEX(Equity!$K:$K,MATCH($B$2&"#"&29,Equity!$P:$P,0)),"") | G44: =IFERROR(INDEX(Equity!$N:$N,MATCH($B$2&"#"&29,Equity!$P:$P,0)),"")
A45: =IFERROR(INDEX(Equity!$B:$B,MATCH($B$2&"#"&30,Equity!$P:$P,0)),"") | B45: =IFERROR(INDEX(Equity!$C:$C,MATCH($B$2&"#"&30,Equity!$P:$P,0)),"") | C45: =IFERROR(INDEX(Equity!$D:$D,MATCH($B$2&"#"&30,Equity!$P:$P,0)),"") | D45: =IFERROR(INDEX(Equity!$E:$E,MATCH($B$2&"#"&30,Equity!$P:$P,0)),"") | E45: =IFERROR(INDEX(Equity!$I:$I,MATCH($B$2&"#"&30,Equity!$P:$P,0)),"") | F45: =IFERROR(INDEX(Equity!$K:$K,MATCH($B$2&"#"&30,Equity!$P:$P,0)),"") | G45: =IFERROR(INDEX(Equity!$N:$N,MATCH($B$2&"#"&30,Equity!$P:$P,0)),"")
A46: =IFERROR(INDEX(Equity!$B:$B,MATCH($B$2&"#"&31,Equity!$P:$P,0)),"") | B46: =IFERROR(INDEX(Equity!$C:$C,MATCH($B$2&"#"&31,Equity!$P:$P,0)),"") | C46: =IFERROR(INDEX(Equity!$D:$D,MATCH($B$2&"#"&31,Equity!$P:$P,0)),"") | D46: =IFERROR(INDEX(Equity!$E:$E,MATCH($B$2&"#"&31,Equity!$P:$P,0)),"") | E46: =IFERROR(INDEX(Equity!$I:$I,MATCH($B$2&"#"&31,Equity!$P:$P,0)),"") | F46: =IFERROR(INDEX(Equity!$K:$K,MATCH($B$2&"#"&31,Equity!$P:$P,0)),"") | G46: =IFERROR(INDEX(Equity!$N:$N,MATCH($B$2&"#"&31,Equity!$P:$P,0)),"")
A47: =IFERROR(INDEX(Equity!$B:$B,MATCH($B$2&"#"&32,Equity!$P:$P,0)),"") | B47: =IFERROR(INDEX(Equity!$C:$C,MATCH($B$2&"#"&32,Equity!$P:$P,0)),"") | C47: =IFERROR(INDEX(Equity!$D:$D,MATCH($B$2&"#"&32,Equity!$P:$P,0)),"") | D47: =IFERROR(INDEX(Equity!$E:$E,MATCH($B$2&"#"&32,Equity!$P:$P,0)),"") | E47: =IFERROR(INDEX(Equity!$I:$I,MATCH($B$2&"#"&32,Equity!$P:$P,0)),"") | F47: =IFERROR(INDEX(Equity!$K:$K,MATCH($B$2&"#"&32,Equity!$P:$P,0)),"") | G47: =IFERROR(INDEX(Equity!$N:$N,MATCH($B$2&"#"&32,Equity!$P:$P,0)),"")
A48: =IFERROR(INDEX(Equity!$B:$B,MATCH($B$2&"#"&33,Equity!$P:$P,0)),"") | B48: =IFERROR(INDEX(Equity!$C:$C,MATCH($B$2&"#"&33,Equity!$P:$P,0)),"") | C48: =IFERROR(INDEX(Equity!$D:$D,MATCH($B$2&"#"&33,Equity!$P:$P,0)),"") | D48: =IFERROR(INDEX(Equity!$E:$E,MATCH($B$2&"#"&33,Equity!$P:$P,0)),"") | E48: =IFERROR(INDEX(Equity!$I:$I,MATCH($B$2&"#"&33,Equity!$P:$P,0)),"") | F48: =IFERROR(INDEX(Equity!$K:$K,MATCH($B$2&"#"&33,Equity!$P:$P,0)),"") | G48: =IFERROR(INDEX(Equity!$N:$N,MATCH($B$2&"#"&33,Equity!$P:$P,0)),"")
A49: =IFERROR(INDEX(Equity!$B:$B,MATCH($B$2&"#"&34,Equity!$P:$P,0)),"") | B49: =IFERROR(INDEX(Equity!$C:$C,MATCH($B$2&"#"&34,Equity!$P:$P,0)),"") | C49: =IFERROR(INDEX(Equity!$D:$D,MATCH($B$2&"#"&34,Equity!$P:$P,0)),"") | D49: =IFERROR(INDEX(Equity!$E:$E,MATCH($B$2&"#"&34,Equity!$P:$P,0)),"") | E49: =IFERROR(INDEX(Equity!$I:$I,MATCH($B$2&"#"&34,Equity!$P:$P,0)),"") | F49: =IFERROR(INDEX(Equity!$K:$K,MATCH($B$2&"#"&34,Equity!$P:$P,0)),"") | G49: =IFERROR(INDEX(Equity!$N:$N,MATCH($B$2&"#"&34,Equity!$P:$P,0)),"")
A50: =IFERROR(INDEX(Equity!$B:$B,MATCH($B$2&"#"&35,Equity!$P:$P,0)),"") | B50: =IFERROR(INDEX(Equity!$C:$C,MATCH($B$2&"#"&35,Equity!$P:$P,0)),"") | C50: =IFERROR(INDEX(Equity!$D:$D,MATCH($B$2&"#"&35,Equity!$P:$P,0)),"") | D50: =IFERROR(INDEX(Equity!$E:$E,MATCH($B$2&"#"&35,Equity!$P:$P,0)),"") | E50: =IFERROR(INDEX(Equity!$I:$I,MATCH($B$2&"#"&35,Equity!$P:$P,0)),"") | F50: =IFERROR(INDEX(Equity!$K:$K,MATCH($B$2&"#"&35,Equity!$P:$P,0)),"") | G50: =IFERROR(INDEX(Equity!$N:$N,MATCH($B$2&"#"&35,Equity!$P:$P,0)),"")
A51: =IFERROR(INDEX(Equity!$B:$B,MATCH($B$2&"#"&36,Equity!$P:$P,0)),"") | B51: =IFERROR(INDEX(Equity!$C:$C,MATCH($B$2&"#"&36,Equity!$P:$P,0)),"") | C51: =IFERROR(INDEX(Equity!$D:$D,MATCH($B$2&"#"&36,Equity!$P:$P,0)),"") | D51: =IFERROR(INDEX(Equity!$E:$E,MATCH($B$2&"#"&36,Equity!$P:$P,0)),"") | E51: =IFERROR(INDEX(Equity!$I:$I,MATCH($B$2&"#"&36,Equity!$P:$P,0)),"") | F51: =IFERROR(INDEX(Equity!$K:$K,MATCH($B$2&"#"&36,Equity!$P:$P,0)),"") | G51: =IFERROR(INDEX(Equity!$N:$N,MATCH($B$2&"#"&36,Equity!$P:$P,0)),"")
A52: =IFERROR(INDEX(Equity!$B:$B,MATCH($B$2&"#"&37,Equity!$P:$P,0)),"") | B52: =IFERROR(INDEX(Equity!$C:$C,MATCH($B$2&"#"&37,Equity!$P:$P,0)),"") | C52: =IFERROR(INDEX(Equity!$D:$D,MATCH($B$2&"#"&37,Equity!$P:$P,0)),"") | D52: =IFERROR(INDEX(Equity!$E:$E,MATCH($B$2&"#"&37,Equity!$P:$P,0)),"") | E52: =IFERROR(INDEX(Equity!$I:$I,MATCH($B$2&"#"&37,Equity!$P:$P,0)),"") | F52: =IFERROR(INDEX(Equity!$K:$K,MATCH($B$2&"#"&37,Equity!$P:$P,0)),"") | G52: =IFERROR(INDEX(Equity!$N:$N,MATCH($B$2&"#"&37,Equity!$P:$P,0)),"")
A53: =IFERROR(INDEX(Equity!$B:$B,MATCH($B$2&"#"&38,Equity!$P:$P,0)),"") | B53: =IFERROR(INDEX(Equity!$C:$C,MATCH($B$2&"#"&38,Equity!$P:$P,0)),"") | C53: =IFERROR(INDEX(Equity!$D:$D,MATCH($B$2&"#"&38,Equity!$P:$P,0)),"") | D53: =IFERROR(INDEX(Equity!$E:$E,MATCH($B$2&"#"&38,Equity!$P:$P,0)),"") | E53: =IFERROR(INDEX(Equity!$I:$I,MATCH($B$2&"#"&38,Equity!$P:$P,0)),"") | F53: =IFERROR(INDEX(Equity!$K:$K,MATCH($B$2&"#"&38,Equity!$P:$P,0)),"") | G53: =IFERROR(INDEX(Equity!$N:$N,MATCH($B$2&"#"&38,Equity!$P:$P,0)),"")
A54: =IFERROR(INDEX(Equity!$B:$B,MATCH($B$2&"#"&39,Equity!$P:$P,0)),"") | B54: =IFERROR(INDEX(Equity!$C:$C,MATCH($B$2&"#"&39,Equity!$P:$P,0)),"") | C54: =IFERROR(INDEX(Equity!$D:$D,MATCH($B$2&"#"&39,Equity!$P:$P,0)),"") | D54: =IFERROR(INDEX(Equity!$E:$E,MATCH($B$2&"#"&39,Equity!$P:$P,0)),"") | E54: =IFERROR(INDEX(Equity!$I:$I,MATCH($B$2&"#"&39,Equity!$P:$P,0)),"") | F54: =IFERROR(INDEX(Equity!$K:$K,MATCH($B$2&"#"&39,Equity!$P:$P,0)),"") | G54: =IFERROR(INDEX(Equity!$N:$N,MATCH($B$2&"#"&39,Equity!$P:$P,0)),"")
A55: =IFERROR(INDEX(Equity!$B:$B,MATCH($B$2&"#"&40,Equity!$P:$P,0)),"") | B55: =IFERROR(INDEX(Equity!$C:$C,MATCH($B$2&"#"&40,Equity!$P:$P,0)),"") | C55: =IFERROR(INDEX(Equity!$D:$D,MATCH($B$2&"#"&40,Equity!$P:$P,0)),"") | D55: =IFERROR(INDEX(Equity!$E:$E,MATCH($B$2&"#"&40,Equity!$P:$P,0)),"") | E55: =IFERROR(INDEX(Equity!$I:$I,MATCH($B$2&"#"&40,Equity!$P:$P,0)),"") | F55: =IFERROR(INDEX(Equity!$K:$K,MATCH($B$2&"#"&40,Equity!$P:$P,0)),"") | G55: =IFERROR(INDEX(Equity!$N:$N,MATCH($B$2&"#"&40,Equity!$P:$P,0)),"")
A57: MUTUAL FUNDS
A58: Fund House | B58: Scheme | C58: Units | D58: Cur NAV | E58: Cur. val | F58: Net chg. | G58: XIRR
A59: =IFERROR(INDEX(MutualFunds!$B:$B,MATCH($B$2&"#"&1,MutualFunds!$N:$N,0)),"") -> SBI Mutual Fund | B59: =IFERROR(INDEX(MutualFunds!$C:$C,MATCH($B$2&"#"&1,MutualFunds!$N:$N,0)),"") -> SBI Bluechip Fund - Direct Growth | C59: =IFERROR(INDEX(MutualFunds!$E:$E,MATCH($B$2&"#"&1,MutualFunds!$N:$N,0)),"") -> 1781.4727 | D59: =IFERROR(INDEX(MutualFunds!$G:$G,MATCH($B$2&"#"&1,MutualFunds!$N:$N,0)),"") -> 96.4 | E59: =IFERROR(INDEX(MutualFunds!$I:$I,MATCH($B$2&"#"&1,MutualFunds!$N:$N,0)),"") -> 171733.97 | F59: =IFERROR(INDEX(MutualFunds!$J:$J,MATCH($B$2&"#"&1,MutualFunds!$N:$N,0)),"") -> 21733.967 | G59: =IFERROR(INDEX(MutualFunds!$L:$L,MATCH($B$2&"#"&1,MutualFunds!$N:$N,0)),"") -> 0.073869
A60: =IFERROR(INDEX(MutualFunds!$B:$B,MATCH($B$2&"#"&2,MutualFunds!$N:$N,0)),"") | B60: =IFERROR(INDEX(MutualFunds!$C:$C,MATCH($B$2&"#"&2,MutualFunds!$N:$N,0)),"") | C60: =IFERROR(INDEX(MutualFunds!$E:$E,MATCH($B$2&"#"&2,MutualFunds!$N:$N,0)),"") | D60: =IFERROR(INDEX(MutualFunds!$G:$G,MATCH($B$2&"#"&2,MutualFunds!$N:$N,0)),"") | E60: =IFERROR(INDEX(MutualFunds!$I:$I,MATCH($B$2&"#"&2,MutualFunds!$N:$N,0)),"") | F60: =IFERROR(INDEX(MutualFunds!$J:$J,MATCH($B$2&"#"&2,MutualFunds!$N:$N,0)),"") | G60: =IFERROR(INDEX(MutualFunds!$L:$L,MATCH($B$2&"#"&2,MutualFunds!$N:$N,0)),"")
A61: =IFERROR(INDEX(MutualFunds!$B:$B,MATCH($B$2&"#"&3,MutualFunds!$N:$N,0)),"") | B61: =IFERROR(INDEX(MutualFunds!$C:$C,MATCH($B$2&"#"&3,MutualFunds!$N:$N,0)),"") | C61: =IFERROR(INDEX(MutualFunds!$E:$E,MATCH($B$2&"#"&3,MutualFunds!$N:$N,0)),"") | D61: =IFERROR(INDEX(MutualFunds!$G:$G,MATCH($B$2&"#"&3,MutualFunds!$N:$N,0)),"") | E61: =IFERROR(INDEX(MutualFunds!$I:$I,MATCH($B$2&"#"&3,MutualFunds!$N:$N,0)),"") | F61: =IFERROR(INDEX(MutualFunds!$J:$J,MATCH($B$2&"#"&3,MutualFunds!$N:$N,0)),"") | G61: =IFERROR(INDEX(MutualFunds!$L:$L,MATCH($B$2&"#"&3,MutualFunds!$N:$N,0)),"")
A62: =IFERROR(INDEX(MutualFunds!$B:$B,MATCH($B$2&"#"&4,MutualFunds!$N:$N,0)),"") | B62: =IFERROR(INDEX(MutualFunds!$C:$C,MATCH($B$2&"#"&4,MutualFunds!$N:$N,0)),"") | C62: =IFERROR(INDEX(MutualFunds!$E:$E,MATCH($B$2&"#"&4,MutualFunds!$N:$N,0)),"") | D62: =IFERROR(INDEX(MutualFunds!$G:$G,MATCH($B$2&"#"&4,MutualFunds!$N:$N,0)),"") | E62: =IFERROR(INDEX(MutualFunds!$I:$I,MATCH($B$2&"#"&4,MutualFunds!$N:$N,0)),"") | F62: =IFERROR(INDEX(MutualFunds!$J:$J,MATCH($B$2&"#"&4,MutualFunds!$N:$N,0)),"") | G62: =IFERROR(INDEX(MutualFunds!$L:$L,MATCH($B$2&"#"&4,MutualFunds!$N:$N,0)),"")
A63: =IFERROR(INDEX(MutualFunds!$B:$B,MATCH($B$2&"#"&5,MutualFunds!$N:$N,0)),"") | B63: =IFERROR(INDEX(MutualFunds!$C:$C,MATCH($B$2&"#"&5,MutualFunds!$N:$N,0)),"") | C63: =IFERROR(INDEX(MutualFunds!$E:$E,MATCH($B$2&"#"&5,MutualFunds!$N:$N,0)),"") | D63: =IFERROR(INDEX(MutualFunds!$G:$G,MATCH($B$2&"#"&5,MutualFunds!$N:$N,0)),"") | E63: =IFERROR(INDEX(MutualFunds!$I:$I,MATCH($B$2&"#"&5,MutualFunds!$N:$N,0)),"") | F63: =IFERROR(INDEX(MutualFunds!$J:$J,MATCH($B$2&"#"&5,MutualFunds!$N:$N,0)),"") | G63: =IFERROR(INDEX(MutualFunds!$L:$L,MATCH($B$2&"#"&5,MutualFunds!$N:$N,0)),"")
A64: =IFERROR(INDEX(MutualFunds!$B:$B,MATCH($B$2&"#"&6,MutualFunds!$N:$N,0)),"") | B64: =IFERROR(INDEX(MutualFunds!$C:$C,MATCH($B$2&"#"&6,MutualFunds!$N:$N,0)),"") | C64: =IFERROR(INDEX(MutualFunds!$E:$E,MATCH($B$2&"#"&6,MutualFunds!$N:$N,0)),"") | D64: =IFERROR(INDEX(MutualFunds!$G:$G,MATCH($B$2&"#"&6,MutualFunds!$N:$N,0)),"") | E64: =IFERROR(INDEX(MutualFunds!$I:$I,MATCH($B$2&"#"&6,MutualFunds!$N:$N,0)),"") | F64: =IFERROR(INDEX(MutualFunds!$J:$J,MATCH($B$2&"#"&6,MutualFunds!$N:$N,0)),"") | G64: =IFERROR(INDEX(MutualFunds!$L:$L,MATCH($B$2&"#"&6,MutualFunds!$N:$N,0)),"")
A65: =IFERROR(INDEX(MutualFunds!$B:$B,MATCH($B$2&"#"&7,MutualFunds!$N:$N,0)),"") | B65: =IFERROR(INDEX(MutualFunds!$C:$C,MATCH($B$2&"#"&7,MutualFunds!$N:$N,0)),"") | C65: =IFERROR(INDEX(MutualFunds!$E:$E,MATCH($B$2&"#"&7,MutualFunds!$N:$N,0)),"") | D65: =IFERROR(INDEX(MutualFunds!$G:$G,MATCH($B$2&"#"&7,MutualFunds!$N:$N,0)),"") | E65: =IFERROR(INDEX(MutualFunds!$I:$I,MATCH($B$2&"#"&7,MutualFunds!$N:$N,0)),"") | F65: =IFERROR(INDEX(MutualFunds!$J:$J,MATCH($B$2&"#"&7,MutualFunds!$N:$N,0)),"") | G65: =IFERROR(INDEX(MutualFunds!$L:$L,MATCH($B$2&"#"&7,MutualFunds!$N:$N,0)),"")
A66: =IFERROR(INDEX(MutualFunds!$B:$B,MATCH($B$2&"#"&8,MutualFunds!$N:$N,0)),"") | B66: =IFERROR(INDEX(MutualFunds!$C:$C,MATCH($B$2&"#"&8,MutualFunds!$N:$N,0)),"") | C66: =IFERROR(INDEX(MutualFunds!$E:$E,MATCH($B$2&"#"&8,MutualFunds!$N:$N,0)),"") | D66: =IFERROR(INDEX(MutualFunds!$G:$G,MATCH($B$2&"#"&8,MutualFunds!$N:$N,0)),"") | E66: =IFERROR(INDEX(MutualFunds!$I:$I,MATCH($B$2&"#"&8,MutualFunds!$N:$N,0)),"") | F66: =IFERROR(INDEX(MutualFunds!$J:$J,MATCH($B$2&"#"&8,MutualFunds!$N:$N,0)),"") | G66: =IFERROR(INDEX(MutualFunds!$L:$L,MATCH($B$2&"#"&8,MutualFunds!$N:$N,0)),"")
A67: =IFERROR(INDEX(MutualFunds!$B:$B,MATCH($B$2&"#"&9,MutualFunds!$N:$N,0)),"") | B67: =IFERROR(INDEX(MutualFunds!$C:$C,MATCH($B$2&"#"&9,MutualFunds!$N:$N,0)),"") | C67: =IFERROR(INDEX(MutualFunds!$E:$E,MATCH($B$2&"#"&9,MutualFunds!$N:$N,0)),"") | D67: =IFERROR(INDEX(MutualFunds!$G:$G,MATCH($B$2&"#"&9,MutualFunds!$N:$N,0)),"") | E67: =IFERROR(INDEX(MutualFunds!$I:$I,MATCH($B$2&"#"&9,MutualFunds!$N:$N,0)),"") | F67: =IFERROR(INDEX(MutualFunds!$J:$J,MATCH($B$2&"#"&9,MutualFunds!$N:$N,0)),"") | G67: =IFERROR(INDEX(MutualFunds!$L:$L,MATCH($B$2&"#"&9,MutualFunds!$N:$N,0)),"")
A68: =IFERROR(INDEX(MutualFunds!$B:$B,MATCH($B$2&"#"&10,MutualFunds!$N:$N,0)),"") | B68: =IFERROR(INDEX(MutualFunds!$C:$C,MATCH($B$2&"#"&10,MutualFunds!$N:$N,0)),"") | C68: =IFERROR(INDEX(MutualFunds!$E:$E,MATCH($B$2&"#"&10,MutualFunds!$N:$N,0)),"") | D68: =IFERROR(INDEX(MutualFunds!$G:$G,MATCH($B$2&"#"&10,MutualFunds!$N:$N,0)),"") | E68: =IFERROR(INDEX(MutualFunds!$I:$I,MATCH($B$2&"#"&10,MutualFunds!$N:$N,0)),"") | F68: =IFERROR(INDEX(MutualFunds!$J:$J,MATCH($B$2&"#"&10,MutualFunds!$N:$N,0)),"") | G68: =IFERROR(INDEX(MutualFunds!$L:$L,MATCH($B$2&"#"&10,MutualFunds!$N:$N,0)),"")
A69: =IFERROR(INDEX(MutualFunds!$B:$B,MATCH($B$2&"#"&11,MutualFunds!$N:$N,0)),"") | B69: =IFERROR(INDEX(MutualFunds!$C:$C,MATCH($B$2&"#"&11,MutualFunds!$N:$N,0)),"") | C69: =IFERROR(INDEX(MutualFunds!$E:$E,MATCH($B$2&"#"&11,MutualFunds!$N:$N,0)),"") | D69: =IFERROR(INDEX(MutualFunds!$G:$G,MATCH($B$2&"#"&11,MutualFunds!$N:$N,0)),"") | E69: =IFERROR(INDEX(MutualFunds!$I:$I,MATCH($B$2&"#"&11,MutualFunds!$N:$N,0)),"") | F69: =IFERROR(INDEX(MutualFunds!$J:$J,MATCH($B$2&"#"&11,MutualFunds!$N:$N,0)),"") | G69: =IFERROR(INDEX(MutualFunds!$L:$L,MATCH($B$2&"#"&11,MutualFunds!$N:$N,0)),"")
A70: =IFERROR(INDEX(MutualFunds!$B:$B,MATCH($B$2&"#"&12,MutualFunds!$N:$N,0)),"") | B70: =IFERROR(INDEX(MutualFunds!$C:$C,MATCH($B$2&"#"&12,MutualFunds!$N:$N,0)),"") | C70: =IFERROR(INDEX(MutualFunds!$E:$E,MATCH($B$2&"#"&12,MutualFunds!$N:$N,0)),"") | D70: =IFERROR(INDEX(MutualFunds!$G:$G,MATCH($B$2&"#"&12,MutualFunds!$N:$N,0)),"") | E70: =IFERROR(INDEX(MutualFunds!$I:$I,MATCH($B$2&"#"&12,MutualFunds!$N:$N,0)),"") | F70: =IFERROR(INDEX(MutualFunds!$J:$J,MATCH($B$2&"#"&12,MutualFunds!$N:$N,0)),"") | G70: =IFERROR(INDEX(MutualFunds!$L:$L,MATCH($B$2&"#"&12,MutualFunds!$N:$N,0)),"")
A71: =IFERROR(INDEX(MutualFunds!$B:$B,MATCH($B$2&"#"&13,MutualFunds!$N:$N,0)),"") | B71: =IFERROR(INDEX(MutualFunds!$C:$C,MATCH($B$2&"#"&13,MutualFunds!$N:$N,0)),"") | C71: =IFERROR(INDEX(MutualFunds!$E:$E,MATCH($B$2&"#"&13,MutualFunds!$N:$N,0)),"") | D71: =IFERROR(INDEX(MutualFunds!$G:$G,MATCH($B$2&"#"&13,MutualFunds!$N:$N,0)),"") | E71: =IFERROR(INDEX(MutualFunds!$I:$I,MATCH($B$2&"#"&13,MutualFunds!$N:$N,0)),"") | F71: =IFERROR(INDEX(MutualFunds!$J:$J,MATCH($B$2&"#"&13,MutualFunds!$N:$N,0)),"") | G71: =IFERROR(INDEX(MutualFunds!$L:$L,MATCH($B$2&"#"&13,MutualFunds!$N:$N,0)),"")
A72: =IFERROR(INDEX(MutualFunds!$B:$B,MATCH($B$2&"#"&14,MutualFunds!$N:$N,0)),"") | B72: =IFERROR(INDEX(MutualFunds!$C:$C,MATCH($B$2&"#"&14,MutualFunds!$N:$N,0)),"") | C72: =IFERROR(INDEX(MutualFunds!$E:$E,MATCH($B$2&"#"&14,MutualFunds!$N:$N,0)),"") | D72: =IFERROR(INDEX(MutualFunds!$G:$G,MATCH($B$2&"#"&14,MutualFunds!$N:$N,0)),"") | E72: =IFERROR(INDEX(MutualFunds!$I:$I,MATCH($B$2&"#"&14,MutualFunds!$N:$N,0)),"") | F72: =IFERROR(INDEX(MutualFunds!$J:$J,MATCH($B$2&"#"&14,MutualFunds!$N:$N,0)),"") | G72: =IFERROR(INDEX(MutualFunds!$L:$L,MATCH($B$2&"#"&14,MutualFunds!$N:$N,0)),"")
A73: =IFERROR(INDEX(MutualFunds!$B:$B,MATCH($B$2&"#"&15,MutualFunds!$N:$N,0)),"") | B73: =IFERROR(INDEX(MutualFunds!$C:$C,MATCH($B$2&"#"&15,MutualFunds!$N:$N,0)),"") | C73: =IFERROR(INDEX(MutualFunds!$E:$E,MATCH($B$2&"#"&15,MutualFunds!$N:$N,0)),"") | D73: =IFERROR(INDEX(MutualFunds!$G:$G,MATCH($B$2&"#"&15,MutualFunds!$N:$N,0)),"") | E73: =IFERROR(INDEX(MutualFunds!$I:$I,MATCH($B$2&"#"&15,MutualFunds!$N:$N,0)),"") | F73: =IFERROR(INDEX(MutualFunds!$J:$J,MATCH($B$2&"#"&15,MutualFunds!$N:$N,0)),"") | G73: =IFERROR(INDEX(MutualFunds!$L:$L,MATCH($B$2&"#"&15,MutualFunds!$N:$N,0)),"")
A74: =IFERROR(INDEX(MutualFunds!$B:$B,MATCH($B$2&"#"&16,MutualFunds!$N:$N,0)),"") | B74: =IFERROR(INDEX(MutualFunds!$C:$C,MATCH($B$2&"#"&16,MutualFunds!$N:$N,0)),"") | C74: =IFERROR(INDEX(MutualFunds!$E:$E,MATCH($B$2&"#"&16,MutualFunds!$N:$N,0)),"") | D74: =IFERROR(INDEX(MutualFunds!$G:$G,MATCH($B$2&"#"&16,MutualFunds!$N:$N,0)),"") | E74: =IFERROR(INDEX(MutualFunds!$I:$I,MATCH($B$2&"#"&16,MutualFunds!$N:$N,0)),"") | F74: =IFERROR(INDEX(MutualFunds!$J:$J,MATCH($B$2&"#"&16,MutualFunds!$N:$N,0)),"") | G74: =IFERROR(INDEX(MutualFunds!$L:$L,MATCH($B$2&"#"&16,MutualFunds!$N:$N,0)),"")
A75: =IFERROR(INDEX(MutualFunds!$B:$B,MATCH($B$2&"#"&17,MutualFunds!$N:$N,0)),"") | B75: =IFERROR(INDEX(MutualFunds!$C:$C,MATCH($B$2&"#"&17,MutualFunds!$N:$N,0)),"") | C75: =IFERROR(INDEX(MutualFunds!$E:$E,MATCH($B$2&"#"&17,MutualFunds!$N:$N,0)),"") | D75: =IFERROR(INDEX(MutualFunds!$G:$G,MATCH($B$2&"#"&17,MutualFunds!$N:$N,0)),"") | E75: =IFERROR(INDEX(MutualFunds!$I:$I,MATCH($B$2&"#"&17,MutualFunds!$N:$N,0)),"") | F75: =IFERROR(INDEX(MutualFunds!$J:$J,MATCH($B$2&"#"&17,MutualFunds!$N:$N,0)),"") | G75: =IFERROR(INDEX(MutualFunds!$L:$L,MATCH($B$2&"#"&17,MutualFunds!$N:$N,0)),"")
A76: =IFERROR(INDEX(MutualFunds!$B:$B,MATCH($B$2&"#"&18,MutualFunds!$N:$N,0)),"") | B76: =IFERROR(INDEX(MutualFunds!$C:$C,MATCH($B$2&"#"&18,MutualFunds!$N:$N,0)),"") | C76: =IFERROR(INDEX(MutualFunds!$E:$E,MATCH($B$2&"#"&18,MutualFunds!$N:$N,0)),"") | D76: =IFERROR(INDEX(MutualFunds!$G:$G,MATCH($B$2&"#"&18,MutualFunds!$N:$N,0)),"") | E76: =IFERROR(INDEX(MutualFunds!$I:$I,MATCH($B$2&"#"&18,MutualFunds!$N:$N,0)),"") | F76: =IFERROR(INDEX(MutualFunds!$J:$J,MATCH($B$2&"#"&18,MutualFunds!$N:$N,0)),"") | G76: =IFERROR(INDEX(MutualFunds!$L:$L,MATCH($B$2&"#"&18,MutualFunds!$N:$N,0)),"")
A77: =IFERROR(INDEX(MutualFunds!$B:$B,MATCH($B$2&"#"&19,MutualFunds!$N:$N,0)),"") | B77: =IFERROR(INDEX(MutualFunds!$C:$C,MATCH($B$2&"#"&19,MutualFunds!$N:$N,0)),"") | C77: =IFERROR(INDEX(MutualFunds!$E:$E,MATCH($B$2&"#"&19,MutualFunds!$N:$N,0)),"") | D77: =IFERROR(INDEX(MutualFunds!$G:$G,MATCH($B$2&"#"&19,MutualFunds!$N:$N,0)),"") | E77: =IFERROR(INDEX(MutualFunds!$I:$I,MATCH($B$2&"#"&19,MutualFunds!$N:$N,0)),"") | F77: =IFERROR(INDEX(MutualFunds!$J:$J,MATCH($B$2&"#"&19,MutualFunds!$N:$N,0)),"") | G77: =IFERROR(INDEX(MutualFunds!$L:$L,MATCH($B$2&"#"&19,MutualFunds!$N:$N,0)),"")
A78: =IFERROR(INDEX(MutualFunds!$B:$B,MATCH($B$2&"#"&20,MutualFunds!$N:$N,0)),"") | B78: =IFERROR(INDEX(MutualFunds!$C:$C,MATCH($B$2&"#"&20,MutualFunds!$N:$N,0)),"") | C78: =IFERROR(INDEX(MutualFunds!$E:$E,MATCH($B$2&"#"&20,MutualFunds!$N:$N,0)),"") | D78: =IFERROR(INDEX(MutualFunds!$G:$G,MATCH($B$2&"#"&20,MutualFunds!$N:$N,0)),"") | E78: =IFERROR(INDEX(MutualFunds!$I:$I,MATCH($B$2&"#"&20,MutualFunds!$N:$N,0)),"") | F78: =IFERROR(INDEX(MutualFunds!$J:$J,MATCH($B$2&"#"&20,MutualFunds!$N:$N,0)),"") | G78: =IFERROR(INDEX(MutualFunds!$L:$L,MATCH($B$2&"#"&20,MutualFunds!$N:$N,0)),"")
A80: FIXED DEPOSITS
A81: Bank | B81: Principal | C81: Rate % | D81: Maturity | E81: Value today
A82: =IFERROR(INDEX(FixedDeposits!$B:$B,MATCH($B$2&"#"&1,FixedDeposits!$L:$L,0)),"") | B82: =IFERROR(INDEX(FixedDeposits!$D:$D,MATCH($B$2&"#"&1,FixedDeposits!$L:$L,0)),"") | C82: =IFERROR(INDEX(FixedDeposits!$E:$E,MATCH($B$2&"#"&1,FixedDeposits!$L:$L,0)),"") | D82: =IFERROR(INDEX(FixedDeposits!$G:$G,MATCH($B$2&"#"&1,FixedDeposits!$L:$L,0)),"") | E82: =IFERROR(INDEX(FixedDeposits!$I:$I,MATCH($B$2&"#"&1,FixedDeposits!$L:$L,0)),"")
A83: =IFERROR(INDEX(FixedDeposits!$B:$B,MATCH($B$2&"#"&2,FixedDeposits!$L:$L,0)),"") | B83: =IFERROR(INDEX(FixedDeposits!$D:$D,MATCH($B$2&"#"&2,FixedDeposits!$L:$L,0)),"") | C83: =IFERROR(INDEX(FixedDeposits!$E:$E,MATCH($B$2&"#"&2,FixedDeposits!$L:$L,0)),"") | D83: =IFERROR(INDEX(FixedDeposits!$G:$G,MATCH($B$2&"#"&2,FixedDeposits!$L:$L,0)),"") | E83: =IFERROR(INDEX(FixedDeposits!$I:$I,MATCH($B$2&"#"&2,FixedDeposits!$L:$L,0)),"")
A84: =IFERROR(INDEX(FixedDeposits!$B:$B,MATCH($B$2&"#"&3,FixedDeposits!$L:$L,0)),"") | B84: =IFERROR(INDEX(FixedDeposits!$D:$D,MATCH($B$2&"#"&3,FixedDeposits!$L:$L,0)),"") | C84: =IFERROR(INDEX(FixedDeposits!$E:$E,MATCH($B$2&"#"&3,FixedDeposits!$L:$L,0)),"") | D84: =IFERROR(INDEX(FixedDeposits!$G:$G,MATCH($B$2&"#"&3,FixedDeposits!$L:$L,0)),"") | E84: =IFERROR(INDEX(FixedDeposits!$I:$I,MATCH($B$2&"#"&3,FixedDeposits!$L:$L,0)),"")
A85: =IFERROR(INDEX(FixedDeposits!$B:$B,MATCH($B$2&"#"&4,FixedDeposits!$L:$L,0)),"") | B85: =IFERROR(INDEX(FixedDeposits!$D:$D,MATCH($B$2&"#"&4,FixedDeposits!$L:$L,0)),"") | C85: =IFERROR(INDEX(FixedDeposits!$E:$E,MATCH($B$2&"#"&4,FixedDeposits!$L:$L,0)),"") | D85: =IFERROR(INDEX(FixedDeposits!$G:$G,MATCH($B$2&"#"&4,FixedDeposits!$L:$L,0)),"") | E85: =IFERROR(INDEX(FixedDeposits!$I:$I,MATCH($B$2&"#"&4,FixedDeposits!$L:$L,0)),"")
A86: =IFERROR(INDEX(FixedDeposits!$B:$B,MATCH($B$2&"#"&5,FixedDeposits!$L:$L,0)),"") | B86: =IFERROR(INDEX(FixedDeposits!$D:$D,MATCH($B$2&"#"&5,FixedDeposits!$L:$L,0)),"") | C86: =IFERROR(INDEX(FixedDeposits!$E:$E,MATCH($B$2&"#"&5,FixedDeposits!$L:$L,0)),"") | D86: =IFERROR(INDEX(FixedDeposits!$G:$G,MATCH($B$2&"#"&5,FixedDeposits!$L:$L,0)),"") | E86: =IFERROR(INDEX(FixedDeposits!$I:$I,MATCH($B$2&"#"&5,FixedDeposits!$L:$L,0)),"")
A87: =IFERROR(INDEX(FixedDeposits!$B:$B,MATCH($B$2&"#"&6,FixedDeposits!$L:$L,0)),"") | B87: =IFERROR(INDEX(FixedDeposits!$D:$D,MATCH($B$2&"#"&6,FixedDeposits!$L:$L,0)),"") | C87: =IFERROR(INDEX(FixedDeposits!$E:$E,MATCH($B$2&"#"&6,FixedDeposits!$L:$L,0)),"") | D87: =IFERROR(INDEX(FixedDeposits!$G:$G,MATCH($B$2&"#"&6,FixedDeposits!$L:$L,0)),"") | E87: =IFERROR(INDEX(FixedDeposits!$I:$I,MATCH($B$2&"#"&6,FixedDeposits!$L:$L,0)),"")
A88: =IFERROR(INDEX(FixedDeposits!$B:$B,MATCH($B$2&"#"&7,FixedDeposits!$L:$L,0)),"") | B88: =IFERROR(INDEX(FixedDeposits!$D:$D,MATCH($B$2&"#"&7,FixedDeposits!$L:$L,0)),"") | C88: =IFERROR(INDEX(FixedDeposits!$E:$E,MATCH($B$2&"#"&7,FixedDeposits!$L:$L,0)),"") | D88: =IFERROR(INDEX(FixedDeposits!$G:$G,MATCH($B$2&"#"&7,FixedDeposits!$L:$L,0)),"") | E88: =IFERROR(INDEX(FixedDeposits!$I:$I,MATCH($B$2&"#"&7,FixedDeposits!$L:$L,0)),"")
A89: =IFERROR(INDEX(FixedDeposits!$B:$B,MATCH($B$2&"#"&8,FixedDeposits!$L:$L,0)),"") | B89: =IFERROR(INDEX(FixedDeposits!$D:$D,MATCH($B$2&"#"&8,FixedDeposits!$L:$L,0)),"") | C89: =IFERROR(INDEX(FixedDeposits!$E:$E,MATCH($B$2&"#"&8,FixedDeposits!$L:$L,0)),"") | D89: =IFERROR(INDEX(FixedDeposits!$G:$G,MATCH($B$2&"#"&8,FixedDeposits!$L:$L,0)),"") | E89: =IFERROR(INDEX(FixedDeposits!$I:$I,MATCH($B$2&"#"&8,FixedDeposits!$L:$L,0)),"")
A90: =IFERROR(INDEX(FixedDeposits!$B:$B,MATCH($B$2&"#"&9,FixedDeposits!$L:$L,0)),"") | B90: =IFERROR(INDEX(FixedDeposits!$D:$D,MATCH($B$2&"#"&9,FixedDeposits!$L:$L,0)),"") | C90: =IFERROR(INDEX(FixedDeposits!$E:$E,MATCH($B$2&"#"&9,FixedDeposits!$L:$L,0)),"") | D90: =IFERROR(INDEX(FixedDeposits!$G:$G,MATCH($B$2&"#"&9,FixedDeposits!$L:$L,0)),"") | E90: =IFERROR(INDEX(FixedDeposits!$I:$I,MATCH($B$2&"#"&9,FixedDeposits!$L:$L,0)),"")
A91: =IFERROR(INDEX(FixedDeposits!$B:$B,MATCH($B$2&"#"&10,FixedDeposits!$L:$L,0)),"") | B91: =IFERROR(INDEX(FixedDeposits!$D:$D,MATCH($B$2&"#"&10,FixedDeposits!$L:$L,0)),"") | C91: =IFERROR(INDEX(FixedDeposits!$E:$E,MATCH($B$2&"#"&10,FixedDeposits!$L:$L,0)),"") | D91: =IFERROR(INDEX(FixedDeposits!$G:$G,MATCH($B$2&"#"&10,FixedDeposits!$L:$L,0)),"") | E91: =IFERROR(INDEX(FixedDeposits!$I:$I,MATCH($B$2&"#"&10,FixedDeposits!$L:$L,0)),"")
A92: =IFERROR(INDEX(FixedDeposits!$B:$B,MATCH($B$2&"#"&11,FixedDeposits!$L:$L,0)),"") | B92: =IFERROR(INDEX(FixedDeposits!$D:$D,MATCH($B$2&"#"&11,FixedDeposits!$L:$L,0)),"") | C92: =IFERROR(INDEX(FixedDeposits!$E:$E,MATCH($B$2&"#"&11,FixedDeposits!$L:$L,0)),"") | D92: =IFERROR(INDEX(FixedDeposits!$G:$G,MATCH($B$2&"#"&11,FixedDeposits!$L:$L,0)),"") | E92: =IFERROR(INDEX(FixedDeposits!$I:$I,MATCH($B$2&"#"&11,FixedDeposits!$L:$L,0)),"")
A93: =IFERROR(INDEX(FixedDeposits!$B:$B,MATCH($B$2&"#"&12,FixedDeposits!$L:$L,0)),"") | B93: =IFERROR(INDEX(FixedDeposits!$D:$D,MATCH($B$2&"#"&12,FixedDeposits!$L:$L,0)),"") | C93: =IFERROR(INDEX(FixedDeposits!$E:$E,MATCH($B$2&"#"&12,FixedDeposits!$L:$L,0)),"") | D93: =IFERROR(INDEX(FixedDeposits!$G:$G,MATCH($B$2&"#"&12,FixedDeposits!$L:$L,0)),"") | E93: =IFERROR(INDEX(FixedDeposits!$I:$I,MATCH($B$2&"#"&12,FixedDeposits!$L:$L,0)),"")
A94: =IFERROR(INDEX(FixedDeposits!$B:$B,MATCH($B$2&"#"&13,FixedDeposits!$L:$L,0)),"") | B94: =IFERROR(INDEX(FixedDeposits!$D:$D,MATCH($B$2&"#"&13,FixedDeposits!$L:$L,0)),"") | C94: =IFERROR(INDEX(FixedDeposits!$E:$E,MATCH($B$2&"#"&13,FixedDeposits!$L:$L,0)),"") | D94: =IFERROR(INDEX(FixedDeposits!$G:$G,MATCH($B$2&"#"&13,FixedDeposits!$L:$L,0)),"") | E94: =IFERROR(INDEX(FixedDeposits!$I:$I,MATCH($B$2&"#"&13,FixedDeposits!$L:$L,0)),"")
A95: =IFERROR(INDEX(FixedDeposits!$B:$B,MATCH($B$2&"#"&14,FixedDeposits!$L:$L,0)),"") | B95: =IFERROR(INDEX(FixedDeposits!$D:$D,MATCH($B$2&"#"&14,FixedDeposits!$L:$L,0)),"") | C95: =IFERROR(INDEX(FixedDeposits!$E:$E,MATCH($B$2&"#"&14,FixedDeposits!$L:$L,0)),"") | D95: =IFERROR(INDEX(FixedDeposits!$G:$G,MATCH($B$2&"#"&14,FixedDeposits!$L:$L,0)),"") | E95: =IFERROR(INDEX(FixedDeposits!$I:$I,MATCH($B$2&"#"&14,FixedDeposits!$L:$L,0)),"")
A96: =IFERROR(INDEX(FixedDeposits!$B:$B,MATCH($B$2&"#"&15,FixedDeposits!$L:$L,0)),"") | B96: =IFERROR(INDEX(FixedDeposits!$D:$D,MATCH($B$2&"#"&15,FixedDeposits!$L:$L,0)),"") | C96: =IFERROR(INDEX(FixedDeposits!$E:$E,MATCH($B$2&"#"&15,FixedDeposits!$L:$L,0)),"") | D96: =IFERROR(INDEX(FixedDeposits!$G:$G,MATCH($B$2&"#"&15,FixedDeposits!$L:$L,0)),"") | E96: =IFERROR(INDEX(FixedDeposits!$I:$I,MATCH($B$2&"#"&15,FixedDeposits!$L:$L,0)),"")
A98: PPF
A99: Institution | B99: Balance | C99: As-on
A100: =IFERROR(INDEX(PPF!$B:$B,MATCH($B$2&"#"&1,PPF!$I:$I,0)),"") -> Post Office | B100: =IFERROR(INDEX(PPF!$D:$D,MATCH($B$2&"#"&1,PPF!$I:$I,0)),"") -> 860000 | C100: =IFERROR(INDEX(PPF!$E:$E,MATCH($B$2&"#"&1,PPF!$I:$I,0)),"") -> 46112
A101: =IFERROR(INDEX(PPF!$B:$B,MATCH($B$2&"#"&2,PPF!$I:$I,0)),"") | B101: =IFERROR(INDEX(PPF!$D:$D,MATCH($B$2&"#"&2,PPF!$I:$I,0)),"") | C101: =IFERROR(INDEX(PPF!$E:$E,MATCH($B$2&"#"&2,PPF!$I:$I,0)),"")
A102: =IFERROR(INDEX(PPF!$B:$B,MATCH($B$2&"#"&3,PPF!$I:$I,0)),"") | B102: =IFERROR(INDEX(PPF!$D:$D,MATCH($B$2&"#"&3,PPF!$I:$I,0)),"") | C102: =IFERROR(INDEX(PPF!$E:$E,MATCH($B$2&"#"&3,PPF!$I:$I,0)),"")
A103: =IFERROR(INDEX(PPF!$B:$B,MATCH($B$2&"#"&4,PPF!$I:$I,0)),"") | B103: =IFERROR(INDEX(PPF!$D:$D,MATCH($B$2&"#"&4,PPF!$I:$I,0)),"") | C103: =IFERROR(INDEX(PPF!$E:$E,MATCH($B$2&"#"&4,PPF!$I:$I,0)),"")
A104: =IFERROR(INDEX(PPF!$B:$B,MATCH($B$2&"#"&5,PPF!$I:$I,0)),"") | B104: =IFERROR(INDEX(PPF!$D:$D,MATCH($B$2&"#"&5,PPF!$I:$I,0)),"") | C104: =IFERROR(INDEX(PPF!$E:$E,MATCH($B$2&"#"&5,PPF!$I:$I,0)),"")
A105: =IFERROR(INDEX(PPF!$B:$B,MATCH($B$2&"#"&6,PPF!$I:$I,0)),"") | B105: =IFERROR(INDEX(PPF!$D:$D,MATCH($B$2&"#"&6,PPF!$I:$I,0)),"") | C105: =IFERROR(INDEX(PPF!$E:$E,MATCH($B$2&"#"&6,PPF!$I:$I,0)),"")
A106: =IFERROR(INDEX(PPF!$B:$B,MATCH($B$2&"#"&7,PPF!$I:$I,0)),"") | B106: =IFERROR(INDEX(PPF!$D:$D,MATCH($B$2&"#"&7,PPF!$I:$I,0)),"") | C106: =IFERROR(INDEX(PPF!$E:$E,MATCH($B$2&"#"&7,PPF!$I:$I,0)),"")
...

Sheet Rahul
A1: Rahul — PORTFOLIO
A2: Owner | B2: Rahul
A3: Net worth | B3: =B11 -> 643218.19
A5: Asset class | B5: Value | C5: # holdings
A6: Equity | B6: =SUMIFS(Equity!$I:$I,Equity!$A:$A,$B$2) -> 260600 | C6: =COUNTIF(Equity!$A:$A,$B$2) -> 3
A7: Mutual Funds | B7: =SUMIFS(MutualFunds!$I:$I,MutualFunds!$A:$A,$B$2) -> 0 | C7: =COUNTIF(MutualFunds!$A:$A,$B$2) -> 0
A8: Fixed Deposits | B8: =SUMIFS(FixedDeposits!$I:$I,FixedDeposits!$A:$A,$B$2) -> 331868.19 | C8: =COUNTIF(FixedDeposits!$A:$A,$B$2) -> 1
A9: PPF | B9: =SUMIFS(PPF!$D:$D,PPF!$A:$A,$B$2) -> 0 | C9: =COUNTIF(PPF!$A:$A,$B$2) -> 0
A10: Bonds | B10: =SUMIFS(Bonds!$K:$K,Bonds!$A:$A,$B$2) -> 50750 | C10: =COUNTIF(Bonds!$A:$A,$B$2) -> 1
A11: Total | B11: =SUM(B6:B10) -> 643218.19 | C11: =SUM(C6:C10) -> 5
A14: EQUITY
A15: ISIN | B15: Scrip | C15: Qty | D15: Avg cost | E15: Cur. val | F15: Net chg. | G15: XIRR
A16: =IFERROR(INDEX(Equity!$B:$B,MATCH($B$2&"#"&1,Equity!$P:$P,0)),"") -> INE018A01030 | B16: =IFERROR(INDEX(Equity!$C:$C,MATCH($B$2&"#"&1,Equity!$P:$P,0)),"") -> LARSEN & TOUBRO LIMITED EQ | C16: =IFERROR(INDEX(Equity!$D:$D,MATCH($B$2&"#"&1,Equity!$P:$P,0)),"") -> 25 | D16: =IFERROR(INDEX(Equity!$E:$E,MATCH($B$2&"#"&1,Equity!$P:$P,0)),"") -> 1470 | E16: =IFERROR(INDEX(Equity!$I:$I,MATCH($B$2&"#"&1,Equity!$P:$P,0)),"") -> 90500 | F16: =IFERROR(INDEX(Equity!$K:$K,MATCH($B$2&"#"&1,Equity!$P:$P,0)),"") -> 53750 | G16: =IFERROR(INDEX(Equity!$N:$N,MATCH($B$2&"#"&1,Equity!$P:$P,0)),"") -> 0.11248003
A17: =IFERROR(INDEX(Equity!$B:$B,MATCH($B$2&"#"&2,Equity!$P:$P,0)),"") -> INE062A01020 | B17: =IFERROR(INDEX(Equity!$C:$C,MATCH($B$2&"#"&2,Equity!$P:$P,0)),"") -> STATE BANK OF INDIA EQ | C17: =IFERROR(INDEX(Equity!$D:$D,MATCH($B$2&"#"&2,Equity!$P:$P,0)),"") -> 120 | D17: =IFERROR(INDEX(Equity!$E:$E,MATCH($B$2&"#"&2,Equity!$P:$P,0)),"") -> 327 | E17: =IFERROR(INDEX(Equity!$I:$I,MATCH($B$2&"#"&2,Equity!$P:$P,0)),"") -> 97800 | F17: =IFERROR(INDEX(Equity!$K:$K,MATCH($B$2&"#"&2,Equity!$P:$P,0)),"") -> 58560 | G17: =IFERROR(INDEX(Equity!$N:$N,MATCH($B$2&"#"&2,Equity!$P:$P,0)),"") -> 0.11406226
A18: =IFERROR(INDEX(Equity!$B:$B,MATCH($B$2&"#"&3,Equity!$P:$P,0)),"") -> INE030A01027 | B18: =IFERROR(INDEX(Equity!$C:$C,MATCH($B$2&"#"&3,Equity!$P:$P,0)),"") -> HINDUSTAN UNILEVER LIMITED EQ | C18: =IFERROR(INDEX(Equity!$D:$D,MATCH($B$2&"#"&3,Equity!$P:$P,0)),"") -> 30 | D18: =IFERROR(INDEX(Equity!$E:$E,MATCH($B$2&"#"&3,Equity!$P:$P,0)),"") -> 1370 | E18: =IFERROR(INDEX(Equity!$I:$I,MATCH($B$2&"#"&3,Equity!$P:$P,0)),"") -> 72300 | F18: =IFERROR(INDEX(Equity!$K:$K,MATCH($B$2&"#"&3,Equity!$P:$P,0)),"") -> 31200 | G18: =IFERROR(INDEX(Equity!$N:$N,MATCH($B$2&"#"&3,Equity!$P:$P,0)),"") -> 0.069086159
A19: =IFERROR(INDEX(Equity!$B:$B,MATCH($B$2&"#"&4,Equity!$P:$P,0)),"") | B19: =IFERROR(INDEX(Equity!$C:$C,MATCH($B$2&"#"&4,Equity!$P:$P,0)),"") | C19: =IFERROR(INDEX(Equity!$D:$D,MATCH($B$2&"#"&4,Equity!$P:$P,0)),"") | D19: =IFERROR(INDEX(Equity!$E:$E,MATCH($B$2&"#"&4,Equity!$P:$P,0)),"") | E19: =IFERROR(INDEX(Equity!$I:$I,MATCH($B$2&"#"&4,Equity!$P:$P,0)),"") | F19: =IFERROR(INDEX(Equity!$K:$K,MATCH($B$2&"#"&4,Equity!$P:$P,0)),"") | G19: =IFERROR(INDEX(Equity!$N:$N,MATCH($B$2&"#"&4,Equity!$P:$P,0)),"")
A20: =IFERROR(INDEX(Equity!$B:$B,MATCH($B$2&"#"&5,Equity!$P:$P,0)),"") | B20: =IFERROR(INDEX(Equity!$C:$C,MATCH($B$2&"#"&5,Equity!$P:$P,0)),"") | C20: =IFERROR(INDEX(Equity!$D:$D,MATCH($B$2&"#"&5,Equity!$P:$P,0)),"") | D20: =IFERROR(INDEX(Equity!$E:$E,MATCH($B$2&"#"&5,Equity!$P:$P,0)),"") | E20: =IFERROR(INDEX(Equity!$I:$I,MATCH($B$2&"#"&5,Equity!$P:$P,0)),"") | F20: =IFERROR(INDEX(Equity!$K:$K,MATCH($B$2&"#"&5,Equity!$P:$P,0)),"") | G20: =IFERROR(INDEX(Equity!$N:$N,MATCH($B$2&"#"&5,Equity!$P:$P,0)),"")
A21: =IFERROR(INDEX(Equity!$B:$B,MATCH($B$2&"#"&6,Equity!$P:$P,0)),"") | B21: =IFERROR(INDEX(Equity!$C:$C,MATCH($B$2&"#"&6,Equity!$P:$P,0)),"") | C21: =IFERROR(INDEX(Equity!$D:$D,MATCH($B$2&"#"&6,Equity!$P:$P,0)),"") | D21: =IFERROR(INDEX(Equity!$E:$E,MATCH($B$2&"#"&6,Equity!$P:$P,0)),"") | E21: =IFERROR(INDEX(Equity!$I:$I,MATCH($B$2&"#"&6,Equity!$P:$P,0)),"") | F21: =IFERROR(INDEX(Equity!$K:$K,MATCH($B$2&"#"&6,Equity!$P:$P,0)),"") | G21: =IFERROR(INDEX(Equity!$N:$N,MATCH($B$2&"#"&6,Equity!$P:$P,0)),"")
A22: =IFERROR(INDEX(Equity!$B:$B,MATCH($B$2&"#"&7,Equity!$P:$P,0)),"") | B22: =IFERROR(INDEX(Equity!$C:$C,MATCH($B$2&"#"&7,Equity!$P:$P,0)),"") | C22: =IFERROR(INDEX(Equity!$D:$D,MATCH($B$2&"#"&7,Equity!$P:$P,0)),"") | D22: =IFERROR(INDEX(Equity!$E:$E,MATCH($B$2&"#"&7,Equity!$P:$P,0)),"") | E22: =IFERROR(INDEX(Equity!$I:$I,MATCH($B$2&"#"&7,Equity!$P:$P,0)),"") | F22: =IFERROR(INDEX(Equity!$K:$K,MATCH($B$2&"#"&7,Equity!$P:$P,0)),"") | G22: =IFERROR(INDEX(Equity!$N:$N,MATCH($B$2&"#"&7,Equity!$P:$P,0)),"")
A23: =IFERROR(INDEX(Equity!$B:$B,MATCH($B$2&"#"&8,Equity!$P:$P,0)),"") | B23: =IFERROR(INDEX(Equity!$C:$C,MATCH($B$2&"#"&8,Equity!$P:$P,0)),"") | C23: =IFERROR(INDEX(Equity!$D:$D,MATCH($B$2&"#"&8,Equity!$P:$P,0)),"") | D23: =IFERROR(INDEX(Equity!$E:$E,MATCH($B$2&"#"&8,Equity!$P:$P,0)),"") | E23: =IFERROR(INDEX(Equity!$I:$I,MATCH($B$2&"#"&8,Equity!$P:$P,0)),"") | F23: =IFERROR(INDEX(Equity!$K:$K,MATCH($B$2&"#"&8,Equity!$P:$P,0)),"") | G23: =IFERROR(INDEX(Equity!$N:$N,MATCH($B$2&"#"&8,Equity!$P:$P,0)),"")
A24: =IFERROR(INDEX(Equity!$B:$B,MATCH($B$2&"#"&9,Equity!$P:$P,0)),"") | B24: =IFERROR(INDEX(Equity!$C:$C,MATCH($B$2&"#"&9,Equity!$P:$P,0)),"") | C24: =IFERROR(INDEX(Equity!$D:$D,MATCH($B$2&"#"&9,Equity!$P:$P,0)),"") | D24: =IFERROR(INDEX(Equity!$E:$E,MATCH($B$2&"#"&9,Equity!$P:$P,0)),"") | E24: =IFERROR(INDEX(Equity!$I:$I,MATCH($B$2&"#"&9,Equity!$P:$P,0)),"") | F24: =IFERROR(INDEX(Equity!$K:$K,MATCH($B$2&"#"&9,Equity!$P:$P,0)),"") | G24: =IFERROR(INDEX(Equity!$N:$N,MATCH($B$2&"#"&9,Equity!$P:$P,0)),"")
A25: =IFERROR(INDEX(Equity!$B:$B,MATCH($B$2&"#"&10,Equity!$P:$P,0)),"") | B25: =IFERROR(INDEX(Equity!$C:$C,MATCH($B$2&"#"&10,Equity!$P:$P,0)),"") | C25: =IFERROR(INDEX(Equity!$D:$D,MATCH($B$2&"#"&10,Equity!$P:$P,0)),"") | D25: =IFERROR(INDEX(Equity!$E:$E,MATCH($B$2&"#"&10,Equity!$P:$P,0)),"") | E25: =IFERROR(INDEX(Equity!$I:$I,MATCH($B$2&"#"&10,Equity!$P:$P,0)),"") | F25: =IFERROR(INDEX(Equity!$K:$K,MATCH($B$2&"#"&10,Equity!$P:$P,0)),"") | G25: =IFERROR(INDEX(Equity!$N:$N,MATCH($B$2&"#"&10,Equity!$P:$P,0)),"")
A26: =IFERROR(INDEX(Equity!$B:$B,MATCH($B$2&"#"&11,Equity!$P:$P,0)),"") | B26: =IFERROR(INDEX(Equity!$C:$C,MATCH($B$2&"#"&11,Equity!$P:$P,0)),"") | C26: =IFERROR(INDEX(Equity!$D:$D,MATCH($B$2&"#"&11,Equity!$P:$P,0)),"") | D26: =IFERROR(INDEX(Equity!$E:$E,MATCH($B$2&"#"&11,Equity!$P:$P,0)),"") | E26: =IFERROR(INDEX(Equity!$I:$I,MATCH($B$2&"#"&11,Equity!$P:$P,0)),"") | F26: =IFERROR(INDEX(Equity!$K:$K,MATCH($B$2&"#"&11,Equity!$P:$P,0)),"") | G26: =IFERROR(INDEX(Equity!$N:$N,MATCH($B$2&"#"&11,Equity!$P:$P,0)),"")
A27: =IFERROR(INDEX(Equity!$B:$B,MATCH($B$2&"#"&12,Equity!$P:$P,0)),"") | B27: =IFERROR(INDEX(Equity!$C:$C,MATCH($B$2&"#"&12,Equity!$P:$P,0)),"") | C27: =IFERROR(INDEX(Equity!$D:$D,MATCH($B$2&"#"&12,Equity!$P:$P,0)),"") | D27: =IFERROR(INDEX(Equity!$E:$E,MATCH($B$2&"#"&12,Equity!$P:$P,0)),"") | E27: =IFERROR(INDEX(Equity!$I:$I,MATCH($B$2&"#"&12,Equity!$P:$P,0)),"") | F27: =IFERROR(INDEX(Equity!$K:$K,MATCH($B$2&"#"&12,Equity!$P:$P,0)),"") | G27: =IFERROR(INDEX(Equity!$N:$N,MATCH($B$2&"#"&12,Equity!$P:$P,0)),"")
A28: =IFERROR(INDEX(Equity!$B:$B,MATCH($B$2&"#"&13,Equity!$P:$P,0)),"") | B28: =IFERROR(INDEX(Equity!$C:$C,MATCH($B$2&"#"&13,Equity!$P:$P,0)),"") | C28: =IFERROR(INDEX(Equity!$D:$D,MATCH($B$2&"#"&13,Equity!$P:$P,0)),"") | D28: =IFERROR(INDEX(Equity!$E:$E,MATCH($B$2&"#"&13,Equity!$P:$P,0)),"") | E28: =IFERROR(INDEX(Equity!$I:$I,MATCH($B$2&"#"&13,Equity!$P:$P,0)),"") | F28: =IFERROR(INDEX(Equity!$K:$K,MATCH($B$2&"#"&13,Equity!$P:$P,0)),"") | G28: =IFERROR(INDEX(Equity!$N:$N,MATCH($B$2&"#"&13,Equity!$P:$P,0)),"")
A29: =IFERROR(INDEX(Equity!$B:$B,MATCH($B$2&"#"&14,Equity!$P:$P,0)),"") | B29: =IFERROR(INDEX(Equity!$C:$C,MATCH($B$2&"#"&14,Equity!$P:$P,0)),"") | C29: =IFERROR(INDEX(Equity!$D:$D,MATCH($B$2&"#"&14,Equity!$P:$P,0)),"") | D29: =IFERROR(INDEX(Equity!$E:$E,MATCH($B$2&"#"&14,Equity!$P:$P,0)),"") | E29: =IFERROR(INDEX(Equity!$I:$I,MATCH($B$2&"#"&14,Equity!$P:$P,0)),"") | F29: =IFERROR(INDEX(Equity!$K:$K,MATCH($B$2&"#"&14,Equity!$P:$P,0)),"") | G29: =IFERROR(INDEX(Equity!$N:$N,MATCH($B$2&"#"&14,Equity!$P:$P,0)),"")
A30: =IFERROR(INDEX(Equity!$B:$B,MATCH($B$2&"#"&15,Equity!$P:$P,0)),"") | B30: =IFERROR(INDEX(Equity!$C:$C,MATCH($B$2&"#"&15,Equity!$P:$P,0)),"") | C30: =IFERROR(INDEX(Equity!$D:$D,MATCH($B$2&"#"&15,Equity!$P:$P,0)),"") | D30: =IFERROR(INDEX(Equity!$E:$E,MATCH($B$2&"#"&15,Equity!$P:$P,0)),"") | E30: =IFERROR(INDEX(Equity!$I:$I,MATCH($B$2&"#"&15,Equity!$P:$P,0)),"") | F30: =IFERROR(INDEX(Equity!$K:$K,MATCH($B$2&"#"&15,Equity!$P:$P,0)),"") | G30: =IFERROR(INDEX(Equity!$N:$N,MATCH($B$2&"#"&15,Equity!$P:$P,0)),"")
A31: =IFERROR(INDEX(Equity!$B:$B,MATCH($B$2&"#"&16,Equity!$P:$P,0)),"") | B31: =IFERROR(INDEX(Equity!$C:$C,MATCH($B$2&"#"&16,Equity!$P:$P,0)),"") | C31: =IFERROR(INDEX(Equity!$D:$D,MATCH($B$2&"#"&16,Equity!$P:$P,0)),"") | D31: =IFERROR(INDEX(Equity!$E:$E,MATCH($B$2&"#"&16,Equity!$P:$P,0)),"") | E31: =IFERROR(INDEX(Equity!$I:$I,MATCH($B$2&"#"&16,Equity!$P:$P,0)),"") | F31: =IFERROR(INDEX(Equity!$K:$K,MATCH($B$2&"#"&16,Equity!$P:$P,0)),"") | G31: =IFERROR(INDEX(Equity!$N:$N,MATCH($B$2&"#"&16,Equity!$P:$P,0)),"")
A32: =IFERROR(INDEX(Equity!$B:$B,MATCH($B$2&"#"&17,Equity!$P:$P,0)),"") | B32: =IFERROR(INDEX(Equity!$C:$C,MATCH($B$2&"#"&17,Equity!$P:$P,0)),"") | C32: =IFERROR(INDEX(Equity!$D:$D,MATCH($B$2&"#"&17,Equity!$P:$P,0)),"") | D32: =IFERROR(INDEX(Equity!$E:$E,MATCH($B$2&"#"&17,Equity!$P:$P,0)),"") | E32: =IFERROR(INDEX(Equity!$I:$I,MATCH($B$2&"#"&17,Equity!$P:$P,0)),"") | F32: =IFERROR(INDEX(Equity!$K:$K,MATCH($B$2&"#"&17,Equity!$P:$P,0)),"") | G32: =IFERROR(INDEX(Equity!$N:$N,MATCH($B$2&"#"&17,Equity!$P:$P,0)),"")
A33: =IFERROR(INDEX(Equity!$B:$B,MATCH($B$2&"#"&18,Equity!$P:$P,0)),"") | B33: =IFERROR(INDEX(Equity!$C:$C,MATCH($B$2&"#"&18,Equity!$P:$P,0)),"") | C33: =IFERROR(INDEX(Equity!$D:$D,MATCH($B$2&"#"&18,Equity!$P:$P,0)),"") | D33: =IFERROR(INDEX(Equity!$E:$E,MATCH($B$2&"#"&18,Equity!$P:$P,0)),"") | E33: =IFERROR(INDEX(Equity!$I:$I,MATCH($B$2&"#"&18,Equity!$P:$P,0)),"") | F33: =IFERROR(INDEX(Equity!$K:$K,MATCH($B$2&"#"&18,Equity!$P:$P,0)),"") | G33: =IFERROR(INDEX(Equity!$N:$N,MATCH($B$2&"#"&18,Equity!$P:$P,0)),"")
A34: =IFERROR(INDEX(Equity!$B:$B,MATCH($B$2&"#"&19,Equity!$P:$P,0)),"") | B34: =IFERROR(INDEX(Equity!$C:$C,MATCH($B$2&"#"&19,Equity!$P:$P,0)),"") | C34: =IFERROR(INDEX(Equity!$D:$D,MATCH($B$2&"#"&19,Equity!$P:$P,0)),"") | D34: =IFERROR(INDEX(Equity!$E:$E,MATCH($B$2&"#"&19,Equity!$P:$P,0)),"") | E34: =IFERROR(INDEX(Equity!$I:$I,MATCH($B$2&"#"&19,Equity!$P:$P,0)),"") | F34: =IFERROR(INDEX(Equity!$K:$K,MATCH($B$2&"#"&19,Equity!$P:$P,0)),"") | G34: =IFERROR(INDEX(Equity!$N:$N,MATCH($B$2&"#"&19,Equity!$P:$P,0)),"")
A35: =IFERROR(INDEX(Equity!$B:$B,MATCH($B$2&"#"&20,Equity!$P:$P,0)),"") | B35: =IFERROR(INDEX(Equity!$C:$C,MATCH($B$2&"#"&20,Equity!$P:$P,0)),"") | C35: =IFERROR(INDEX(Equity!$D:$D,MATCH($B$2&"#"&20,Equity!$P:$P,0)),"") | D35: =IFERROR(INDEX(Equity!$E:$E,MATCH($B$2&"#"&20,Equity!$P:$P,0)),"") | E35: =IFERROR(INDEX(Equity!$I:$I,MATCH($B$2&"#"&20,Equity!$P:$P,0)),"") | F35: =IFERROR(INDEX(Equity!$K:$K,MATCH($B$2&"#"&20,Equity!$P:$P,0)),"") | G35: =IFERROR(INDEX(Equity!$N:$N,MATCH($B$2&"#"&20,Equity!$P:$P,0)),"")
A36: =IFERROR(INDEX(Equity!$B:$B,MATCH($B$2&"#"&21,Equity!$P:$P,0)),"") | B36: =IFERROR(INDEX(Equity!$C:$C,MATCH($B$2&"#"&21,Equity!$P:$P,0)),"") | C36: =IFERROR(INDEX(Equity!$D:$D,MATCH($B$2&"#"&21,Equity!$P:$P,0)),"") | D36: =IFERROR(INDEX(Equity!$E:$E,MATCH($B$2&"#"&21,Equity!$P:$P,0)),"") | E36: =IFERROR(INDEX(Equity!$I:$I,MATCH($B$2&"#"&21,Equity!$P:$P,0)),"") | F36: =IFERROR(INDEX(Equity!$K:$K,MATCH($B$2&"#"&21,Equity!$P:$P,0)),"") | G36: =IFERROR(INDEX(Equity!$N:$N,MATCH($B$2&"#"&21,Equity!$P:$P,0)),"")
A37: =IFERROR(INDEX(Equity!$B:$B,MATCH($B$2&"#"&22,Equity!$P:$P,0)),"") | B37: =IFERROR(INDEX(Equity!$C:$C,MATCH($B$2&"#"&22,Equity!$P:$P,0)),"") | C37: =IFERROR(INDEX(Equity!$D:$D,MATCH($B$2&"#"&22,Equity!$P:$P,0)),"") | D37: =IFERROR(INDEX(Equity!$E:$E,MATCH($B$2&"#"&22,Equity!$P:$P,0)),"") | E37: =IFERROR(INDEX(Equity!$I:$I,MATCH($B$2&"#"&22,Equity!$P:$P,0)),"") | F37: =IFERROR(INDEX(Equity!$K:$K,MATCH($B$2&"#"&22,Equity!$P:$P,0)),"") | G37: =IFERROR(INDEX(Equity!$N:$N,MATCH($B$2&"#"&22,Equity!$P:$P,0)),"")
A38: =IFERROR(INDEX(Equity!$B:$B,MATCH($B$2&"#"&23,Equity!$P:$P,0)),"") | B38: =IFERROR(INDEX(Equity!$C:$C,MATCH($B$2&"#"&23,Equity!$P:$P,0)),"") | C38: =IFERROR(INDEX(Equity!$D:$D,MATCH($B$2&"#"&23,Equity!$P:$P,0)),"") | D38: =IFERROR(INDEX(Equity!$E:$E,MATCH($B$2&"#"&23,Equity!$P:$P,0)),"") | E38: =IFERROR(INDEX(Equity!$I:$I,MATCH($B$2&"#"&23,Equity!$P:$P,0)),"") | F38: =IFERROR(INDEX(Equity!$K:$K,MATCH($B$2&"#"&23,Equity!$P:$P,0)),"") | G38: =IFERROR(INDEX(Equity!$N:$N,MATCH($B$2&"#"&23,Equity!$P:$P,0)),"")
A39: =IFERROR(INDEX(Equity!$B:$B,MATCH($B$2&"#"&24,Equity!$P:$P,0)),"") | B39: =IFERROR(INDEX(Equity!$C:$C,MATCH($B$2&"#"&24,Equity!$P:$P,0)),"") | C39: =IFERROR(INDEX(Equity!$D:$D,MATCH($B$2&"#"&24,Equity!$P:$P,0)),"") | D39: =IFERROR(INDEX(Equity!$E:$E,MATCH($B$2&"#"&24,Equity!$P:$P,0)),"") | E39: =IFERROR(INDEX(Equity!$I:$I,MATCH($B$2&"#"&24,Equity!$P:$P,0)),"") | F39: =IFERROR(INDEX(Equity!$K:$K,MATCH($B$2&"#"&24,Equity!$P:$P,0)),"") | G39: =IFERROR(INDEX(Equity!$N:$N,MATCH($B$2&"#"&24,Equity!$P:$P,0)),"")
A40: =IFERROR(INDEX(Equity!$B:$B,MATCH($B$2&"#"&25,Equity!$P:$P,0)),"") | B40: =IFERROR(INDEX(Equity!$C:$C,MATCH($B$2&"#"&25,Equity!$P:$P,0)),"") | C40: =IFERROR(INDEX(Equity!$D:$D,MATCH($B$2&"#"&25,Equity!$P:$P,0)),"") | D40: =IFERROR(INDEX(Equity!$E:$E,MATCH($B$2&"#"&25,Equity!$P:$P,0)),"") | E40: =IFERROR(INDEX(Equity!$I:$I,MATCH($B$2&"#"&25,Equity!$P:$P,0)),"") | F40: =IFERROR(INDEX(Equity!$K:$K,MATCH($B$2&"#"&25,Equity!$P:$P,0)),"") | G40: =IFERROR(INDEX(Equity!$N:$N,MATCH($B$2&"#"&25,Equity!$P:$P,0)),"")
A41: =IFERROR(INDEX(Equity!$B:$B,MATCH($B$2&"#"&26,Equity!$P:$P,0)),"") | B41: =IFERROR(INDEX(Equity!$C:$C,MATCH($B$2&"#"&26,Equity!$P:$P,0)),"") | C41: =IFERROR(INDEX(Equity!$D:$D,MATCH($B$2&"#"&26,Equity!$P:$P,0)),"") | D41: =IFERROR(INDEX(Equity!$E:$E,MATCH($B$2&"#"&26,Equity!$P:$P,0)),"") | E41: =IFERROR(INDEX(Equity!$I:$I,MATCH($B$2&"#"&26,Equity!$P:$P,0)),"") | F41: =IFERROR(INDEX(Equity!$K:$K,MATCH($B$2&"#"&26,Equity!$P:$P,0)),"") | G41: =IFERROR(INDEX(Equity!$N:$N,MATCH($B$2&"#"&26,Equity!$P:$P,0)),"")
A42: =IFERROR(INDEX(Equity!$B:$B,MATCH($B$2&"#"&27,Equity!$P:$P,0)),"") | B42: =IFERROR(INDEX(Equity!$C:$C,MATCH($B$2&"#"&27,Equity!$P:$P,0)),"") | C42: =IFERROR(INDEX(Equity!$D:$D,MATCH($B$2&"#"&27,Equity!$P:$P,0)),"") | D42: =IFERROR(INDEX(Equity!$E:$E,MATCH($B$2&"#"&27,Equity!$P:$P,0)),"") | E42: =IFERROR(INDEX(Equity!$I:$I,MATCH($B$2&"#"&27,Equity!$P:$P,0)),"") | F42: =IFERROR(INDEX(Equity!$K:$K,MATCH($B$2&"#"&27,Equity!$P:$P,0)),"") | G42: =IFERROR(INDEX(Equity!$N:$N,MATCH($B$2&"#"&27,Equity!$P:$P,0)),"")
A43: =IFERROR(INDEX(Equity!$B:$B,MATCH($B$2&"#"&28,Equity!$P:$P,0)),"") | B43: =IFERROR(INDEX(Equity!$C:$C,MATCH($B$2&"#"&28,Equity!$P:$P,0)),"") | C43: =IFERROR(INDEX(Equity!$D:$D,MATCH($B$2&"#"&28,Equity!$P:$P,0)),"") | D43: =IFERROR(INDEX(Equity!$E:$E,MATCH($B$2&"#"&28,Equity!$P:$P,0)),"") | E43: =IFERROR(INDEX(Equity!$I:$I,MATCH($B$2&"#"&28,Equity!$P:$P,0)),"") | F43: =IFERROR(INDEX(Equity!$K:$K,MATCH($B$2&"#"&28,Equity!$P:$P,0)),"") | G43: =IFERROR(INDEX(Equity!$N:$N,MATCH($B$2&"#"&28,Equity!$P:$P,0)),"")
A44: =IFERROR(INDEX(Equity!$B:$B,MATCH($B$2&"#"&29,Equity!$P:$P,0)),"") | B44: =IFERROR(INDEX(Equity!$C:$C,MATCH($B$2&"#"&29,Equity!$P:$P,0)),"") | C44: =IFERROR(INDEX(Equity!$D:$D,MATCH($B$2&"#"&29,Equity!$P:$P,0)),"") | D44: =IFERROR(INDEX(Equity!$E:$E,MATCH($B$2&"#"&29,Equity!$P:$P,0)),"") | E44: =IFERROR(INDEX(Equity!$I:$I,MATCH($B$2&"#"&29,Equity!$P:$P,0)),"") | F44: =IFERROR(INDEX(Equity!$K:$K,MATCH($B$2&"#"&29,Equity!$P:$P,0)),"") | G44: =IFERROR(INDEX(Equity!$N:$N,MATCH($B$2&"#"&29,Equity!$P:$P,0)),"")
A45: =IFERROR(INDEX(Equity!$B:$B,MATCH($B$2&"#"&30,Equity!$P:$P,0)),"") | B45: =IFERROR(INDEX(Equity!$C:$C,MATCH($B$2&"#"&30,Equity!$P:$P,0)),"") | C45: =IFERROR(INDEX(Equity!$D:$D,MATCH($B$2&"#"&30,Equity!$P:$P,0)),"") | D45: =IFERROR(INDEX(Equity!$E:$E,MATCH($B$2&"#"&30,Equity!$P:$P,0)),"") | E45: =IFERROR(INDEX(Equity!$I:$I,MATCH($B$2&"#"&30,Equity!$P:$P,0)),"") | F45: =IFERROR(INDEX(Equity!$K:$K,MATCH($B$2&"#"&30,Equity!$P:$P,0)),"") | G45: =IFERROR(INDEX(Equity!$N:$N,MATCH($B$2&"#"&30,Equity!$P:$P,0)),"")
A46: =IFERROR(INDEX(Equity!$B:$B,MATCH($B$2&"#"&31,Equity!$P:$P,0)),"") | B46: =IFERROR(INDEX(Equity!$C:$C,MATCH($B$2&"#"&31,Equity!$P:$P,0)),"") | C46: =IFERROR(INDEX(Equity!$D:$D,MATCH($B$2&"#"&31,Equity!$P:$P,0)),"") | D46: =IFERROR(INDEX(Equity!$E:$E,MATCH($B$2&"#"&31,Equity!$P:$P,0)),"") | E46: =IFERROR(INDEX(Equity!$I:$I,MATCH($B$2&"#"&31,Equity!$P:$P,0)),"") | F46: =IFERROR(INDEX(Equity!$K:$K,MATCH($B$2&"#"&31,Equity!$P:$P,0)),"") | G46: =IFERROR(INDEX(Equity!$N:$N,MATCH($B$2&"#"&31,Equity!$P:$P,0)),"")
A47: =IFERROR(INDEX(Equity!$B:$B,MATCH($B$2&"#"&32,Equity!$P:$P,0)),"") | B47: =IFERROR(INDEX(Equity!$C:$C,MATCH($B$2&"#"&32,Equity!$P:$P,0)),"") | C47: =IFERROR(INDEX(Equity!$D:$D,MATCH($B$2&"#"&32,Equity!$P:$P,0)),"") | D47: =IFERROR(INDEX(Equity!$E:$E,MATCH($B$2&"#"&32,Equity!$P:$P,0)),"") | E47: =IFERROR(INDEX(Equity!$I:$I,MATCH($B$2&"#"&32,Equity!$P:$P,0)),"") | F47: =IFERROR(INDEX(Equity!$K:$K,MATCH($B$2&"#"&32,Equity!$P:$P,0)),"") | G47: =IFERROR(INDEX(Equity!$N:$N,MATCH($B$2&"#"&32,Equity!$P:$P,0)),"")
A48: =IFERROR(INDEX(Equity!$B:$B,MATCH($B$2&"#"&33,Equity!$P:$P,0)),"") | B48: =IFERROR(INDEX(Equity!$C:$C,MATCH($B$2&"#"&33,Equity!$P:$P,0)),"") | C48: =IFERROR(INDEX(Equity!$D:$D,MATCH($B$2&"#"&33,Equity!$P:$P,0)),"") | D48: =IFERROR(INDEX(Equity!$E:$E,MATCH($B$2&"#"&33,Equity!$P:$P,0)),"") | E48: =IFERROR(INDEX(Equity!$I:$I,MATCH($B$2&"#"&33,Equity!$P:$P,0)),"") | F48: =IFERROR(INDEX(Equity!$K:$K,MATCH($B$2&"#"&33,Equity!$P:$P,0)),"") | G48: =IFERROR(INDEX(Equity!$N:$N,MATCH($B$2&"#"&33,Equity!$P:$P,0)),"")
A49: =IFERROR(INDEX(Equity!$B:$B,MATCH($B$2&"#"&34,Equity!$P:$P,0)),"") | B49: =IFERROR(INDEX(Equity!$C:$C,MATCH($B$2&"#"&34,Equity!$P:$P,0)),"") | C49: =IFERROR(INDEX(Equity!$D:$D,MATCH($B$2&"#"&34,Equity!$P:$P,0)),"") | D49: =IFERROR(INDEX(Equity!$E:$E,MATCH($B$2&"#"&34,Equity!$P:$P,0)),"") | E49: =IFERROR(INDEX(Equity!$I:$I,MATCH($B$2&"#"&34,Equity!$P:$P,0)),"") | F49: =IFERROR(INDEX(Equity!$K:$K,MATCH($B$2&"#"&34,Equity!$P:$P,0)),"") | G49: =IFERROR(INDEX(Equity!$N:$N,MATCH($B$2&"#"&34,Equity!$P:$P,0)),"")
A50: =IFERROR(INDEX(Equity!$B:$B,MATCH($B$2&"#"&35,Equity!$P:$P,0)),"") | B50: =IFERROR(INDEX(Equity!$C:$C,MATCH($B$2&"#"&35,Equity!$P:$P,0)),"") | C50: =IFERROR(INDEX(Equity!$D:$D,MATCH($B$2&"#"&35,Equity!$P:$P,0)),"") | D50: =IFERROR(INDEX(Equity!$E:$E,MATCH($B$2&"#"&35,Equity!$P:$P,0)),"") | E50: =IFERROR(INDEX(Equity!$I:$I,MATCH($B$2&"#"&35,Equity!$P:$P,0)),"") | F50: =IFERROR(INDEX(Equity!$K:$K,MATCH($B$2&"#"&35,Equity!$P:$P,0)),"") | G50: =IFERROR(INDEX(Equity!$N:$N,MATCH($B$2&"#"&35,Equity!$P:$P,0)),"")
A51: =IFERROR(INDEX(Equity!$B:$B,MATCH($B$2&"#"&36,Equity!$P:$P,0)),"") | B51: =IFERROR(INDEX(Equity!$C:$C,MATCH($B$2&"#"&36,Equity!$P:$P,0)),"") | C51: =IFERROR(INDEX(Equity!$D:$D,MATCH($B$2&"#"&36,Equity!$P:$P,0)),"") | D51: =IFERROR(INDEX(Equity!$E:$E,MATCH($B$2&"#"&36,Equity!$P:$P,0)),"") | E51: =IFERROR(INDEX(Equity!$I:$I,MATCH($B$2&"#"&36,Equity!$P:$P,0)),"") | F51: =IFERROR(INDEX(Equity!$K:$K,MATCH($B$2&"#"&36,Equity!$P:$P,0)),"") | G51: =IFERROR(INDEX(Equity!$N:$N,MATCH($B$2&"#"&36,Equity!$P:$P,0)),"")
A52: =IFERROR(INDEX(Equity!$B:$B,MATCH($B$2&"#"&37,Equity!$P:$P,0)),"") | B52: =IFERROR(INDEX(Equity!$C:$C,MATCH($B$2&"#"&37,Equity!$P:$P,0)),"") | C52: =IFERROR(INDEX(Equity!$D:$D,MATCH($B$2&"#"&37,Equity!$P:$P,0)),"") | D52: =IFERROR(INDEX(Equity!$E:$E,MATCH($B$2&"#"&37,Equity!$P:$P,0)),"") | E52: =IFERROR(INDEX(Equity!$I:$I,MATCH($B$2&"#"&37,Equity!$P:$P,0)),"") | F52: =IFERROR(INDEX(Equity!$K:$K,MATCH($B$2&"#"&37,Equity!$P:$P,0)),"") | G52: =IFERROR(INDEX(Equity!$N:$N,MATCH($B$2&"#"&37,Equity!$P:$P,0)),"")
A53: =IFERROR(INDEX(Equity!$B:$B,MATCH($B$2&"#"&38,Equity!$P:$P,0)),"") | B53: =IFERROR(INDEX(Equity!$C:$C,MATCH($B$2&"#"&38,Equity!$P:$P,0)),"") | C53: =IFERROR(INDEX(Equity!$D:$D,MATCH($B$2&"#"&38,Equity!$P:$P,0)),"") | D53: =IFERROR(INDEX(Equity!$E:$E,MATCH($B$2&"#"&38,Equity!$P:$P,0)),"") | E53: =IFERROR(INDEX(Equity!$I:$I,MATCH($B$2&"#"&38,Equity!$P:$P,0)),"") | F53: =IFERROR(INDEX(Equity!$K:$K,MATCH($B$2&"#"&38,Equity!$P:$P,0)),"") | G53: =IFERROR(INDEX(Equity!$N:$N,MATCH($B$2&"#"&38,Equity!$P:$P,0)),"")
A54: =IFERROR(INDEX(Equity!$B:$B,MATCH($B$2&"#"&39,Equity!$P:$P,0)),"") | B54: =IFERROR(INDEX(Equity!$C:$C,MATCH($B$2&"#"&39,Equity!$P:$P,0)),"") | C54: =IFERROR(INDEX(Equity!$D:$D,MATCH($B$2&"#"&39,Equity!$P:$P,0)),"") | D54: =IFERROR(INDEX(Equity!$E:$E,MATCH($B$2&"#"&39,Equity!$P:$P,0)),"") | E54: =IFERROR(INDEX(Equity!$I:$I,MATCH($B$2&"#"&39,Equity!$P:$P,0)),"") | F54: =IFERROR(INDEX(Equity!$K:$K,MATCH($B$2&"#"&39,Equity!$P:$P,0)),"") | G54: =IFERROR(INDEX(Equity!$N:$N,MATCH($B$2&"#"&39,Equity!$P:$P,0)),"")
A55: =IFERROR(INDEX(Equity!$B:$B,MATCH($B$2&"#"&40,Equity!$P:$P,0)),"") | B55: =IFERROR(INDEX(Equity!$C:$C,MATCH($B$2&"#"&40,Equity!$P:$P,0)),"") | C55: =IFERROR(INDEX(Equity!$D:$D,MATCH($B$2&"#"&40,Equity!$P:$P,0)),"") | D55: =IFERROR(INDEX(Equity!$E:$E,MATCH($B$2&"#"&40,Equity!$P:$P,0)),"") | E55: =IFERROR(INDEX(Equity!$I:$I,MATCH($B$2&"#"&40,Equity!$P:$P,0)),"") | F55: =IFERROR(INDEX(Equity!$K:$K,MATCH($B$2&"#"&40,Equity!$P:$P,0)),"") | G55: =IFERROR(INDEX(Equity!$N:$N,MATCH($B$2&"#"&40,Equity!$P:$P,0)),"")
A57: MUTUAL FUNDS
A58: Fund House | B58: Scheme | C58: Units | D58: Cur NAV | E58: Cur. val | F58: Net chg. | G58: XIRR
A59: =IFERROR(INDEX(MutualFunds!$B:$B,MATCH($B$2&"#"&1,MutualFunds!$N:$N,0)),"") | B59: =IFERROR(INDEX(MutualFunds!$C:$C,MATCH($B$2&"#"&1,MutualFunds!$N:$N,0)),"") | C59: =IFERROR(INDEX(MutualFunds!$E:$E,MATCH($B$2&"#"&1,MutualFunds!$N:$N,0)),"") | D59: =IFERROR(INDEX(MutualFunds!$G:$G,MATCH($B$2&"#"&1,MutualFunds!$N:$N,0)),"") | E59: =IFERROR(INDEX(MutualFunds!$I:$I,MATCH($B$2&"#"&1,MutualFunds!$N:$N,0)),"") | F59: =IFERROR(INDEX(MutualFunds!$J:$J,MATCH($B$2&"#"&1,MutualFunds!$N:$N,0)),"") | G59: =IFERROR(INDEX(MutualFunds!$L:$L,MATCH($B$2&"#"&1,MutualFunds!$N:$N,0)),"")
A60: =IFERROR(INDEX(MutualFunds!$B:$B,MATCH($B$2&"#"&2,MutualFunds!$N:$N,0)),"") | B60: =IFERROR(INDEX(MutualFunds!$C:$C,MATCH($B$2&"#"&2,MutualFunds!$N:$N,0)),"") | C60: =IFERROR(INDEX(MutualFunds!$E:$E,MATCH($B$2&"#"&2,MutualFunds!$N:$N,0)),"") | D60: =IFERROR(INDEX(MutualFunds!$G:$G,MATCH($B$2&"#"&2,MutualFunds!$N:$N,0)),"") | E60: =IFERROR(INDEX(MutualFunds!$I:$I,MATCH($B$2&"#"&2,MutualFunds!$N:$N,0)),"") | F60: =IFERROR(INDEX(MutualFunds!$J:$J,MATCH($B$2&"#"&2,MutualFunds!$N:$N,0)),"") | G60: =IFERROR(INDEX(MutualFunds!$L:$L,MATCH($B$2&"#"&2,MutualFunds!$N:$N,0)),"")
A61: =IFERROR(INDEX(MutualFunds!$B:$B,MATCH($B$2&"#"&3,MutualFunds!$N:$N,0)),"") | B61: =IFERROR(INDEX(MutualFunds!$C:$C,MATCH($B$2&"#"&3,MutualFunds!$N:$N,0)),"") | C61: =IFERROR(INDEX(MutualFunds!$E:$E,MATCH($B$2&"#"&3,MutualFunds!$N:$N,0)),"") | D61: =IFERROR(INDEX(MutualFunds!$G:$G,MATCH($B$2&"#"&3,MutualFunds!$N:$N,0)),"") | E61: =IFERROR(INDEX(MutualFunds!$I:$I,MATCH($B$2&"#"&3,MutualFunds!$N:$N,0)),"") | F61: =IFERROR(INDEX(MutualFunds!$J:$J,MATCH($B$2&"#"&3,MutualFunds!$N:$N,0)),"") | G61: =IFERROR(INDEX(MutualFunds!$L:$L,MATCH($B$2&"#"&3,MutualFunds!$N:$N,0)),"")
A62: =IFERROR(INDEX(MutualFunds!$B:$B,MATCH($B$2&"#"&4,MutualFunds!$N:$N,0)),"") | B62: =IFERROR(INDEX(MutualFunds!$C:$C,MATCH($B$2&"#"&4,MutualFunds!$N:$N,0)),"") | C62: =IFERROR(INDEX(MutualFunds!$E:$E,MATCH($B$2&"#"&4,MutualFunds!$N:$N,0)),"") | D62: =IFERROR(INDEX(MutualFunds!$G:$G,MATCH($B$2&"#"&4,MutualFunds!$N:$N,0)),"") | E62: =IFERROR(INDEX(MutualFunds!$I:$I,MATCH($B$2&"#"&4,MutualFunds!$N:$N,0)),"") | F62: =IFERROR(INDEX(MutualFunds!$J:$J,MATCH($B$2&"#"&4,MutualFunds!$N:$N,0)),"") | G62: =IFERROR(INDEX(MutualFunds!$L:$L,MATCH($B$2&"#"&4,MutualFunds!$N:$N,0)),"")
A63: =IFERROR(INDEX(MutualFunds!$B:$B,MATCH($B$2&"#"&5,MutualFunds!$N:$N,0)),"") | B63: =IFERROR(INDEX(MutualFunds!$C:$C,MATCH($B$2&"#"&5,MutualFunds!$N:$N,0)),"") | C63: =IFERROR(INDEX(MutualFunds!$E:$E,MATCH($B$2&"#"&5,MutualFunds!$N:$N,0)),"") | D63: =IFERROR(INDEX(MutualFunds!$G:$G,MATCH($B$2&"#"&5,MutualFunds!$N:$N,0)),"") | E63: =IFERROR(INDEX(MutualFunds!$I:$I,MATCH($B$2&"#"&5,MutualFunds!$N:$N,0)),"") | F63: =IFERROR(INDEX(MutualFunds!$J:$J,MATCH($B$2&"#"&5,MutualFunds!$N:$N,0)),"") | G63: =IFERROR(INDEX(MutualFunds!$L:$L,MATCH($B$2&"#"&5,MutualFunds!$N:$N,0)),"")
A64: =IFERROR(INDEX(MutualFunds!$B:$B,MATCH($B$2&"#"&6,MutualFunds!$N:$N,0)),"") | B64: =IFERROR(INDEX(MutualFunds!$C:$C,MATCH($B$2&"#"&6,MutualFunds!$N:$N,0)),"") | C64: =IFERROR(INDEX(MutualFunds!$E:$E,MATCH($B$2&"#"&6,MutualFunds!$N:$N,0)),"") | D64: =IFERROR(INDEX(MutualFunds!$G:$G,MATCH($B$2&"#"&6,MutualFunds!$N:$N,0)),"") | E64: =IFERROR(INDEX(MutualFunds!$I:$I,MATCH($B$2&"#"&6,MutualFunds!$N:$N,0)),"") | F64: =IFERROR(INDEX(MutualFunds!$J:$J,MATCH($B$2&"#"&6,MutualFunds!$N:$N,0)),"") | G64: =IFERROR(INDEX(MutualFunds!$L:$L,MATCH($B$2&"#"&6,MutualFunds!$N:$N,0)),"")
A65: =IFERROR(INDEX(MutualFunds!$B:$B,MATCH($B$2&"#"&7,MutualFunds!$N:$N,0)),"") | B65: =IFERROR(INDEX(MutualFunds!$C:$C,MATCH($B$2&"#"&7,MutualFunds!$N:$N,0)),"") | C65: =IFERROR(INDEX(MutualFunds!$E:$E,MATCH($B$2&"#"&7,MutualFunds!$N:$N,0)),"") | D65: =IFERROR(INDEX(MutualFunds!$G:$G,MATCH($B$2&"#"&7,MutualFunds!$N:$N,0)),"") | E65: =IFERROR(INDEX(MutualFunds!$I:$I,MATCH($B$2&"#"&7,MutualFunds!$N:$N,0)),"") | F65: =IFERROR(INDEX(MutualFunds!$J:$J,MATCH($B$2&"#"&7,MutualFunds!$N:$N,0)),"") | G65: =IFERROR(INDEX(MutualFunds!$L:$L,MATCH($B$2&"#"&7,MutualFunds!$N:$N,0)),"")
A66: =IFERROR(INDEX(MutualFunds!$B:$B,MATCH($B$2&"#"&8,MutualFunds!$N:$N,0)),"") | B66: =IFERROR(INDEX(MutualFunds!$C:$C,MATCH($B$2&"#"&8,MutualFunds!$N:$N,0)),"") | C66: =IFERROR(INDEX(MutualFunds!$E:$E,MATCH($B$2&"#"&8,MutualFunds!$N:$N,0)),"") | D66: =IFERROR(INDEX(MutualFunds!$G:$G,MATCH($B$2&"#"&8,MutualFunds!$N:$N,0)),"") | E66: =IFERROR(INDEX(MutualFunds!$I:$I,MATCH($B$2&"#"&8,MutualFunds!$N:$N,0)),"") | F66: =IFERROR(INDEX(MutualFunds!$J:$J,MATCH($B$2&"#"&8,MutualFunds!$N:$N,0)),"") | G66: =IFERROR(INDEX(MutualFunds!$L:$L,MATCH($B$2&"#"&8,MutualFunds!$N:$N,0)),"")
A67: =IFERROR(INDEX(MutualFunds!$B:$B,MATCH($B$2&"#"&9,MutualFunds!$N:$N,0)),"") | B67: =IFERROR(INDEX(MutualFunds!$C:$C,MATCH($B$2&"#"&9,MutualFunds!$N:$N,0)),"") | C67: =IFERROR(INDEX(MutualFunds!$E:$E,MATCH($B$2&"#"&9,MutualFunds!$N:$N,0)),"") | D67: =IFERROR(INDEX(MutualFunds!$G:$G,MATCH($B$2&"#"&9,MutualFunds!$N:$N,0)),"") | E67: =IFERROR(INDEX(MutualFunds!$I:$I,MATCH($B$2&"#"&9,MutualFunds!$N:$N,0)),"") | F67: =IFERROR(INDEX(MutualFunds!$J:$J,MATCH($B$2&"#"&9,MutualFunds!$N:$N,0)),"") | G67: =IFERROR(INDEX(MutualFunds!$L:$L,MATCH($B$2&"#"&9,MutualFunds!$N:$N,0)),"")
A68: =IFERROR(INDEX(MutualFunds!$B:$B,MATCH($B$2&"#"&10,MutualFunds!$N:$N,0)),"") | B68: =IFERROR(INDEX(MutualFunds!$C:$C,MATCH($B$2&"#"&10,MutualFunds!$N:$N,0)),"") | C68: =IFERROR(INDEX(MutualFunds!$E:$E,MATCH($B$2&"#"&10,MutualFunds!$N:$N,0)),"") | D68: =IFERROR(INDEX(MutualFunds!$G:$G,MATCH($B$2&"#"&10,MutualFunds!$N:$N,0)),"") | E68: =IFERROR(INDEX(MutualFunds!$I:$I,MATCH($B$2&"#"&10,MutualFunds!$N:$N,0)),"") | F68: =IFERROR(INDEX(MutualFunds!$J:$J,MATCH($B$2&"#"&10,MutualFunds!$N:$N,0)),"") | G68: =IFERROR(INDEX(MutualFunds!$L:$L,MATCH($B$2&"#"&10,MutualFunds!$N:$N,0)),"")
A69: =IFERROR(INDEX(MutualFunds!$B:$B,MATCH($B$2&"#"&11,MutualFunds!$N:$N,0)),"") | B69: =IFERROR(INDEX(MutualFunds!$C:$C,MATCH($B$2&"#"&11,MutualFunds!$N:$N,0)),"") | C69: =IFERROR(INDEX(MutualFunds!$E:$E,MATCH($B$2&"#"&11,MutualFunds!$N:$N,0)),"") | D69: =IFERROR(INDEX(MutualFunds!$G:$G,MATCH($B$2&"#"&11,MutualFunds!$N:$N,0)),"") | E69: =IFERROR(INDEX(MutualFunds!$I:$I,MATCH($B$2&"#"&11,MutualFunds!$N:$N,0)),"") | F69: =IFERROR(INDEX(MutualFunds!$J:$J,MATCH($B$2&"#"&11,MutualFunds!$N:$N,0)),"") | G69: =IFERROR(INDEX(MutualFunds!$L:$L,MATCH($B$2&"#"&11,MutualFunds!$N:$N,0)),"")
A70: =IFERROR(INDEX(MutualFunds!$B:$B,MATCH($B$2&"#"&12,MutualFunds!$N:$N,0)),"") | B70: =IFERROR(INDEX(MutualFunds!$C:$C,MATCH($B$2&"#"&12,MutualFunds!$N:$N,0)),"") | C70: =IFERROR(INDEX(MutualFunds!$E:$E,MATCH($B$2&"#"&12,MutualFunds!$N:$N,0)),"") | D70: =IFERROR(INDEX(MutualFunds!$G:$G,MATCH($B$2&"#"&12,MutualFunds!$N:$N,0)),"") | E70: =IFERROR(INDEX(MutualFunds!$I:$I,MATCH($B$2&"#"&12,MutualFunds!$N:$N,0)),"") | F70: =IFERROR(INDEX(MutualFunds!$J:$J,MATCH($B$2&"#"&12,MutualFunds!$N:$N,0)),"") | G70: =IFERROR(INDEX(MutualFunds!$L:$L,MATCH($B$2&"#"&12,MutualFunds!$N:$N,0)),"")
A71: =IFERROR(INDEX(MutualFunds!$B:$B,MATCH($B$2&"#"&13,MutualFunds!$N:$N,0)),"") | B71: =IFERROR(INDEX(MutualFunds!$C:$C,MATCH($B$2&"#"&13,MutualFunds!$N:$N,0)),"") | C71: =IFERROR(INDEX(MutualFunds!$E:$E,MATCH($B$2&"#"&13,MutualFunds!$N:$N,0)),"") | D71: =IFERROR(INDEX(MutualFunds!$G:$G,MATCH($B$2&"#"&13,MutualFunds!$N:$N,0)),"") | E71: =IFERROR(INDEX(MutualFunds!$I:$I,MATCH($B$2&"#"&13,MutualFunds!$N:$N,0)),"") | F71: =IFERROR(INDEX(MutualFunds!$J:$J,MATCH($B$2&"#"&13,MutualFunds!$N:$N,0)),"") | G71: =IFERROR(INDEX(MutualFunds!$L:$L,MATCH($B$2&"#"&13,MutualFunds!$N:$N,0)),"")
A72: =IFERROR(INDEX(MutualFunds!$B:$B,MATCH($B$2&"#"&14,MutualFunds!$N:$N,0)),"") | B72: =IFERROR(INDEX(MutualFunds!$C:$C,MATCH($B$2&"#"&14,MutualFunds!$N:$N,0)),"") | C72: =IFERROR(INDEX(MutualFunds!$E:$E,MATCH($B$2&"#"&14,MutualFunds!$N:$N,0)),"") | D72: =IFERROR(INDEX(MutualFunds!$G:$G,MATCH($B$2&"#"&14,MutualFunds!$N:$N,0)),"") | E72: =IFERROR(INDEX(MutualFunds!$I:$I,MATCH($B$2&"#"&14,MutualFunds!$N:$N,0)),"") | F72: =IFERROR(INDEX(MutualFunds!$J:$J,MATCH($B$2&"#"&14,MutualFunds!$N:$N,0)),"") | G72: =IFERROR(INDEX(MutualFunds!$L:$L,MATCH($B$2&"#"&14,MutualFunds!$N:$N,0)),"")
A73: =IFERROR(INDEX(MutualFunds!$B:$B,MATCH($B$2&"#"&15,MutualFunds!$N:$N,0)),"") | B73: =IFERROR(INDEX(MutualFunds!$C:$C,MATCH($B$2&"#"&15,MutualFunds!$N:$N,0)),"") | C73: =IFERROR(INDEX(MutualFunds!$E:$E,MATCH($B$2&"#"&15,MutualFunds!$N:$N,0)),"") | D73: =IFERROR(INDEX(MutualFunds!$G:$G,MATCH($B$2&"#"&15,MutualFunds!$N:$N,0)),"") | E73: =IFERROR(INDEX(MutualFunds!$I:$I,MATCH($B$2&"#"&15,MutualFunds!$N:$N,0)),"") | F73: =IFERROR(INDEX(MutualFunds!$J:$J,MATCH($B$2&"#"&15,MutualFunds!$N:$N,0)),"") | G73: =IFERROR(INDEX(MutualFunds!$L:$L,MATCH($B$2&"#"&15,MutualFunds!$N:$N,0)),"")
A74: =IFERROR(INDEX(MutualFunds!$B:$B,MATCH($B$2&"#"&16,MutualFunds!$N:$N,0)),"") | B74: =IFERROR(INDEX(MutualFunds!$C:$C,MATCH($B$2&"#"&16,MutualFunds!$N:$N,0)),"") | C74: =IFERROR(INDEX(MutualFunds!$E:$E,MATCH($B$2&"#"&16,MutualFunds!$N:$N,0)),"") | D74: =IFERROR(INDEX(MutualFunds!$G:$G,MATCH($B$2&"#"&16,MutualFunds!$N:$N,0)),"") | E74: =IFERROR(INDEX(MutualFunds!$I:$I,MATCH($B$2&"#"&16,MutualFunds!$N:$N,0)),"") | F74: =IFERROR(INDEX(MutualFunds!$J:$J,MATCH($B$2&"#"&16,MutualFunds!$N:$N,0)),"") | G74: =IFERROR(INDEX(MutualFunds!$L:$L,MATCH($B$2&"#"&16,MutualFunds!$N:$N,0)),"")
A75: =IFERROR(INDEX(MutualFunds!$B:$B,MATCH($B$2&"#"&17,MutualFunds!$N:$N,0)),"") | B75: =IFERROR(INDEX(MutualFunds!$C:$C,MATCH($B$2&"#"&17,MutualFunds!$N:$N,0)),"") | C75: =IFERROR(INDEX(MutualFunds!$E:$E,MATCH($B$2&"#"&17,MutualFunds!$N:$N,0)),"") | D75: =IFERROR(INDEX(MutualFunds!$G:$G,MATCH($B$2&"#"&17,MutualFunds!$N:$N,0)),"") | E75: =IFERROR(INDEX(MutualFunds!$I:$I,MATCH($B$2&"#"&17,MutualFunds!$N:$N,0)),"") | F75: =IFERROR(INDEX(MutualFunds!$J:$J,MATCH($B$2&"#"&17,MutualFunds!$N:$N,0)),"") | G75: =IFERROR(INDEX(MutualFunds!$L:$L,MATCH($B$2&"#"&17,MutualFunds!$N:$N,0)),"")
A76: =IFERROR(INDEX(MutualFunds!$B:$B,MATCH($B$2&"#"&18,MutualFunds!$N:$N,0)),"") | B76: =IFERROR(INDEX(MutualFunds!$C:$C,MATCH($B$2&"#"&18,MutualFunds!$N:$N,0)),"") | C76: =IFERROR(INDEX(MutualFunds!$E:$E,MATCH($B$2&"#"&18,MutualFunds!$N:$N,0)),"") | D76: =IFERROR(INDEX(MutualFunds!$G:$G,MATCH($B$2&"#"&18,MutualFunds!$N:$N,0)),"") | E76: =IFERROR(INDEX(MutualFunds!$I:$I,MATCH($B$2&"#"&18,MutualFunds!$N:$N,0)),"") | F76: =IFERROR(INDEX(MutualFunds!$J:$J,MATCH($B$2&"#"&18,MutualFunds!$N:$N,0)),"") | G76: =IFERROR(INDEX(MutualFunds!$L:$L,MATCH($B$2&"#"&18,MutualFunds!$N:$N,0)),"")
A77: =IFERROR(INDEX(MutualFunds!$B:$B,MATCH($B$2&"#"&19,MutualFunds!$N:$N,0)),"") | B77: =IFERROR(INDEX(MutualFunds!$C:$C,MATCH($B$2&"#"&19,MutualFunds!$N:$N,0)),"") | C77: =IFERROR(INDEX(MutualFunds!$E:$E,MATCH($B$2&"#"&19,MutualFunds!$N:$N,0)),"") | D77: =IFERROR(INDEX(MutualFunds!$G:$G,MATCH($B$2&"#"&19,MutualFunds!$N:$N,0)),"") | E77: =IFERROR(INDEX(MutualFunds!$I:$I,MATCH($B$2&"#"&19,MutualFunds!$N:$N,0)),"") | F77: =IFERROR(INDEX(MutualFunds!$J:$J,MATCH($B$2&"#"&19,MutualFunds!$N:$N,0)),"") | G77: =IFERROR(INDEX(MutualFunds!$L:$L,MATCH($B$2&"#"&19,MutualFunds!$N:$N,0)),"")
A78: =IFERROR(INDEX(MutualFunds!$B:$B,MATCH($B$2&"#"&20,MutualFunds!$N:$N,0)),"") | B78: =IFERROR(INDEX(MutualFunds!$C:$C,MATCH($B$2&"#"&20,MutualFunds!$N:$N,0)),"") | C78: =IFERROR(INDEX(MutualFunds!$E:$E,MATCH($B$2&"#"&20,MutualFunds!$N:$N,0)),"") | D78: =IFERROR(INDEX(MutualFunds!$G:$G,MATCH($B$2&"#"&20,MutualFunds!$N:$N,0)),"") | E78: =IFERROR(INDEX(MutualFunds!$I:$I,MATCH($B$2&"#"&20,MutualFunds!$N:$N,0)),"") | F78: =IFERROR(INDEX(MutualFunds!$J:$J,MATCH($B$2&"#"&20,MutualFunds!$N:$N,0)),"") | G78: =IFERROR(INDEX(MutualFunds!$L:$L,MATCH($B$2&"#"&20,MutualFunds!$N:$N,0)),"")
A80: FIXED DEPOSITS
A81: Bank | B81: Principal | C81: Rate % | D81: Maturity | E81: Value today
A82: =IFERROR(INDEX(FixedDeposits!$B:$B,MATCH($B$2&"#"&1,FixedDeposits!$L:$L,0)),"") -> SBI | B82: =IFERROR(INDEX(FixedDeposits!$D:$D,MATCH($B$2&"#"&1,FixedDeposits!$L:$L,0)),"") -> 300000 | C82: =IFERROR(INDEX(FixedDeposits!$E:$E,MATCH($B$2&"#"&1,FixedDeposits!$L:$L,0)),"") -> 6.8 | D82: =IFERROR(INDEX(FixedDeposits!$G:$G,MATCH($B$2&"#"&1,FixedDeposits!$L:$L,0)),"") -> 46767 | E82: =IFERROR(INDEX(FixedDeposits!$I:$I,MATCH($B$2&"#"&1,FixedDeposits!$L:$L,0)),"") -> 331868.19
A83: =IFERROR(INDEX(FixedDeposits!$B:$B,MATCH($B$2&"#"&2,FixedDeposits!$L:$L,0)),"") | B83: =IFERROR(INDEX(FixedDeposits!$D:$D,MATCH($B$2&"#"&2,FixedDeposits!$L:$L,0)),"") | C83: =IFERROR(INDEX(FixedDeposits!$E:$E,MATCH($B$2&"#"&2,FixedDeposits!$L:$L,0)),"") | D83: =IFERROR(INDEX(FixedDeposits!$G:$G,MATCH($B$2&"#"&2,FixedDeposits!$L:$L,0)),"") | E83: =IFERROR(INDEX(FixedDeposits!$I:$I,MATCH($B$2&"#"&2,FixedDeposits!$L:$L,0)),"")
A84: =IFERROR(INDEX(FixedDeposits!$B:$B,MATCH($B$2&"#"&3,FixedDeposits!$L:$L,0)),"") | B84: =IFERROR(INDEX(FixedDeposits!$D:$D,MATCH($B$2&"#"&3,FixedDeposits!$L:$L,0)),"") | C84: =IFERROR(INDEX(FixedDeposits!$E:$E,MATCH($B$2&"#"&3,FixedDeposits!$L:$L,0)),"") | D84: =IFERROR(INDEX(FixedDeposits!$G:$G,MATCH($B$2&"#"&3,FixedDeposits!$L:$L,0)),"") | E84: =IFERROR(INDEX(FixedDeposits!$I:$I,MATCH($B$2&"#"&3,FixedDeposits!$L:$L,0)),"")
A85: =IFERROR(INDEX(FixedDeposits!$B:$B,MATCH($B$2&"#"&4,FixedDeposits!$L:$L,0)),"") | B85: =IFERROR(INDEX(FixedDeposits!$D:$D,MATCH($B$2&"#"&4,FixedDeposits!$L:$L,0)),"") | C85: =IFERROR(INDEX(FixedDeposits!$E:$E,MATCH($B$2&"#"&4,FixedDeposits!$L:$L,0)),"") | D85: =IFERROR(INDEX(FixedDeposits!$G:$G,MATCH($B$2&"#"&4,FixedDeposits!$L:$L,0)),"") | E85: =IFERROR(INDEX(FixedDeposits!$I:$I,MATCH($B$2&"#"&4,FixedDeposits!$L:$L,0)),"")
A86: =IFERROR(INDEX(FixedDeposits!$B:$B,MATCH($B$2&"#"&5,FixedDeposits!$L:$L,0)),"") | B86: =IFERROR(INDEX(FixedDeposits!$D:$D,MATCH($B$2&"#"&5,FixedDeposits!$L:$L,0)),"") | C86: =IFERROR(INDEX(FixedDeposits!$E:$E,MATCH($B$2&"#"&5,FixedDeposits!$L:$L,0)),"") | D86: =IFERROR(INDEX(FixedDeposits!$G:$G,MATCH($B$2&"#"&5,FixedDeposits!$L:$L,0)),"") | E86: =IFERROR(INDEX(FixedDeposits!$I:$I,MATCH($B$2&"#"&5,FixedDeposits!$L:$L,0)),"")
A87: =IFERROR(INDEX(FixedDeposits!$B:$B,MATCH($B$2&"#"&6,FixedDeposits!$L:$L,0)),"") | B87: =IFERROR(INDEX(FixedDeposits!$D:$D,MATCH($B$2&"#"&6,FixedDeposits!$L:$L,0)),"") | C87: =IFERROR(INDEX(FixedDeposits!$E:$E,MATCH($B$2&"#"&6,FixedDeposits!$L:$L,0)),"") | D87: =IFERROR(INDEX(FixedDeposits!$G:$G,MATCH($B$2&"#"&6,FixedDeposits!$L:$L,0)),"") | E87: =IFERROR(INDEX(FixedDeposits!$I:$I,MATCH($B$2&"#"&6,FixedDeposits!$L:$L,0)),"")
A88: =IFERROR(INDEX(FixedDeposits!$B:$B,MATCH($B$2&"#"&7,FixedDeposits!$L:$L,0)),"") | B88: =IFERROR(INDEX(FixedDeposits!$D:$D,MATCH($B$2&"#"&7,FixedDeposits!$L:$L,0)),"") | C88: =IFERROR(INDEX(FixedDeposits!$E:$E,MATCH($B$2&"#"&7,FixedDeposits!$L:$L,0)),"") | D88: =IFERROR(INDEX(FixedDeposits!$G:$G,MATCH($B$2&"#"&7,FixedDeposits!$L:$L,0)),"") | E88: =IFERROR(INDEX(FixedDeposits!$I:$I,MATCH($B$2&"#"&7,FixedDeposits!$L:$L,0)),"")
A89: =IFERROR(INDEX(FixedDeposits!$B:$B,MATCH($B$2&"#"&8,FixedDeposits!$L:$L,0)),"") | B89: =IFERROR(INDEX(FixedDeposits!$D:$D,MATCH($B$2&"#"&8,FixedDeposits!$L:$L,0)),"") | C89: =IFERROR(INDEX(FixedDeposits!$E:$E,MATCH($B$2&"#"&8,FixedDeposits!$L:$L,0)),"") | D89: =IFERROR(INDEX(FixedDeposits!$G:$G,MATCH($B$2&"#"&8,FixedDeposits!$L:$L,0)),"") | E89: =IFERROR(INDEX(FixedDeposits!$I:$I,MATCH($B$2&"#"&8,FixedDeposits!$L:$L,0)),"")
A90: =IFERROR(INDEX(FixedDeposits!$B:$B,MATCH($B$2&"#"&9,FixedDeposits!$L:$L,0)),"") | B90: =IFERROR(INDEX(FixedDeposits!$D:$D,MATCH($B$2&"#"&9,FixedDeposits!$L:$L,0)),"") | C90: =IFERROR(INDEX(FixedDeposits!$E:$E,MATCH($B$2&"#"&9,FixedDeposits!$L:$L,0)),"") | D90: =IFERROR(INDEX(FixedDeposits!$G:$G,MATCH($B$2&"#"&9,FixedDeposits!$L:$L,0)),"") | E90: =IFERROR(INDEX(FixedDeposits!$I:$I,MATCH($B$2&"#"&9,FixedDeposits!$L:$L,0)),"")
A91: =IFERROR(INDEX(FixedDeposits!$B:$B,MATCH($B$2&"#"&10,FixedDeposits!$L:$L,0)),"") | B91: =IFERROR(INDEX(FixedDeposits!$D:$D,MATCH($B$2&"#"&10,FixedDeposits!$L:$L,0)),"") | C91: =IFERROR(INDEX(FixedDeposits!$E:$E,MATCH($B$2&"#"&10,FixedDeposits!$L:$L,0)),"") | D91: =IFERROR(INDEX(FixedDeposits!$G:$G,MATCH($B$2&"#"&10,FixedDeposits!$L:$L,0)),"") | E91: =IFERROR(INDEX(FixedDeposits!$I:$I,MATCH($B$2&"#"&10,FixedDeposits!$L:$L,0)),"")
A92: =IFERROR(INDEX(FixedDeposits!$B:$B,MATCH($B$2&"#"&11,FixedDeposits!$L:$L,0)),"") | B92: =IFERROR(INDEX(FixedDeposits!$D:$D,MATCH($B$2&"#"&11,FixedDeposits!$L:$L,0)),"") | C92: =IFERROR(INDEX(FixedDeposits!$E:$E,MATCH($B$2&"#"&11,FixedDeposits!$L:$L,0)),"") | D92: =IFERROR(INDEX(FixedDeposits!$G:$G,MATCH($B$2&"#"&11,FixedDeposits!$L:$L,0)),"") | E92: =IFERROR(INDEX(FixedDeposits!$I:$I,MATCH($B$2&"#"&11,FixedDeposits!$L:$L,0)),"")
A93: =IFERROR(INDEX(FixedDeposits!$B:$B,MATCH($B$2&"#"&12,FixedDeposits!$L:$L,0)),"") | B93: =IFERROR(INDEX(FixedDeposits!$D:$D,MATCH($B$2&"#"&12,FixedDeposits!$L:$L,0)),"") | C93: =IFERROR(INDEX(FixedDeposits!$E:$E,MATCH($B$2&"#"&12,FixedDeposits!$L:$L,0)),"") | D93: =IFERROR(INDEX(FixedDeposits!$G:$G,MATCH($B$2&"#"&12,FixedDeposits!$L:$L,0)),"") | E93: =IFERROR(INDEX(FixedDeposits!$I:$I,MATCH($B$2&"#"&12,FixedDeposits!$L:$L,0)),"")
A94: =IFERROR(INDEX(FixedDeposits!$B:$B,MATCH($B$2&"#"&13,FixedDeposits!$L:$L,0)),"") | B94: =IFERROR(INDEX(FixedDeposits!$D:$D,MATCH($B$2&"#"&13,FixedDeposits!$L:$L,0)),"") | C94: =IFERROR(INDEX(FixedDeposits!$E:$E,MATCH($B$2&"#"&13,FixedDeposits!$L:$L,0)),"") | D94: =IFERROR(INDEX(FixedDeposits!$G:$G,MATCH($B$2&"#"&13,FixedDeposits!$L:$L,0)),"") | E94: =IFERROR(INDEX(FixedDeposits!$I:$I,MATCH($B$2&"#"&13,FixedDeposits!$L:$L,0)),"")
A95: =IFERROR(INDEX(FixedDeposits!$B:$B,MATCH($B$2&"#"&14,FixedDeposits!$L:$L,0)),"") | B95: =IFERROR(INDEX(FixedDeposits!$D:$D,MATCH($B$2&"#"&14,FixedDeposits!$L:$L,0)),"") | C95: =IFERROR(INDEX(FixedDeposits!$E:$E,MATCH($B$2&"#"&14,FixedDeposits!$L:$L,0)),"") | D95: =IFERROR(INDEX(FixedDeposits!$G:$G,MATCH($B$2&"#"&14,FixedDeposits!$L:$L,0)),"") | E95: =IFERROR(INDEX(FixedDeposits!$I:$I,MATCH($B$2&"#"&14,FixedDeposits!$L:$L,0)),"")
A96: =IFERROR(INDEX(FixedDeposits!$B:$B,MATCH($B$2&"#"&15,FixedDeposits!$L:$L,0)),"") | B96: =IFERROR(INDEX(FixedDeposits!$D:$D,MATCH($B$2&"#"&15,FixedDeposits!$L:$L,0)),"") | C96: =IFERROR(INDEX(FixedDeposits!$E:$E,MATCH($B$2&"#"&15,FixedDeposits!$L:$L,0)),"") | D96: =IFERROR(INDEX(FixedDeposits!$G:$G,MATCH($B$2&"#"&15,FixedDeposits!$L:$L,0)),"") | E96: =IFERROR(INDEX(FixedDeposits!$I:$I,MATCH($B$2&"#"&15,FixedDeposits!$L:$L,0)),"")
A98: PPF
A99: Institution | B99: Balance | C99: As-on
A100: =IFERROR(INDEX(PPF!$B:$B,MATCH($B$2&"#"&1,PPF!$I:$I,0)),"") | B100: =IFERROR(INDEX(PPF!$D:$D,MATCH($B$2&"#"&1,PPF!$I:$I,0)),"") | C100: =IFERROR(INDEX(PPF!$E:$E,MATCH($B$2&"#"&1,PPF!$I:$I,0)),"")
A101: =IFERROR(INDEX(PPF!$B:$B,MATCH($B$2&"#"&2,PPF!$I:$I,0)),"") | B101: =IFERROR(INDEX(PPF!$D:$D,MATCH($B$2&"#"&2,PPF!$I:$I,0)),"") | C101: =IFERROR(INDEX(PPF!$E:$E,MATCH($B$2&"#"&2,PPF!$I:$I,0)),"")
A102: =IFERROR(INDEX(PPF!$B:$B,MATCH($B$2&"#"&3,PPF!$I:$I,0)),"") | B102: =IFERROR(INDEX(PPF!$D:$D,MATCH($B$2&"#"&3,PPF!$I:$I,0)),"") | C102: =IFERROR(INDEX(PPF!$E:$E,MATCH($B$2&"#"&3,PPF!$I:$I,0)),"")
A103: =IFERROR(INDEX(PPF!$B:$B,MATCH($B$2&"#"&4,PPF!$I:$I,0)),"") | B103: =IFERROR(INDEX(PPF!$D:$D,MATCH($B$2&"#"&4,PPF!$I:$I,0)),"") | C103: =IFERROR(INDEX(PPF!$E:$E,MATCH($B$2&"#"&4,PPF!$I:$I,0)),"")
A104: =IFERROR(INDEX(PPF!$B:$B,MATCH($B$2&"#"&5,PPF!$I:$I,0)),"") | B104: =IFERROR(INDEX(PPF!$D:$D,MATCH($B$2&"#"&5,PPF!$I:$I,0)),"") | C104: =IFERROR(INDEX(PPF!$E:$E,MATCH($B$2&"#"&5,PPF!$I:$I,0)),"")
A105: =IFERROR(INDEX(PPF!$B:$B,MATCH($B$2&"#"&6,PPF!$I:$I,0)),"") | B105: =IFERROR(INDEX(PPF!$D:$D,MATCH($B$2&"#"&6,PPF!$I:$I,0)),"") | C105: =IFERROR(INDEX(PPF!$E:$E,MATCH($B$2&"#"&6,PPF!$I:$I,0)),"")
A106: =IFERROR(INDEX(PPF!$B:$B,MATCH($B$2&"#"&7,PPF!$I:$I,0)),"") | B106: =IFERROR(INDEX(PPF!$D:$D,MATCH($B$2&"#"&7,PPF!$I:$I,0)),"") | C106: =IFERROR(INDEX(PPF!$E:$E,MATCH($B$2&"#"&7,PPF!$I:$I,0)),"")
...

Sheet Equity
A1: EQUITY HOLDINGS
A2: Enter Owner, then PICK the Scrip from the dropdown — ISIN fills itself from Stock_Master (type it only for delisted scrips). Enter Qty, Avg cost and Cost date (drives XIRR); prices refresh via UpdatePrices.bat. Grey columns compute themselves.
A3: Owner | B3: ISIN | C3: Scrip | D3: Quantity | E3: Avg. cost | F3: Closing Price | G3: Prev. close | H3: Closing Price Date | I3: Cur. val | J3: Invested | K3: Net chg. | L3: Day chg. | M3: Cost date | N3: XIRR | P3: Key
A4: Amit | B4: =IF($C4="","",IFERROR(INDEX(Stock_Master!$C:$C,MATCH($C4,Stock_Master!$B:$B,0)),"")) -> INE002A01018 | C4: RELIANCE INDUSTRIES LTD. | D4: 50 | E4: 964.9 | F4: 1520 | G4: 1512.3 | H4: 13-07-2026 | I4: =IF($D4="","",$D4*$F4) -> 76000 | J4: =IF(OR($D4="",$E4=""),"",$D4*$E4) -> 48245 | K4: =IF(OR($E4="",$D4=""),"",$I4-$J4) -> 27755 | L4: =IF(OR($G4="",$D4=""),"",$D4*($F4-$G4)) -> 385 | M4: 43131 | N4: =IF(OR($M4="",N($J4)=0,$I4="",TODAY()<=$M4),"",($I4/$J4)^(365/(TODAY()-$M4))-1) -> 0.055220257 | P4: =IF($A4="","",$A4&"#"&COUNTIF($A$4:$A4,$A4)) -> Amit#1
A5: Amit | B5: =IF($C5="","",IFERROR(INDEX(Stock_Master!$C:$C,MATCH($C5,Stock_Master!$B:$B,0)),"")) -> INE467B01029 | C5: TATA CONSULTANCY SERVICES LTD. | D5: 12 | E5: 2916.05 | F5: 3450 | G5: 3462.1 | H5: 13-07-2026 | I5: =IF($D5="","",$D5*$F5) -> 41400 | J5: =IF(OR($D5="",$E5=""),"",$D5*$E5) -> 34992.6 | K5: =IF(OR($E5="",$D5=""),"",$I5-$J5) -> 6407.4 | L5: =IF(OR($G5="",$D5=""),"",$D5*($F5-$G5)) -> -145.2 | M5: 43131 | N5: =IF(OR($M5="",N($J5)=0,$I5="",TODAY()<=$M5),"",($I5/$J5)^(365/(TODAY()-$M5))-1) -> 0.020086519 | P5: =IF($A5="","",$A5&"#"&COUNTIF($A$4:$A5,$A5)) -> Amit#2
A6: Amit | B6: =IF($C6="","",IFERROR(INDEX(Stock_Master!$C:$C,MATCH($C6,Stock_Master!$B:$B,0)),"")) -> INE009A01021 | C6: INFOSYS LTD. | D6: 40 | E6: 1173.85 | F6: 1610 | G6: 1598.7 | H6: 13-07-2026 | I6: =IF($D6="","",$D6*$F6) -> 64400 | J6: =IF(OR($D6="",$E6=""),"",$D6*$E6) -> 46954 | K6: =IF(OR($E6="",$D6=""),"",$I6-$J6) -> 17446 | L6: =IF(OR($G6="",$D6=""),"",$D6*($F6-$G6)) -> 452 | M6: 43131 | N6: =IF(OR($M6="",N($J6)=0,$I6="",TODAY()<=$M6),"",($I6/$J6)^(365/(TODAY()-$M6))-1) -> 0.038075757 | P6: =IF($A6="","",$A6&"#"&COUNTIF($A$4:$A6,$A6)) -> Amit#3
A7: Amit | B7: =IF($C7="","",IFERROR(INDEX(Stock_Master!$C:$C,MATCH($C7,Stock_Master!$B:$B,0)),"")) -> INE040A01034 | C7: HDFC BANK LTD. | D7: 60 | E7: 1076 | F7: 1690 | G7: 1701.5 | H7: 13-07-2026 | I7: =IF($D7="","",$D7*$F7) -> 101400 | J7: =IF(OR($D7="",$E7=""),"",$D7*$E7) -> 64560 | K7: =IF(OR($E7="",$D7=""),"",$I7-$J7) -> 36840 | L7: =IF(OR($G7="",$D7=""),"",$D7*($F7-$G7)) -> -690 | M7: 43131 | N7: =IF(OR($M7="",N($J7)=0,$I7="",TODAY()<=$M7),"",($I7/$J7)^(365/(TODAY()-$M7))-1) -> 0.054850508 | P7: =IF($A7="","",$A7&"#"&COUNTIF($A$4:$A7,$A7)) -> Amit#4
A8: Priya | B8: =IF($C8="","",IFERROR(INDEX(Stock_Master!$C:$C,MATCH($C8,Stock_Master!$B:$B,0)),"")) -> INE154A01025 | C8: ITC LTD. | D8: 200 | E8: 282.6 | F8: 435 | G8: 432.9 | H8: 13-07-2026 | I8: =IF($D8="","",$D8*$F8) -> 87000 | J8: =IF(OR($D8="",$E8=""),"",$D8*$E8) -> 56520 | K8: =IF(OR($E8="",$D8=""),"",$I8-$J8) -> 30480 | L8: =IF(OR($G8="",$D8=""),"",$D8*($F8-$G8)) -> 420 | M8: 43131 | N8: =IF(OR($M8="",N($J8)=0,$I8="",TODAY()<=$M8),"",($I8/$J8)^(365/(TODAY()-$M8))-1) -> 0.05233771 | P8: =IF($A8="","",$A8&"#"&COUNTIF($A$4:$A8,$A8)) -> Priya#1
A9: Priya | B9: =IF($C9="","",IFERROR(INDEX(Stock_Master!$C:$C,MATCH($C9,Stock_Master!$B:$B,0)),"")) -> INE090A01021 | C9: ICICI BANK LTD. | D9: 80 | E9: 365 | F9: 1240 | G9: 1231 | H9: 13-07-2026 | I9: =IF($D9="","",$D9*$F9) -> 99200 | J9: =IF(OR($D9="",$E9=""),"",$D9*$E9) -> 29200 | K9: =IF(OR($E9="",$D9=""),"",$I9-$J9) -> 70000 | L9: =IF(OR($G9="",$D9=""),"",$D9*($F9-$G9)) -> 720 | M9: 43131 | N9: =IF(OR($M9="",N($J9)=0,$I9="",TODAY()<=$M9),"",($I9/$J9)^(365/(TODAY()-$M9))-1) -> 0.15563274 | P9: =IF($A9="","",$A9&"#"&COUNTIF($A$4:$A9,$A9)) -> Priya#2
A10: Priya | B10: =IF($C10="","",IFERROR(INDEX(Stock_Master!$C:$C,MATCH($C10,Stock_Master!$B:$B,0)),"")) -> INE075A01022 | C10: WIPRO LTD. | D10: 150 | E10: 317 | F10: 245 | G10: 247.2 | H10: 13-07-2026 | I10: =IF($D10="","",$D10*$F10) -> 36750 | J10: =IF(OR($D10="",$E10=""),"",$D10*$E10) -> 47550 | K10: =IF(OR($E10="",$D10=""),"",$I10-$J10) -> -10800 | L10: =IF(OR($G10="",$D10=""),"",$D10*($F10-$G10)) -> -330 | M10: 43131 | N10: =IF(OR($M10="",N($J10)=0,$I10="",TODAY()<=$M10),"",($I10/$J10)^(365/(TODAY()-$M10))-1) -> -0.030013449 | P10: =IF($A10="","",$A10&"#"&COUNTIF($A$4:$A10,$A10)) -> Priya#3
A11: Rahul | B11: =IF($C11="","",IFERROR(INDEX(Stock_Master!$C:$C,MATCH($C11,Stock_Master!$B:$B,0)),"")) -> INE018A01030 | C11: LARSEN & TOUBRO LTD. | D11: 25 | E11: 1470 | F11: 3620 | G11: 3608.4 | H11: 13-07-2026 | I11: =IF($D11="","",$D11*$F11) -> 90500 | J11: =IF(OR($D11="",$E11=""),"",$D11*$E11) -> 36750 | K11: =IF(OR($E11="",$D11=""),"",$I11-$J11) -> 53750 | L11: =IF(OR($G11="",$D11=""),"",$D11*($F11-$G11)) -> 290 | M11: 43131 | N11: =IF(OR($M11="",N($J11)=0,$I11="",TODAY()<=$M11),"",($I11/$J11)^(365/(TODAY()-$M11))-1) -> 0.11248003 | P11: =IF($A11="","",$A11&"#"&COUNTIF($A$4:$A11,$A11)) -> Rahul#1
A12: Rahul | B12: =IF($C12="","",IFERROR(INDEX(Stock_Master!$C:$C,MATCH($C12,Stock_Master!$B:$B,0)),"")) -> INE062A01020 | C12: STATE BANK OF INDIA | D12: 120 | E12: 327 | F12: 815 | G12: 812.5 | H12: 13-07-2026 | I12: =IF($D12="","",$D12*$F12) -> 97800 | J12: =IF(OR($D12="",$E12=""),"",$D12*$E12) -> 39240 | K12: =IF(OR($E12="",$D12=""),"",$I12-$J12) -> 58560 | L12: =IF(OR($G12="",$D12=""),"",$D12*($F12-$G12)) -> 300 | M12: 43131 | N12: =IF(OR($M12="",N($J12)=0,$I12="",TODAY()<=$M12),"",($I12/$J12)^(365/(TODAY()-$M12))-1) -> 0.11406226 | P12: =IF($A12="","",$A12&"#"&COUNTIF($A$4:$A12,$A12)) -> Rahul#2
A13: Rahul | B13: =IF($C13="","",IFERROR(INDEX(Stock_Master!$C:$C,MATCH($C13,Stock_Master!$B:$B,0)),"")) -> INE030A01027 | C13: HINDUSTAN UNILEVER LTD. | D13: 30 | E13: 1370 | F13: 2410 | G13: 2422.8 | H13: 13-07-2026 | I13: =IF($D13="","",$D13*$F13) -> 72300 | J13: =IF(OR($D13="",$E13=""),"",$D13*$E13) -> 41100 | K13: =IF(OR($E13="",$D13=""),"",$I13-$J13) -> 31200 | L13: =IF(OR($G13="",$D13=""),"",$D13*($F13-$G13)) -> -384 | M13: 43131 | N13: =IF(OR($M13="",N($J13)=0,$I13="",TODAY()<=$M13),"",($I13/$J13)^(365/(TODAY()-$M13))-1) -> 0.069086159 | P13: =IF($A13="","",$A13&"#"&COUNTIF($A$4:$A13,$A13)) -> Rahul#3
B14: =IF($C14="","",IFERROR(INDEX(Stock_Master!$C:$C,MATCH($C14,Stock_Master!$B:$B,0)),"")) | I14: =IF($D14="","",$D14*$F14) | J14: =IF(OR($D14="",$E14=""),"",$D14*$E14) | K14: =IF(OR($E14="",$D14=""),"",$I14-$J14) | L14: =IF(OR($G14="",$D14=""),"",$D14*($F14-$G14)) | N14: =IF(OR($M14="",N($J14)=0,$I14="",TODAY()<=$M14),"",($I14/$J14)^(365/(TODAY()-$M14))-1) | P14: =IF($A14="","",$A14&"#"&COUNTIF($A$4:$A14,$A14))
B15: =IF($C15="","",IFERROR(INDEX(Stock_Master!$C:$C,MATCH($C15,Stock_Master!$B:$B,0)),"")) | I15: =IF($D15="","",$D15*$F15) | J15: =IF(OR($D15="",$E15=""),"",$D15*$E15) | K15: =IF(OR($E15="",$D15=""),"",$I15-$J15) | L15: =IF(OR($G15="",$D15=""),"",$D15*($F15-$G15)) | N15: =IF(OR($M15="",N($J15)=0,$I15="",TODAY()<=$M15),"",($I15/$J15)^(365/(TODAY()-$M15))-1) | P15: =IF($A15="","",$A15&"#"&COUNTIF($A$4:$A15,$A15))
B16: =IF($C16="","",IFERROR(INDEX(Stock_Master!$C:$C,MATCH($C16,Stock_Master!$B:$B,0)),"")) | I16: =IF($D16="","",$D16*$F16) | J16: =IF(OR($D16="",$E16=""),"",$D16*$E16) | K16: =IF(OR($E16="",$D16=""),"",$I16-$J16) | L16: =IF(OR($G16="",$D16=""),"",$D16*($F16-$G16)) | N16: =IF(OR($M16="",N($J16)=0,$I16="",TODAY()<=$M16),"",($I16/$J16)^(365/(TODAY()-$M16))-1) | P16: =IF($A16="","",$A16&"#"&COUNTIF($A$4:$A16,$A16))
B17: =IF($C17="","",IFERROR(INDEX(Stock_Master!$C:$C,MATCH($C17,Stock_Master!$B:$B,0)),"")) | I17: =IF($D17="","",$D17*$F17) | J17: =IF(OR($D17="",$E17=""),"",$D17*$E17) | K17: =IF(OR($E17="",$D17=""),"",$I17-$J17) | L17: =IF(OR($G17="",$D17=""),"",$D17*($F17-$G17)) | N17: =IF(OR($M17="",N($J17)=0,$I17="",TODAY()<=$M17),"",($I17/$J17)^(365/(TODAY()-$M17))-1) | P17: =IF($A17="","",$A17&"#"&COUNTIF($A$4:$A17,$A17))
B18: =IF($C18="","",IFERROR(INDEX(Stock_Master!$C:$C,MATCH($C18,Stock_Master!$B:$B,0)),"")) | I18: =IF($D18="","",$D18*$F18) | J18: =IF(OR($D18="",$E18=""),"",$D18*$E18) | K18: =IF(OR($E18="",$D18=""),"",$I18-$J18) | L18: =IF(OR($G18="",$D18=""),"",$D18*($F18-$G18)) | N18: =IF(OR($M18="",N($J18)=0,$I18="",TODAY()<=$M18),"",($I18/$J18)^(365/(TODAY()-$M18))-1) | P18: =IF($A18="","",$A18&"#"&COUNTIF($A$4:$A18,$A18))
B19: =IF($C19="","",IFERROR(INDEX(Stock_Master!$C:$C,MATCH($C19,Stock_Master!$B:$B,0)),"")) | I19: =IF($D19="","",$D19*$F19) | J19: =IF(OR($D19="",$E19=""),"",$D19*$E19) | K19: =IF(OR($E19="",$D19=""),"",$I19-$J19) | L19: =IF(OR($G19="",$D19=""),"",$D19*($F19-$G19)) | N19: =IF(OR($M19="",N($J19)=0,$I19="",TODAY()<=$M19),"",($I19/$J19)^(365/(TODAY()-$M19))-1) | P19: =IF($A19="","",$A19&"#"&COUNTIF($A$4:$A19,$A19))
B20: =IF($C20="","",IFERROR(INDEX(Stock_Master!$C:$C,MATCH($C20,Stock_Master!$B:$B,0)),"")) | I20: =IF($D20="","",$D20*$F20) | J20: =IF(OR($D20="",$E20=""),"",$D20*$E20) | K20: =IF(OR($E20="",$D20=""),"",$I20-$J20) | L20: =IF(OR($G20="",$D20=""),"",$D20*($F20-$G20)) | N20: =IF(OR($M20="",N($J20)=0,$I20="",TODAY()<=$M20),"",($I20/$J20)^(365/(TODAY()-$M20))-1) | P20: =IF($A20="","",$A20&"#"&COUNTIF($A$4:$A20,$A20))
B21: =IF($C21="","",IFERROR(INDEX(Stock_Master!$C:$C,MATCH($C21,Stock_Master!$B:$B,0)),"")) | I21: =IF($D21="","",$D21*$F21) | J21: =IF(OR($D21="",$E21=""),"",$D21*$E21) | K21: =IF(OR($E21="",$D21=""),"",$I21-$J21) | L21: =IF(OR($G21="",$D21=""),"",$D21*($F21-$G21)) | N21: =IF(OR($M21="",N($J21)=0,$I21="",TODAY()<=$M21),"",($I21/$J21)^(365/(TODAY()-$M21))-1) | P21: =IF($A21="","",$A21&"#"&COUNTIF($A$4:$A21,$A21))
B22: =IF($C22="","",IFERROR(INDEX(Stock_Master!$C:$C,MATCH($C22,Stock_Master!$B:$B,0)),"")) | I22: =IF($D22="","",$D22*$F22) | J22: =IF(OR($D22="",$E22=""),"",$D22*$E22) | K22: =IF(OR($E22="",$D22=""),"",$I22-$J22) | L22: =IF(OR($G22="",$D22=""),"",$D22*($F22-$G22)) | N22: =IF(OR($M22="",N($J22)=0,$I22="",TODAY()<=$M22),"",($I22/$J22)^(365/(TODAY()-$M22))-1) | P22: =IF($A22="","",$A22&"#"&COUNTIF($A$4:$A22,$A22))
B23: =IF($C23="","",IFERROR(INDEX(Stock_Master!$C:$C,MATCH($C23,Stock_Master!$B:$B,0)),"")) | I23: =IF($D23="","",$D23*$F23) | J23: =IF(OR($D23="",$E23=""),"",$D23*$E23) | K23: =IF(OR($E23="",$D23=""),"",$I23-$J23) | L23: =IF(OR($G23="",$D23=""),"",$D23*($F23-$G23)) | N23: =IF(OR($M23="",N($J23)=0,$I23="",TODAY()<=$M23),"",($I23/$J23)^(365/(TODAY()-$M23))-1) | P23: =IF($A23="","",$A23&"#"&COUNTIF($A$4:$A23,$A23))
B24: =IF($C24="","",IFERROR(INDEX(Stock_Master!$C:$C,MATCH($C24,Stock_Master!$B:$B,0)),"")) | I24: =IF($D24="","",$D24*$F24) | J24: =IF(OR($D24="",$E24=""),"",$D24*$E24) | K24: =IF(OR($E24="",$D24=""),"",$I24-$J24) | L24: =IF(OR($G24="",$D24=""),"",$D24*($F24-$G24)) | N24: =IF(OR($M24="",N($J24)=0,$I24="",TODAY()<=$M24),"",($I24/$J24)^(365/(TODAY()-$M24))-1) | P24: =IF($A24="","",$A24&"#"&COUNTIF($A$4:$A24,$A24))
B25: =IF($C25="","",IFERROR(INDEX(Stock_Master!$C:$C,MATCH($C25,Stock_Master!$B:$B,0)),"")) | I25: =IF($D25="","",$D25*$F25) | J25: =IF(OR($D25="",$E25=""),"",$D25*$E25) | K25: =IF(OR($E25="",$D25=""),"",$I25-$J25) | L25: =IF(OR($G25="",$D25=""),"",$D25*($F25-$G25)) | N25: =IF(OR($M25="",N($J25)=0,$I25="",TODAY()<=$M25),"",($I25/$J25)^(365/(TODAY()-$M25))-1) | P25: =IF($A25="","",$A25&"#"&COUNTIF($A$4:$A25,$A25))
... B140: =IF($C140="","",IFERROR(INDEX(Stock_Master!$C:$C,MATCH($C140,Stock_Master!$B:$B,0)),"")) | I140: =IF($D140="","",$D140*$F140) | J140: =IF(OR($D140="",$E140=""),"",$D140*$E140) | K140: =IF(OR($E140="",$D140=""),"",$I140-$J140) | L140: =IF(OR($G140="",$D140=""),"",$D140*($F140-$G140)) | N140: =IF(OR($M140="",N($J140)=0,$I140="",TODAY()<=$M140),"",($I140/$J140)^(365/(TODAY()-$M140))-1) | P140: =IF($A140="","",$A140&"#"&COUNTIF($A$4:$A140,$A140))
C142: TOTAL | I142: =SUM(I4:I140) -> 766750 | J142: =SUM(J4:J140) -> 445111.6 | K142: =SUM(K4:K140) -> 321638.4 | L142: =SUM(L4:L140) -> 1017.8 | M142: XIRR → | N142: 0.066437

Sheet MutualFunds
A1: MUTUAL FUNDS
A2: One row per scheme. Enter Owner, then PICK the Scheme Name from the dropdown — Fund House and ISIN fill themselves from the MF_Master sheet (type them only for schemes missing there). Enter Current NAV or run UpdateNAV.bat. Units / Invested / Avg cost NAV / Return % / XIRR compute from the MF_SIP ledger.
A3: Owner | B3: Fund House | C3: Scheme Name | D3: ISIN | E3: Units | F3: Avg cost NAV | G3: Current NAV | H3: Invested | I3: Cur. val | J3: Net chg. | K3: Return % | L3: XIRR | N3: Key
A4: Amit | B4: =IF($C4="","",IFERROR(INDEX(MF_Master!$A:$A,MATCH($C4,MF_Master!$B:$B,0)),"")) -> PPFAS Mutual Fund | C4: Parag Parikh Flexi Cap Fund - Direct Plan - Growth | D4: =IF($C4="","",IFERROR(INDEX(MF_Master!$C:$C,MATCH($C4,MF_Master!$B:$B,0)),"")) -> INF879O01027 | E4: =IF($A4="","",SUMIFS(MF_SIP!$H:$H,MF_SIP!$A:$A,$A4,MF_SIP!$D:$D,$D4)) -> 720.17792 | F4: =IF(OR($A4="",N($E4)=0),"",$H4/$E4) -> 83.312746 | G4: 91.2 | H4: =IF($A4="","",SUMIFS(MF_SIP!$F:$F,MF_SIP!$A:$A,$A4,MF_SIP!$D:$D,$D4)) -> 60000 | I4: =IF(OR(N($E4)=0,$G4=""),"",$E4*$G4) -> 65680.226 | J4: =IF(N($E4)=0,"",$I4-$H4) -> 5680.2263 | K4: =IF(OR(N($H4)=0,N($J4)=0),"",$J4/$H4) -> 0.094670439 | L4: 0.36695 | N4: =IF($A4="","",$A4&"#"&COUNTIF($A$4:$A4,$A4)) -> Amit#1
A5: Priya | B5: =IF($C5="","",IFERROR(INDEX(MF_Master!$A:$A,MATCH($C5,MF_Master!$B:$B,0)),"")) -> SBI Mutual Fund | C5: SBI Large Cap FUND-DIRECT PLAN -GROWTH | D5: =IF($C5="","",IFERROR(INDEX(MF_Master!$C:$C,MATCH($C5,MF_Master!$B:$B,0)),"")) -> INF200K01QX4 | E5: =IF($A5="","",SUMIFS(MF_SIP!$H:$H,MF_SIP!$A:$A,$A5,MF_SIP!$D:$D,$D5)) -> 1781.4727 | F5: =IF(OR($A5="",N($E5)=0),"",$H5/$E5) -> 84.2 | G5: 96.4 | H5: =IF($A5="","",SUMIFS(MF_SIP!$F:$F,MF_SIP!$A:$A,$A5,MF_SIP!$D:$D,$D5)) -> 150000 | I5: =IF(OR(N($E5)=0,$G5=""),"",$E5*$G5) -> 171733.97 | J5: =IF(N($E5)=0,"",$I5-$H5) -> 21733.967 | K5: =IF(OR(N($H5)=0,N($J5)=0),"",$J5/$H5) -> 0.14489311 | L5: 0.073869 | N5: =IF($A5="","",$A5&"#"&COUNTIF($A$4:$A5,$A5)) -> Priya#1
B6: =IF($C6="","",IFERROR(INDEX(MF_Master!$A:$A,MATCH($C6,MF_Master!$B:$B,0)),"")) | D6: =IF($C6="","",IFERROR(INDEX(MF_Master!$C:$C,MATCH($C6,MF_Master!$B:$B,0)),"")) | E6: =IF($A6="","",SUMIFS(MF_SIP!$H:$H,MF_SIP!$A:$A,$A6,MF_SIP!$D:$D,$D6)) | F6: =IF(OR($A6="",N($E6)=0),"",$H6/$E6) | H6: =IF($A6="","",SUMIFS(MF_SIP!$F:$F,MF_SIP!$A:$A,$A6,MF_SIP!$D:$D,$D6)) | I6: =IF(OR(N($E6)=0,$G6=""),"",$E6*$G6) | J6: =IF(N($E6)=0,"",$I6-$H6) | K6: =IF(OR(N($H6)=0,N($J6)=0),"",$J6/$H6) | N6: =IF($A6="","",$A6&"#"&COUNTIF($A$4:$A6,$A6))
B7: =IF($C7="","",IFERROR(INDEX(MF_Master!$A:$A,MATCH($C7,MF_Master!$B:$B,0)),"")) | D7: =IF($C7="","",IFERROR(INDEX(MF_Master!$C:$C,MATCH($C7,MF_Master!$B:$B,0)),"")) | E7: =IF($A7="","",SUMIFS(MF_SIP!$H:$H,MF_SIP!$A:$A,$A7,MF_SIP!$D:$D,$D7)) | F7: =IF(OR($A7="",N($E7)=0),"",$H7/$E7) | H7: =IF($A7="","",SUMIFS(MF_SIP!$F:$F,MF_SIP!$A:$A,$A7,MF_SIP!$D:$D,$D7)) | I7: =IF(OR(N($E7)=0,$G7=""),"",$E7*$G7) | J7: =IF(N($E7)=0,"",$I7-$H7) | K7: =IF(OR(N($H7)=0,N($J7)=0),"",$J7/$H7) | N7: =IF($A7="","",$A7&"#"&COUNTIF($A$4:$A7,$A7))
B8: =IF($C8="","",IFERROR(INDEX(MF_Master!$A:$A,MATCH($C8,MF_Master!$B:$B,0)),"")) | D8: =IF($C8="","",IFERROR(INDEX(MF_Master!$C:$C,MATCH($C8,MF_Master!$B:$B,0)),"")) | E8: =IF($A8="","",SUMIFS(MF_SIP!$H:$H,MF_SIP!$A:$A,$A8,MF_SIP!$D:$D,$D8)) | F8: =IF(OR($A8="",N($E8)=0),"",$H8/$E8) | H8: =IF($A8="","",SUMIFS(MF_SIP!$F:$F,MF_SIP!$A:$A,$A8,MF_SIP!$D:$D,$D8)) | I8: =IF(OR(N($E8)=0,$G8=""),"",$E8*$G8) | J8: =IF(N($E8)=0,"",$I8-$H8) | K8: =IF(OR(N($H8)=0,N($J8)=0),"",$J8/$H8) | N8: =IF($A8="","",$A8&"#"&COUNTIF($A$4:$A8,$A8))
B9: =IF($C9="","",IFERROR(INDEX(MF_Master!$A:$A,MATCH($C9,MF_Master!$B:$B,0)),"")) | D9: =IF($C9="","",IFERROR(INDEX(MF_Master!$C:$C,MATCH($C9,MF_Master!$B:$B,0)),"")) | E9: =IF($A9="","",SUMIFS(MF_SIP!$H:$H,MF_SIP!$A:$A,$A9,MF_SIP!$D:$D,$D9)) | F9: =IF(OR($A9="",N($E9)=0),"",$H9/$E9) | H9: =IF($A9="","",SUMIFS(MF_SIP!$F:$F,MF_SIP!$A:$A,$A9,MF_SIP!$D:$D,$D9)) | I9: =IF(OR(N($E9)=0,$G9=""),"",$E9*$G9) | J9: =IF(N($E9)=0,"",$I9-$H9) | K9: =IF(OR(N($H9)=0,N($J9)=0),"",$J9/$H9) | N9: =IF($A9="","",$A9&"#"&COUNTIF($A$4:$A9,$A9))
B10: =IF($C10="","",IFERROR(INDEX(MF_Master!$A:$A,MATCH($C10,MF_Master!$B:$B,0)),"")) | D10: =IF($C10="","",IFERROR(INDEX(MF_Master!$C:$C,MATCH($C10,MF_Master!$B:$B,0)),"")) | E10: =IF($A10="","",SUMIFS(MF_SIP!$H:$H,MF_SIP!$A:$A,$A10,MF_SIP!$D:$D,$D10)) | F10: =IF(OR($A10="",N($E10)=0),"",$H10/$E10) | H10: =IF($A10="","",SUMIFS(MF_SIP!$F:$F,MF_SIP!$A:$A,$A10,MF_SIP!$D:$D,$D10)) | I10: =IF(OR(N($E10)=0,$G10=""),"",$E10*$G10) | J10: =IF(N($E10)=0,"",$I10-$H10) | K10: =IF(OR(N($H10)=0,N($J10)=0),"",$J10/$H10) | N10: =IF($A10="","",$A10&"#"&COUNTIF($A$4:$A10,$A10))
B11: =IF($C11="","",IFERROR(INDEX(MF_Master!$A:$A,MATCH($C11,MF_Master!$B:$B,0)),"")) | D11: =IF($C11="","",IFERROR(INDEX(MF_Master!$C:$C,MATCH($C11,MF_Master!$B:$B,0)),"")) | E11: =IF($A11="","",SUMIFS(MF_SIP!$H:$H,MF_SIP!$A:$A,$A11,MF_SIP!$D:$D,$D11)) | F11: =IF(OR($A11="",N($E11)=0),"",$H11/$E11) | H11: =IF($A11="","",SUMIFS(MF_SIP!$F:$F,MF_SIP!$A:$A,$A11,MF_SIP!$D:$D,$D11)) | I11: =IF(OR(N($E11)=0,$G11=""),"",$E11*$G11) | J11: =IF(N($E11)=0,"",$I11-$H11) | K11: =IF(OR(N($H11)=0,N($J11)=0),"",$J11/$H11) | N11: =IF($A11="","",$A11&"#"&COUNTIF($A$4:$A11,$A11))
B12: =IF($C12="","",IFERROR(INDEX(MF_Master!$A:$A,MATCH($C12,MF_Master!$B:$B,0)),"")) | D12: =IF($C12="","",IFERROR(INDEX(MF_Master!$C:$C,MATCH($C12,MF_Master!$B:$B,0)),"")) | E12: =IF($A12="","",SUMIFS(MF_SIP!$H:$H,MF_SIP!$A:$A,$A12,MF_SIP!$D:$D,$D12)) | F12: =IF(OR($A12="",N($E12)=0),"",$H12/$E12) | H12: =IF($A12="","",SUMIFS(MF_SIP!$F:$F,MF_SIP!$A:$A,$A12,MF_SIP!$D:$D,$D12)) | I12: =IF(OR(N($E12)=0,$G12=""),"",$E12*$G12) | J12: =IF(N($E12)=0,"",$I12-$H12) | K12: =IF(OR(N($H12)=0,N($J12)=0),"",$J12/$H12) | N12: =IF($A12="","",$A12&"#"&COUNTIF($A$4:$A12,$A12))
B13: =IF($C13="","",IFERROR(INDEX(MF_Master!$A:$A,MATCH($C13,MF_Master!$B:$B,0)),"")) | D13: =IF($C13="","",IFERROR(INDEX(MF_Master!$C:$C,MATCH($C13,MF_Master!$B:$B,0)),"")) | E13: =IF($A13="","",SUMIFS(MF_SIP!$H:$H,MF_SIP!$A:$A,$A13,MF_SIP!$D:$D,$D13)) | F13: =IF(OR($A13="",N($E13)=0),"",$H13/$E13) | H13: =IF($A13="","",SUMIFS(MF_SIP!$F:$F,MF_SIP!$A:$A,$A13,MF_SIP!$D:$D,$D13)) | I13: =IF(OR(N($E13)=0,$G13=""),"",$E13*$G13) | J13: =IF(N($E13)=0,"",$I13-$H13) | K13: =IF(OR(N($H13)=0,N($J13)=0),"",$J13/$H13) | N13: =IF($A13="","",$A13&"#"&COUNTIF($A$4:$A13,$A13))
B14: =IF($C14="","",IFERROR(INDEX(MF_Master!$A:$A,MATCH($C14,MF_Master!$B:$B,0)),"")) | D14: =IF($C14="","",IFERROR(INDEX(MF_Master!$C:$C,MATCH($C14,MF_Master!$B:$B,0)),"")) | E14: =IF($A14="","",SUMIFS(MF_SIP!$H:$H,MF_SIP!$A:$A,$A14,MF_SIP!$D:$D,$D14)) | F14: =IF(OR($A14="",N($E14)=0),"",$H14/$E14) | H14: =IF($A14="","",SUMIFS(MF_SIP!$F:$F,MF_SIP!$A:$A,$A14,MF_SIP!$D:$D,$D14)) | I14: =IF(OR(N($E14)=0,$G14=""),"",$E14*$G14) | J14: =IF(N($E14)=0,"",$I14-$H14) | K14: =IF(OR(N($H14)=0,N($J14)=0),"",$J14/$H14) | N14: =IF($A14="","",$A14&"#"&COUNTIF($A$4:$A14,$A14))
B15: =IF($C15="","",IFERROR(INDEX(MF_Master!$A:$A,MATCH($C15,MF_Master!$B:$B,0)),"")) | D15: =IF($C15="","",IFERROR(INDEX(MF_Master!$C:$C,MATCH($C15,MF_Master!$B:$B,0)),"")) | E15: =IF($A15="","",SUMIFS(MF_SIP!$H:$H,MF_SIP!$A:$A,$A15,MF_SIP!$D:$D,$D15)) | F15: =IF(OR($A15="",N($E15)=0),"",$H15/$E15) | H15: =IF($A15="","",SUMIFS(MF_SIP!$F:$F,MF_SIP!$A:$A,$A15,MF_SIP!$D:$D,$D15)) | I15: =IF(OR(N($E15)=0,$G15=""),"",$E15*$G15) | J15: =IF(N($E15)=0,"",$I15-$H15) | K15: =IF(OR(N($H15)=0,N($J15)=0),"",$J15/$H15) | N15: =IF($A15="","",$A15&"#"&COUNTIF($A$4:$A15,$A15))
B16: =IF($C16="","",IFERROR(INDEX(MF_Master!$A:$A,MATCH($C16,MF_Master!$B:$B,0)),"")) | D16: =IF($C16="","",IFERROR(INDEX(MF_Master!$C:$C,MATCH($C16,MF_Master!$B:$B,0)),"")) | E16: =IF($A16="","",SUMIFS(MF_SIP!$H:$H,MF_SIP!$A:$A,$A16,MF_SIP!$D:$D,$D16)) | F16: =IF(OR($A16="",N($E16)=0),"",$H16/$E16) | H16: =IF($A16="","",SUMIFS(MF_SIP!$F:$F,MF_SIP!$A:$A,$A16,MF_SIP!$D:$D,$D16)) | I16: =IF(OR(N($E16)=0,$G16=""),"",$E16*$G16) | J16: =IF(N($E16)=0,"",$I16-$H16) | K16: =IF(OR(N($H16)=0,N($J16)=0),"",$J16/$H16) | N16: =IF($A16="","",$A16&"#"&COUNTIF($A$4:$A16,$A16))
B17: =IF($C17="","",IFERROR(INDEX(MF_Master!$A:$A,MATCH($C17,MF_Master!$B:$B,0)),"")) | D17: =IF($C17="","",IFERROR(INDEX(MF_Master!$C:$C,MATCH($C17,MF_Master!$B:$B,0)),"")) | E17: =IF($A17="","",SUMIFS(MF_SIP!$H:$H,MF_SIP!$A:$A,$A17,MF_SIP!$D:$D,$D17)) | F17: =IF(OR($A17="",N($E17)=0),"",$H17/$E17) | H17: =IF($A17="","",SUMIFS(MF_SIP!$F:$F,MF_SIP!$A:$A,$A17,MF_SIP!$D:$D,$D17)) | I17: =IF(OR(N($E17)=0,$G17=""),"",$E17*$G17) | J17: =IF(N($E17)=0,"",$I17-$H17) | K17: =IF(OR(N($H17)=0,N($J17)=0),"",$J17/$H17) | N17: =IF($A17="","",$A17&"#"&COUNTIF($A$4:$A17,$A17))
... B63: =IF($C63="","",IFERROR(INDEX(MF_Master!$A:$A,MATCH($C63,MF_Master!$B:$B,0)),"")) | D63: =IF($C63="","",IFERROR(INDEX(MF_Master!$C:$C,MATCH($C63,MF_Master!$B:$B,0)),"")) | E63: =IF($A63="","",SUMIFS(MF_SIP!$H:$H,MF_SIP!$A:$A,$A63,MF_SIP!$D:$D,$D63)) | F63: =IF(OR($A63="",N($E63)=0),"",$H63/$E63) | H63: =IF($A63="","",SUMIFS(MF_SIP!$F:$F,MF_SIP!$A:$A,$A63,MF_SIP!$D:$D,$D63)) | I63: =IF(OR(N($E63)=0,$G63=""),"",$E63*$G63) | J63: =IF(N($E63)=0,"",$I63-$H63) | K63: =IF(OR(N($H63)=0,N($J63)=0),"",$J63/$H63) | N63: =IF($A63="","",$A63&"#"&COUNTIF($A$4:$A63,$A63))
C65: TOTAL | H65: =SUM(H4:H63) -> 210000 | I65: =SUM(I4:I63) -> 237414.19 | J65: =SUM(J4:J63) -> 27414.193 | K65: =IF(N(H65)=0,"",J65/H65) -> 0.13054378 | L65: 0.087671

Sheet MF_SIP
A1: MUTUAL FUND SIP / PURCHASE LEDGER | J1: Portfolio MF XIRR
A2: One row per SIP installment or lump-sum buy. Enter Owner, PICK the Scheme Name from the dropdown — Fund House and ISIN fill themselves from MF_Master — then Date, Amount and NAV on that date. Units compute. Redemptions: negative Amount. | J2: 0.087671
A3: Owner | B3: Fund House | C3: Scheme Name | D3: ISIN | E3: Date | F3: Amount | G3: NAV on date | H3: Units
A4: Amit | B4: =IF($C4="","",IFERROR(INDEX(MF_Master!$A:$A,MATCH($C4,MF_Master!$B:$B,0)),"")) -> PPFAS Mutual Fund | C4: Parag Parikh Flexi Cap Fund - Direct Plan - Growth | D4: =IF($C4="","",IFERROR(INDEX(MF_Master!$C:$C,MATCH($C4,MF_Master!$B:$B,0)),"")) -> INF879O01027 | E4: 46037 | F4: 10000 | G4: 78.42 | H4: =IF(OR($F4="",$G4=""),"",$F4/$G4) -> 127.51849
A5: Amit | B5: =IF($C5="","",IFERROR(INDEX(MF_Master!$A:$A,MATCH($C5,MF_Master!$B:$B,0)),"")) -> PPFAS Mutual Fund | C5: Parag Parikh Flexi Cap Fund - Direct Plan - Growth | D5: =IF($C5="","",IFERROR(INDEX(MF_Master!$C:$C,MATCH($C5,MF_Master!$B:$B,0)),"")) -> INF879O01027 | E5: 46069 | F5: 10000 | G5: 80.11 | H5: =IF(OR($F5="",$G5=""),"",$F5/$G5) -> 124.82836
A6: Amit | B6: =IF($C6="","",IFERROR(INDEX(MF_Master!$A:$A,MATCH($C6,MF_Master!$B:$B,0)),"")) -> PPFAS Mutual Fund | C6: Parag Parikh Flexi Cap Fund - Direct Plan - Growth | D6: =IF($C6="","",IFERROR(INDEX(MF_Master!$C:$C,MATCH($C6,MF_Master!$B:$B,0)),"")) -> INF879O01027 | E6: 46097 | F6: 10000 | G6: 82.05 | H6: =IF(OR($F6="",$G6=""),"",$F6/$G6) -> 121.8769
A7: Amit | B7: =IF($C7="","",IFERROR(INDEX(MF_Master!$A:$A,MATCH($C7,MF_Master!$B:$B,0)),"")) -> PPFAS Mutual Fund | C7: Parag Parikh Flexi Cap Fund - Direct Plan - Growth | D7: =IF($C7="","",IFERROR(INDEX(MF_Master!$C:$C,MATCH($C7,MF_Master!$B:$B,0)),"")) -> INF879O01027 | E7: 46127 | F7: 10000 | G7: 84.6 | H7: =IF(OR($F7="",$G7=""),"",$F7/$G7) -> 118.20331
A8: Amit | B8: =IF($C8="","",IFERROR(INDEX(MF_Master!$A:$A,MATCH($C8,MF_Master!$B:$B,0)),"")) -> PPFAS Mutual Fund | C8: Parag Parikh Flexi Cap Fund - Direct Plan - Growth | D8: =IF($C8="","",IFERROR(INDEX(MF_Master!$C:$C,MATCH($C8,MF_Master!$B:$B,0)),"")) -> INF879O01027 | E8: 46157 | F8: 10000 | G8: 86.9 | H8: =IF(OR($F8="",$G8=""),"",$F8/$G8) -> 115.0748
A9: Amit | B9: =IF($C9="","",IFERROR(INDEX(MF_Master!$A:$A,MATCH($C9,MF_Master!$B:$B,0)),"")) -> PPFAS Mutual Fund | C9: Parag Parikh Flexi Cap Fund - Direct Plan - Growth | D9: =IF($C9="","",IFERROR(INDEX(MF_Master!$C:$C,MATCH($C9,MF_Master!$B:$B,0)),"")) -> INF879O01027 | E9: 46188 | F9: 10000 | G9: 88.75 | H9: =IF(OR($F9="",$G9=""),"",$F9/$G9) -> 112.67606
A10: Priya | B10: =IF($C10="","",IFERROR(INDEX(MF_Master!$A:$A,MATCH($C10,MF_Master!$B:$B,0)),"")) -> SBI Mutual Fund | C10: SBI Large Cap FUND-DIRECT PLAN -GROWTH | D10: =IF($C10="","",IFERROR(INDEX(MF_Master!$C:$C,MATCH($C10,MF_Master!$B:$B,0)),"")) -> INF200K01QX4 | E10: 45524 | F10: 150000 | G10: 84.2 | H10: =IF(OR($F10="",$G10=""),"",$F10/$G10) -> 1781.4727
B11: =IF($C11="","",IFERROR(INDEX(MF_Master!$A:$A,MATCH($C11,MF_Master!$B:$B,0)),"")) | D11: =IF($C11="","",IFERROR(INDEX(MF_Master!$C:$C,MATCH($C11,MF_Master!$B:$B,0)),"")) | H11: =IF(OR($F11="",$G11=""),"",$F11/$G11)
B12: =IF($C12="","",IFERROR(INDEX(MF_Master!$A:$A,MATCH($C12,MF_Master!$B:$B,0)),"")) | D12: =IF($C12="","",IFERROR(INDEX(MF_Master!$C:$C,MATCH($C12,MF_Master!$B:$B,0)),"")) | H12: =IF(OR($F12="",$G12=""),"",$F12/$G12)
B13: =IF($C13="","",IFERROR(INDEX(MF_Master!$A:$A,MATCH($C13,MF_Master!$B:$B,0)),"")) | D13: =IF($C13="","",IFERROR(INDEX(MF_Master!$C:$C,MATCH($C13,MF_Master!$B:$B,0)),"")) | H13: =IF(OR($F13="",$G13=""),"",$F13/$G13)
B14: =IF($C14="","",IFERROR(INDEX(MF_Master!$A:$A,MATCH($C14,MF_Master!$B:$B,0)),"")) | D14: =IF($C14="","",IFERROR(INDEX(MF_Master!$C:$C,MATCH($C14,MF_Master!$B:$B,0)),"")) | H14: =IF(OR($F14="",$G14=""),"",$F14/$G14)
B15: =IF($C15="","",IFERROR(INDEX(MF_Master!$A:$A,MATCH($C15,MF_Master!$B:$B,0)),"")) | D15: =IF($C15="","",IFERROR(INDEX(MF_Master!$C:$C,MATCH($C15,MF_Master!$B:$B,0)),"")) | H15: =IF(OR($F15="",$G15=""),"",$F15/$G15)
B16: =IF($C16="","",IFERROR(INDEX(MF_Master!$A:$A,MATCH($C16,MF_Master!$B:$B,0)),"")) | D16: =IF($C16="","",IFERROR(INDEX(MF_Master!$C:$C,MATCH($C16,MF_Master!$B:$B,0)),"")) | H16: =IF(OR($F16="",$G16=""),"",$F16/$G16)
B17: =IF($C17="","",IFERROR(INDEX(MF_Master!$A:$A,MATCH($C17,MF_Master!$B:$B,0)),"")) | D17: =IF($C17="","",IFERROR(INDEX(MF_Master!$C:$C,MATCH($C17,MF_Master!$B:$B,0)),"")) | H17: =IF(OR($F17="",$G17=""),"",$F17/$G17)
B18: =IF($C18="","",IFERROR(INDEX(MF_Master!$A:$A,MATCH($C18,MF_Master!$B:$B,0)),"")) | D18: =IF($C18="","",IFERROR(INDEX(MF_Master!$C:$C,MATCH($C18,MF_Master!$B:$B,0)),"")) | H18: =IF(OR($F18="",$G18=""),"",$F18/$G18)
B19: =IF($C19="","",IFERROR(INDEX(MF_Master!$A:$A,MATCH($C19,MF_Master!$B:$B,0)),"")) | D19: =IF($C19="","",IFERROR(INDEX(MF_Master!$C:$C,MATCH($C19,MF_Master!$B:$B,0)),"")) | H19: =IF(OR($F19="",$G19=""),"",$F19/$G19)
B20: =IF($C20="","",IFERROR(INDEX(MF_Master!$A:$A,MATCH($C20,MF_Master!$B:$B,0)),"")) | D20: =IF($C20="","",IFERROR(INDEX(MF_Master!$C:$C,MATCH($C20,MF_Master!$B:$B,0)),"")) | H20: =IF(OR($F20="",$G20=""),"",$F20/$G20)
B21: =IF($C21="","",IFERROR(INDEX(MF_Master!$A:$A,MATCH($C21,MF_Master!$B:$B,0)),"")) | D21: =IF($C21="","",IFERROR(INDEX(MF_Master!$C:$C,MATCH($C21,MF_Master!$B:$B,0)),"")) | H21: =IF(OR($F21="",$G21=""),"",$F21/$G21)
B22: =IF($C22="","",IFERROR(INDEX(MF_Master!$A:$A,MATCH($C22,MF_Master!$B:$B,0)),"")) | D22: =IF($C22="","",IFERROR(INDEX(MF_Master!$C:$C,MATCH($C22,MF_Master!$B:$B,0)),"")) | H22: =IF(OR($F22="",$G22=""),"",$F22/$G22)
... B503: =IF($C503="","",IFERROR(INDEX(MF_Master!$A:$A,MATCH($C503,MF_Master!$B:$B,0)),"")) | D503: =IF($C503="","",IFERROR(INDEX(MF_Master!$C:$C,MATCH($C503,MF_Master!$B:$B,0)),"")) | H503: =IF(OR($F503="",$G503=""),"",$F503/$G503)

Sheet MF_Master
A1: MUTUAL FUND MASTER (AMFI)
A2: Every AMFI scheme with an ISIN — feeds the Scheme dropdowns on MutualFunds and MF_SIP. Kept sorted by scheme name (the dropdown filter needs that). Do not edit by hand: double-click UpdateFundMaster.bat to refresh it. | D2: Refreshed: | E2: 14-07-2026
A3: Fund Name | B3: Scheme Name | C3: ISIN
A4: 360 ONE Mutual Fund | B4: 360 ONE Balanced Hybrid Fund - Direct Plan - IDCW | C4: INF579M01AZ6
A5: 360 ONE Mutual Fund | B5: 360 ONE Balanced Hybrid Fund - Regular Plan - Growth | C5: INF579M01AV5
A6: 360 ONE Mutual Fund | B6: 360 ONE Balanced Hybrid Fund- Direct Plan - Growth | C6: INF579M01AY9
A7: 360 ONE Mutual Fund | B7: 360 ONE Balanced Hyrbrid fund - Regular Plan - IDCW | C7: INF579M01AW3
A8: 360 ONE Mutual Fund | B8: 360 ONE Dynamic Bond Fund - Regular Plan - Growth Option | C8: INF579M01183
A9: 360 ONE Mutual Fund | B9: 360 ONE Dynamic Bond Fund Direct Plan Growth | C9: INF579M01266
A10: 360 ONE Mutual Fund | B10: 360 ONE Dynamic Bond Fund Direct Plan Monthly Dividend | C10: INF579M01282
A11: 360 ONE Mutual Fund | B11: 360 ONE Dynamic Bond Fund Direct Plan Quarterly Dividend | C11: INF579M01290
A12: 360 ONE Mutual Fund | B12: 360 ONE Dynamic Bond Fund Regular Plan Bonus | C12: INF579M01191
A13: 360 ONE Mutual Fund | B13: 360 ONE Dynamic Bond Fund Regular Plan Half Yearly Dividend | C13: INF579M01225
A14: 360 ONE Mutual Fund | B14: 360 ONE Dynamic Bond Fund Regular Plan Monthly Dividend | C14: INF579M01209
... A14049: Zerodha Mutual Fund | B14049: Zerodha Silver ETF FoF - Direct Growth | C14049: INF0R8F01109

Sheet Stock_Master
A1: STOCK MASTER (BSE/NSE bhavcopy)
A2: Feeds the Scrip dropdown on the Equity sheet. Auto-refreshed by UpdatePrices.bat: newly listed stocks are added, existing names are kept stable. Do not edit by hand. | D2: Refreshed: | E2: 14-07-2026
A3: Symbol | B3: Stock Name | C3: ISIN
A4: 20MICRONS | B4: 20 MICRONS LTD. | C4: INE144J01027
A5: 360ONE | B5: 360 ONE WAM LIMITED | C5: INE466L01038
A6: 926ONE29 | B6: 360OPL-9.26%-18-1-29-NCD | C6: INE248U07ES6
A7: 961ONE27 | B7: 360OPL-9.61%-18-1-27-NCD | C7: INE248U07EW8
A8: 3BBLACKBIO | B8: 3B BlackBio Dx Limited | C8: INE994E01018
A9: 3BFILMS | B9: 3B FILMS LIMITED | C9: INE0TE101010
A10: 3IINFOLTD | B10: 3I INFOTECH LTD. | C10: INE748C01038
A11: 3MINDIA | B11: 3M INDIA LTD. | C11: INE470A01017
A12: 3PLAND | B12: 3P LAND HOLDINGS LTD. | C12: INE105C01023
A13: 5PAISA | B13: 5paisa Capital Limited | C13: INE618L01018
A14: 63MOONS | B14: 63 Moons Technologies Limited | C14: INE111B01023
... A4564: ZYDUSWELL | B4564: ZYDUS WELLNESS LTD. | C4564: INE768C01028

Sheet FixedDeposits
A1: FIXED DEPOSITS
A2: Enter Owner, Bank, FD no., Principal, Rate % p.a., Start & Maturity dates, Compounding/yr (4 = quarterly, the usual). Value today & Maturity value compute with compound interest.
A3: Owner | B3: Bank / Institution | C3: FD No. | D3: Principal | E3: Rate % p.a. | F3: Start Date | G3: Maturity Date | H3: Comp./yr | I3: Value as on today | J3: Maturity Value | L3: Key
A4: Amit | B4: HDFC Bank | C4: FD-2024-0117 | D4: 500000 | E4: 7.1 | F4: 45383 | G4: 46478 | H4: 4 | I4: =IF($D4="","",$D4*(1+($E4/100)/$H4)^($H4*YEARFRAC($F4,MIN(TODAY(),$G4)))) -> 587277.98 | J4: =IF($D4="","",$D4*(1+($E4/100)/$H4)^($H4*YEARFRAC($F4,$G4))) -> 617537.5 | L4: =IF($A4="","",$A4&"#"&COUNTIF($A$4:$A4,$A4)) -> Amit#1
A5: Rahul | B5: SBI | C5: FD-2025-0342 | D5: 300000 | E5: 6.8 | F5: 45672 | G5: 46767 | H5: 4 | I5: =IF($D5="","",$D5*(1+($E5/100)/$H5)^($H5*YEARFRAC($F5,MIN(TODAY(),$G5)))) -> 331868.19 | J5: =IF($D5="","",$D5*(1+($E5/100)/$H5)^($H5*YEARFRAC($F5,$G5))) -> 367259.21 | L5: =IF($A5="","",$A5&"#"&COUNTIF($A$4:$A5,$A5)) -> Rahul#1
I6: =IF($D6="","",$D6*(1+($E6/100)/$H6)^($H6*YEARFRAC($F6,MIN(TODAY(),$G6)))) | J6: =IF($D6="","",$D6*(1+($E6/100)/$H6)^($H6*YEARFRAC($F6,$G6))) | L6: =IF($A6="","",$A6&"#"&COUNTIF($A$4:$A6,$A6))
I7: =IF($D7="","",$D7*(1+($E7/100)/$H7)^($H7*YEARFRAC($F7,MIN(TODAY(),$G7)))) | J7: =IF($D7="","",$D7*(1+($E7/100)/$H7)^($H7*YEARFRAC($F7,$G7))) | L7: =IF($A7="","",$A7&"#"&COUNTIF($A$4:$A7,$A7))
I8: =IF($D8="","",$D8*(1+($E8/100)/$H8)^($H8*YEARFRAC($F8,MIN(TODAY(),$G8)))) | J8: =IF($D8="","",$D8*(1+($E8/100)/$H8)^($H8*YEARFRAC($F8,$G8))) | L8: =IF($A8="","",$A8&"#"&COUNTIF($A$4:$A8,$A8))
I9: =IF($D9="","",$D9*(1+($E9/100)/$H9)^($H9*YEARFRAC($F9,MIN(TODAY(),$G9)))) | J9: =IF($D9="","",$D9*(1+($E9/100)/$H9)^($H9*YEARFRAC($F9,$G9))) | L9: =IF($A9="","",$A9&"#"&COUNTIF($A$4:$A9,$A9))
I10: =IF($D10="","",$D10*(1+($E10/100)/$H10)^($H10*YEARFRAC($F10,MIN(TODAY(),$G10)))) | J10: =IF($D10="","",$D10*(1+($E10/100)/$H10)^($H10*YEARFRAC($F10,$G10))) | L10: =IF($A10="","",$A10&"#"&COUNTIF($A$4:$A10,$A10))
I11: =IF($D11="","",$D11*(1+($E11/100)/$H11)^($H11*YEARFRAC($F11,MIN(TODAY(),$G11)))) | J11: =IF($D11="","",$D11*(1+($E11/100)/$H11)^($H11*YEARFRAC($F11,$G11))) | L11: =IF($A11="","",$A11&"#"&COUNTIF($A$4:$A11,$A11))
I12: =IF($D12="","",$D12*(1+($E12/100)/$H12)^($H12*YEARFRAC($F12,MIN(TODAY(),$G12)))) | J12: =IF($D12="","",$D12*(1+($E12/100)/$H12)^($H12*YEARFRAC($F12,$G12))) | L12: =IF($A12="","",$A12&"#"&COUNTIF($A$4:$A12,$A12))
I13: =IF($D13="","",$D13*(1+($E13/100)/$H13)^($H13*YEARFRAC($F13,MIN(TODAY(),$G13)))) | J13: =IF($D13="","",$D13*(1+($E13/100)/$H13)^($H13*YEARFRAC($F13,$G13))) | L13: =IF($A13="","",$A13&"#"&COUNTIF($A$4:$A13,$A13))
I14: =IF($D14="","",$D14*(1+($E14/100)/$H14)^($H14*YEARFRAC($F14,MIN(TODAY(),$G14)))) | J14: =IF($D14="","",$D14*(1+($E14/100)/$H14)^($H14*YEARFRAC($F14,$G14))) | L14: =IF($A14="","",$A14&"#"&COUNTIF($A$4:$A14,$A14))
I15: =IF($D15="","",$D15*(1+($E15/100)/$H15)^($H15*YEARFRAC($F15,MIN(TODAY(),$G15)))) | J15: =IF($D15="","",$D15*(1+($E15/100)/$H15)^($H15*YEARFRAC($F15,$G15))) | L15: =IF($A15="","",$A15&"#"&COUNTIF($A$4:$A15,$A15))
I16: =IF($D16="","",$D16*(1+($E16/100)/$H16)^($H16*YEARFRAC($F16,MIN(TODAY(),$G16)))) | J16: =IF($D16="","",$D16*(1+($E16/100)/$H16)^($H16*YEARFRAC($F16,$G16))) | L16: =IF($A16="","",$A16&"#"&COUNTIF($A$4:$A16,$A16))
I17: =IF($D17="","",$D17*(1+($E17/100)/$H17)^($H17*YEARFRAC($F17,MIN(TODAY(),$G17)))) | J17: =IF($D17="","",$D17*(1+($E17/100)/$H17)^($H17*YEARFRAC($F17,$G17))) | L17: =IF($A17="","",$A17&"#"&COUNTIF($A$4:$A17,$A17))
... I53: =IF($D53="","",$D53*(1+($E53/100)/$H53)^($H53*YEARFRAC($F53,MIN(TODAY(),$G53)))) | J53: =IF($D53="","",$D53*(1+($E53/100)/$H53)^($H53*YEARFRAC($F53,$G53))) | L53: =IF($A53="","",$A53&"#"&COUNTIF($A$4:$A53,$A53))
C55: TOTAL | I55: =SUM(I4:I53) -> 919146.17 | J55: =SUM(J4:J53) -> 984796.71

Sheet PPF
A1: PPF ACCOUNTS
A2: Enter Owner, Institution, Account no., Current balance and the date it is as-of. Update the balance yourself (typically once a year after interest is credited).
A3: Owner | B3: Institution | C3: Account No. | D3: Current Balance | E3: Balance as-on | F3: Rate % (ref) | G3: Notes | I3: Key
A4: Priya | B4: Post Office | C4: PPF-104522 | D4: 860000 | E4: 46112 | F4: 7.1 | G4: Matures 2031 | I4: =IF($A4="","",$A4&"#"&COUNTIF($A$4:$A4,$A4)) -> Priya#1
A5: Amit | B5: SBI | C5: PPF-778101 | D5: 425000 | E5: 46112 | F5: 7.1 | I5: =IF($A5="","",$A5&"#"&COUNTIF($A$4:$A5,$A5)) -> Amit#1
I6: =IF($A6="","",$A6&"#"&COUNTIF($A$4:$A6,$A6))
I7: =IF($A7="","",$A7&"#"&COUNTIF($A$4:$A7,$A7))
I8: =IF($A8="","",$A8&"#"&COUNTIF($A$4:$A8,$A8))
I9: =IF($A9="","",$A9&"#"&COUNTIF($A$4:$A9,$A9))
I10: =IF($A10="","",$A10&"#"&COUNTIF($A$4:$A10,$A10))
I11: =IF($A11="","",$A11&"#"&COUNTIF($A$4:$A11,$A11))
I12: =IF($A12="","",$A12&"#"&COUNTIF($A$4:$A12,$A12))
I13: =IF($A13="","",$A13&"#"&COUNTIF($A$4:$A13,$A13))
I14: =IF($A14="","",$A14&"#"&COUNTIF($A$4:$A14,$A14))
I15: =IF($A15="","",$A15&"#"&COUNTIF($A$4:$A15,$A15))
I16: =IF($A16="","",$A16&"#"&COUNTIF($A$4:$A16,$A16))
I17: =IF($A17="","",$A17&"#"&COUNTIF($A$4:$A17,$A17))
... I43: =IF($A43="","",$A43&"#"&COUNTIF($A$4:$A43,$A43))
C45: TOTAL | D45: =SUM(D4:D43) -> 1285000

Sheet Bonds
A1: CORPORATE / OTHER BONDS
A2: Enter Owner, Issuer, ISIN, Qty, Face value, Buy price, Current price, Coupon %, Maturity and Buy Date (drives XIRR; leave it empty to keep the row out of XIRR). Invested / Cur. val / Net chg. compute themselves. Corporate bonds are illiquid — update Current Price manually.
A3: Owner | B3: Issuer / Bond | C3: ISIN | D3: Qty | E3: Face Value | F3: Buy Price | G3: Current Price | H3: Coupon % p.a. | I3: Maturity Date | J3: Invested | K3: Cur. val | L3: Net chg. | M3: Buy Date | N3: Key
A4: Rahul | B4: 8.5% NHAI Bond 2029 | C4: INE906B07CB9 | D4: 50 | E4: 1000 | F4: 1000 | G4: 1015 | H4: 8.5 | I4: 47133 | J4: =IF(OR($D4="",$F4=""),"",$D4*$F4) -> 50000 | K4: =IF(OR($D4="",$G4=""),"",$D4*$G4) -> 50750 | L4: =IF(OR($F4="",$D4=""),"",$K4-$J4) -> 750 | M4: 45306 | N4: =IF($A4="","",$A4&"#"&COUNTIF($A$4:$A4,$A4)) -> Rahul#1
J5: =IF(OR($D5="",$F5=""),"",$D5*$F5) | K5: =IF(OR($D5="",$G5=""),"",$D5*$G5) | L5: =IF(OR($F5="",$D5=""),"",$K5-$J5) | N5: =IF($A5="","",$A5&"#"&COUNTIF($A$4:$A5,$A5))
J6: =IF(OR($D6="",$F6=""),"",$D6*$F6) | K6: =IF(OR($D6="",$G6=""),"",$D6*$G6) | L6: =IF(OR($F6="",$D6=""),"",$K6-$J6) | N6: =IF($A6="","",$A6&"#"&COUNTIF($A$4:$A6,$A6))
J7: =IF(OR($D7="",$F7=""),"",$D7*$F7) | K7: =IF(OR($D7="",$G7=""),"",$D7*$G7) | L7: =IF(OR($F7="",$D7=""),"",$K7-$J7) | N7: =IF($A7="","",$A7&"#"&COUNTIF($A$4:$A7,$A7))
J8: =IF(OR($D8="",$F8=""),"",$D8*$F8) | K8: =IF(OR($D8="",$G8=""),"",$D8*$G8) | L8: =IF(OR($F8="",$D8=""),"",$K8-$J8) | N8: =IF($A8="","",$A8&"#"&COUNTIF($A$4:$A8,$A8))
J9: =IF(OR($D9="",$F9=""),"",$D9*$F9) | K9: =IF(OR($D9="",$G9=""),"",$D9*$G9) | L9: =IF(OR($F9="",$D9=""),"",$K9-$J9) | N9: =IF($A9="","",$A9&"#"&COUNTIF($A$4:$A9,$A9))
J10: =IF(OR($D10="",$F10=""),"",$D10*$F10) | K10: =IF(OR($D10="",$G10=""),"",$D10*$G10) | L10: =IF(OR($F10="",$D10=""),"",$K10-$J10) | N10: =IF($A10="","",$A10&"#"&COUNTIF($A$4:$A10,$A10))
J11: =IF(OR($D11="",$F11=""),"",$D11*$F11) | K11: =IF(OR($D11="",$G11=""),"",$D11*$G11) | L11: =IF(OR($F11="",$D11=""),"",$K11-$J11) | N11: =IF($A11="","",$A11&"#"&COUNTIF($A$4:$A11,$A11))
J12: =IF(OR($D12="",$F12=""),"",$D12*$F12) | K12: =IF(OR($D12="",$G12=""),"",$D12*$G12) | L12: =IF(OR($F12="",$D12=""),"",$K12-$J12) | N12: =IF($A12="","",$A12&"#"&COUNTIF($A$4:$A12,$A12))
J13: =IF(OR($D13="",$F13=""),"",$D13*$F13) | K13: =IF(OR($D13="",$G13=""),"",$D13*$G13) | L13: =IF(OR($F13="",$D13=""),"",$K13-$J13) | N13: =IF($A13="","",$A13&"#"&COUNTIF($A$4:$A13,$A13))
J14: =IF(OR($D14="",$F14=""),"",$D14*$F14) | K14: =IF(OR($D14="",$G14=""),"",$D14*$G14) | L14: =IF(OR($F14="",$D14=""),"",$K14-$J14) | N14: =IF($A14="","",$A14&"#"&COUNTIF($A$4:$A14,$A14))
J15: =IF(OR($D15="",$F15=""),"",$D15*$F15) | K15: =IF(OR($D15="",$G15=""),"",$D15*$G15) | L15: =IF(OR($F15="",$D15=""),"",$K15-$J15) | N15: =IF($A15="","",$A15&"#"&COUNTIF($A$4:$A15,$A15))
J16: =IF(OR($D16="",$F16=""),"",$D16*$F16) | K16: =IF(OR($D16="",$G16=""),"",$D16*$G16) | L16: =IF(OR($F16="",$D16=""),"",$K16-$J16) | N16: =IF($A16="","",$A16&"#"&COUNTIF($A$4:$A16,$A16))
... J53: =IF(OR($D53="",$F53=""),"",$D53*$F53) | K53: =IF(OR($D53="",$G53=""),"",$D53*$G53) | L53: =IF(OR($F53="",$D53=""),"",$K53-$J53) | N53: =IF($A53="","",$A53&"#"&COUNTIF($A$4:$A53,$A53))
C55: TOTAL | J55: =SUM(J4:J53) -> 50000 | K55: =SUM(K4:K53) -> 50750 | L55: =SUM(L4:L53) -> 750

Sheet By Scrip
A1: FAMILY EXPOSURE BY SCRIP
A2: Total family quantity and current value per scrip, split by person. Live from the Equity sheet. To add a scrip not listed, type its ISIN and name in a blank row.
A3: ISIN | B3: Scrip | C3: Total Qty | D3: Amit | E3: Priya | F3: Rahul | G3: Cur. val
A4: INE040A01034 | B4: HDFC BANK LTD. | C4: =IF($A4="","",SUMIF(Equity!$B:$B,$A4,Equity!$D:$D)) -> 60 | D4: =IF($A4="","",SUMIFS(Equity!$D:$D,Equity!$B:$B,$A4,Equity!$A:$A,"Amit")) -> 60 | E4: =IF($A4="","",SUMIFS(Equity!$D:$D,Equity!$B:$B,$A4,Equity!$A:$A,"Priya")) -> 0 | F4: =IF($A4="","",SUMIFS(Equity!$D:$D,Equity!$B:$B,$A4,Equity!$A:$A,"Rahul")) -> 0 | G4: =IF($A4="","",SUMIF(Equity!$B:$B,$A4,Equity!$I:$I)) -> 101400
A5: INE030A01027 | B5: HINDUSTAN UNILEVER LTD. | C5: =IF($A5="","",SUMIF(Equity!$B:$B,$A5,Equity!$D:$D)) -> 30 | D5: =IF($A5="","",SUMIFS(Equity!$D:$D,Equity!$B:$B,$A5,Equity!$A:$A,"Amit")) -> 0 | E5: =IF($A5="","",SUMIFS(Equity!$D:$D,Equity!$B:$B,$A5,Equity!$A:$A,"Priya")) -> 0 | F5: =IF($A5="","",SUMIFS(Equity!$D:$D,Equity!$B:$B,$A5,Equity!$A:$A,"Rahul")) -> 30 | G5: =IF($A5="","",SUMIF(Equity!$B:$B,$A5,Equity!$I:$I)) -> 72300
A6: INE090A01021 | B6: ICICI BANK LTD. | C6: =IF($A6="","",SUMIF(Equity!$B:$B,$A6,Equity!$D:$D)) -> 80 | D6: =IF($A6="","",SUMIFS(Equity!$D:$D,Equity!$B:$B,$A6,Equity!$A:$A,"Amit")) -> 0 | E6: =IF($A6="","",SUMIFS(Equity!$D:$D,Equity!$B:$B,$A6,Equity!$A:$A,"Priya")) -> 80 | F6: =IF($A6="","",SUMIFS(Equity!$D:$D,Equity!$B:$B,$A6,Equity!$A:$A,"Rahul")) -> 0 | G6: =IF($A6="","",SUMIF(Equity!$B:$B,$A6,Equity!$I:$I)) -> 99200
A7: INE009A01021 | B7: INFOSYS LTD. | C7: =IF($A7="","",SUMIF(Equity!$B:$B,$A7,Equity!$D:$D)) -> 40 | D7: =IF($A7="","",SUMIFS(Equity!$D:$D,Equity!$B:$B,$A7,Equity!$A:$A,"Amit")) -> 40 | E7: =IF($A7="","",SUMIFS(Equity!$D:$D,Equity!$B:$B,$A7,Equity!$A:$A,"Priya")) -> 0 | F7: =IF($A7="","",SUMIFS(Equity!$D:$D,Equity!$B:$B,$A7,Equity!$A:$A,"Rahul")) -> 0 | G7: =IF($A7="","",SUMIF(Equity!$B:$B,$A7,Equity!$I:$I)) -> 64400
A8: INE154A01025 | B8: ITC LTD. | C8: =IF($A8="","",SUMIF(Equity!$B:$B,$A8,Equity!$D:$D)) -> 200 | D8: =IF($A8="","",SUMIFS(Equity!$D:$D,Equity!$B:$B,$A8,Equity!$A:$A,"Amit")) -> 0 | E8: =IF($A8="","",SUMIFS(Equity!$D:$D,Equity!$B:$B,$A8,Equity!$A:$A,"Priya")) -> 200 | F8: =IF($A8="","",SUMIFS(Equity!$D:$D,Equity!$B:$B,$A8,Equity!$A:$A,"Rahul")) -> 0 | G8: =IF($A8="","",SUMIF(Equity!$B:$B,$A8,Equity!$I:$I)) -> 87000
A9: INE018A01030 | B9: LARSEN & TOUBRO LTD. | C9: =IF($A9="","",SUMIF(Equity!$B:$B,$A9,Equity!$D:$D)) -> 25 | D9: =IF($A9="","",SUMIFS(Equity!$D:$D,Equity!$B:$B,$A9,Equity!$A:$A,"Amit")) -> 0 | E9: =IF($A9="","",SUMIFS(Equity!$D:$D,Equity!$B:$B,$A9,Equity!$A:$A,"Priya")) -> 0 | F9: =IF($A9="","",SUMIFS(Equity!$D:$D,Equity!$B:$B,$A9,Equity!$A:$A,"Rahul")) -> 25 | G9: =IF($A9="","",SUMIF(Equity!$B:$B,$A9,Equity!$I:$I)) -> 90500
A10: INE002A01018 | B10: RELIANCE INDUSTRIES LTD. | C10: =IF($A10="","",SUMIF(Equity!$B:$B,$A10,Equity!$D:$D)) -> 50 | D10: =IF($A10="","",SUMIFS(Equity!$D:$D,Equity!$B:$B,$A10,Equity!$A:$A,"Amit")) -> 50 | E10: =IF($A10="","",SUMIFS(Equity!$D:$D,Equity!$B:$B,$A10,Equity!$A:$A,"Priya")) -> 0 | F10: =IF($A10="","",SUMIFS(Equity!$D:$D,Equity!$B:$B,$A10,Equity!$A:$A,"Rahul")) -> 0 | G10: =IF($A10="","",SUMIF(Equity!$B:$B,$A10,Equity!$I:$I)) -> 76000
A11: INE062A01020 | B11: STATE BANK OF INDIA | C11: =IF($A11="","",SUMIF(Equity!$B:$B,$A11,Equity!$D:$D)) -> 120 | D11: =IF($A11="","",SUMIFS(Equity!$D:$D,Equity!$B:$B,$A11,Equity!$A:$A,"Amit")) -> 0 | E11: =IF($A11="","",SUMIFS(Equity!$D:$D,Equity!$B:$B,$A11,Equity!$A:$A,"Priya")) -> 0 | F11: =IF($A11="","",SUMIFS(Equity!$D:$D,Equity!$B:$B,$A11,Equity!$A:$A,"Rahul")) -> 120 | G11: =IF($A11="","",SUMIF(Equity!$B:$B,$A11,Equity!$I:$I)) -> 97800
A12: INE467B01029 | B12: TATA CONSULTANCY SERVICES LTD. | C12: =IF($A12="","",SUMIF(Equity!$B:$B,$A12,Equity!$D:$D)) -> 12 | D12: =IF($A12="","",SUMIFS(Equity!$D:$D,Equity!$B:$B,$A12,Equity!$A:$A,"Amit")) -> 12 | E12: =IF($A12="","",SUMIFS(Equity!$D:$D,Equity!$B:$B,$A12,Equity!$A:$A,"Priya")) -> 0 | F12: =IF($A12="","",SUMIFS(Equity!$D:$D,Equity!$B:$B,$A12,Equity!$A:$A,"Rahul")) -> 0 | G12: =IF($A12="","",SUMIF(Equity!$B:$B,$A12,Equity!$I:$I)) -> 41400
A13: INE075A01022 | B13: WIPRO LTD. | C13: =IF($A13="","",SUMIF(Equity!$B:$B,$A13,Equity!$D:$D)) -> 150 | D13: =IF($A13="","",SUMIFS(Equity!$D:$D,Equity!$B:$B,$A13,Equity!$A:$A,"Amit")) -> 0 | E13: =IF($A13="","",SUMIFS(Equity!$D:$D,Equity!$B:$B,$A13,Equity!$A:$A,"Priya")) -> 150 | F13: =IF($A13="","",SUMIFS(Equity!$D:$D,Equity!$B:$B,$A13,Equity!$A:$A,"Rahul")) -> 0 | G13: =IF($A13="","",SUMIF(Equity!$B:$B,$A13,Equity!$I:$I)) -> 36750
C14: =IF($A14="","",SUMIF(Equity!$B:$B,$A14,Equity!$D:$D)) | D14: =IF($A14="","",SUMIFS(Equity!$D:$D,Equity!$B:$B,$A14,Equity!$A:$A,"Amit")) | E14: =IF($A14="","",SUMIFS(Equity!$D:$D,Equity!$B:$B,$A14,Equity!$A:$A,"Priya")) | F14: =IF($A14="","",SUMIFS(Equity!$D:$D,Equity!$B:$B,$A14,Equity!$A:$A,"Rahul")) | G14: =IF($A14="","",SUMIF(Equity!$B:$B,$A14,Equity!$I:$I))
C15: =IF($A15="","",SUMIF(Equity!$B:$B,$A15,Equity!$D:$D)) | D15: =IF($A15="","",SUMIFS(Equity!$D:$D,Equity!$B:$B,$A15,Equity!$A:$A,"Amit")) | E15: =IF($A15="","",SUMIFS(Equity!$D:$D,Equity!$B:$B,$A15,Equity!$A:$A,"Priya")) | F15: =IF($A15="","",SUMIFS(Equity!$D:$D,Equity!$B:$B,$A15,Equity!$A:$A,"Rahul")) | G15: =IF($A15="","",SUMIF(Equity!$B:$B,$A15,Equity!$I:$I))
C16: =IF($A16="","",SUMIF(Equity!$B:$B,$A16,Equity!$D:$D)) | D16: =IF($A16="","",SUMIFS(Equity!$D:$D,Equity!$B:$B,$A16,Equity!$A:$A,"Amit")) | E16: =IF($A16="","",SUMIFS(Equity!$D:$D,Equity!$B:$B,$A16,Equity!$A:$A,"Priya")) | F16: =IF($A16="","",SUMIFS(Equity!$D:$D,Equity!$B:$B,$A16,Equity!$A:$A,"Rahul")) | G16: =IF($A16="","",SUMIF(Equity!$B:$B,$A16,Equity!$I:$I))
C17: =IF($A17="","",SUMIF(Equity!$B:$B,$A17,Equity!$D:$D)) | D17: =IF($A17="","",SUMIFS(Equity!$D:$D,Equity!$B:$B,$A17,Equity!$A:$A,"Amit")) | E17: =IF($A17="","",SUMIFS(Equity!$D:$D,Equity!$B:$B,$A17,Equity!$A:$A,"Priya")) | F17: =IF($A17="","",SUMIFS(Equity!$D:$D,Equity!$B:$B,$A17,Equity!$A:$A,"Rahul")) | G17: =IF($A17="","",SUMIF(Equity!$B:$B,$A17,Equity!$I:$I))
C18: =IF($A18="","",SUMIF(Equity!$B:$B,$A18,Equity!$D:$D)) | D18: =IF($A18="","",SUMIFS(Equity!$D:$D,Equity!$B:$B,$A18,Equity!$A:$A,"Amit")) | E18: =IF($A18="","",SUMIFS(Equity!$D:$D,Equity!$B:$B,$A18,Equity!$A:$A,"Priya")) | F18: =IF($A18="","",SUMIFS(Equity!$D:$D,Equity!$B:$B,$A18,Equity!$A:$A,"Rahul")) | G18: =IF($A18="","",SUMIF(Equity!$B:$B,$A18,Equity!$I:$I))
C19: =IF($A19="","",SUMIF(Equity!$B:$B,$A19,Equity!$D:$D)) | D19: =IF($A19="","",SUMIFS(Equity!$D:$D,Equity!$B:$B,$A19,Equity!$A:$A,"Amit")) | E19: =IF($A19="","",SUMIFS(Equity!$D:$D,Equity!$B:$B,$A19,Equity!$A:$A,"Priya")) | F19: =IF($A19="","",SUMIFS(Equity!$D:$D,Equity!$B:$B,$A19,Equity!$A:$A,"Rahul")) | G19: =IF($A19="","",SUMIF(Equity!$B:$B,$A19,Equity!$I:$I))
C20: =IF($A20="","",SUMIF(Equity!$B:$B,$A20,Equity!$D:$D)) | D20: =IF($A20="","",SUMIFS(Equity!$D:$D,Equity!$B:$B,$A20,Equity!$A:$A,"Amit")) | E20: =IF($A20="","",SUMIFS(Equity!$D:$D,Equity!$B:$B,$A20,Equity!$A:$A,"Priya")) | F20: =IF($A20="","",SUMIFS(Equity!$D:$D,Equity!$B:$B,$A20,Equity!$A:$A,"Rahul")) | G20: =IF($A20="","",SUMIF(Equity!$B:$B,$A20,Equity!$I:$I))
C21: =IF($A21="","",SUMIF(Equity!$B:$B,$A21,Equity!$D:$D)) | D21: =IF($A21="","",SUMIFS(Equity!$D:$D,Equity!$B:$B,$A21,Equity!$A:$A,"Amit")) | E21: =IF($A21="","",SUMIFS(Equity!$D:$D,Equity!$B:$B,$A21,Equity!$A:$A,"Priya")) | F21: =IF($A21="","",SUMIFS(Equity!$D:$D,Equity!$B:$B,$A21,Equity!$A:$A,"Rahul")) | G21: =IF($A21="","",SUMIF(Equity!$B:$B,$A21,Equity!$I:$I))
C22: =IF($A22="","",SUMIF(Equity!$B:$B,$A22,Equity!$D:$D)) | D22: =IF($A22="","",SUMIFS(Equity!$D:$D,Equity!$B:$B,$A22,Equity!$A:$A,"Amit")) | E22: =IF($A22="","",SUMIFS(Equity!$D:$D,Equity!$B:$B,$A22,Equity!$A:$A,"Priya")) | F22: =IF($A22="","",SUMIFS(Equity!$D:$D,Equity!$B:$B,$A22,Equity!$A:$A,"Rahul")) | G22: =IF($A22="","",SUMIF(Equity!$B:$B,$A22,Equity!$I:$I))
C23: =IF($A23="","",SUMIF(Equity!$B:$B,$A23,Equity!$D:$D)) | D23: =IF($A23="","",SUMIFS(Equity!$D:$D,Equity!$B:$B,$A23,Equity!$A:$A,"Amit")) | E23: =IF($A23="","",SUMIFS(Equity!$D:$D,Equity!$B:$B,$A23,Equity!$A:$A,"Priya")) | F23: =IF($A23="","",SUMIFS(Equity!$D:$D,Equity!$B:$B,$A23,Equity!$A:$A,"Rahul")) | G23: =IF($A23="","",SUMIF(Equity!$B:$B,$A23,Equity!$I:$I))
C24: =IF($A24="","",SUMIF(Equity!$B:$B,$A24,Equity!$D:$D)) | D24: =IF($A24="","",SUMIFS(Equity!$D:$D,Equity!$B:$B,$A24,Equity!$A:$A,"Amit")) | E24: =IF($A24="","",SUMIFS(Equity!$D:$D,Equity!$B:$B,$A24,Equity!$A:$A,"Priya")) | F24: =IF($A24="","",SUMIFS(Equity!$D:$D,Equity!$B:$B,$A24,Equity!$A:$A,"Rahul")) | G24: =IF($A24="","",SUMIF(Equity!$B:$B,$A24,Equity!$I:$I))
C25: =IF($A25="","",SUMIF(Equity!$B:$B,$A25,Equity!$D:$D)) | D25: =IF($A25="","",SUMIFS(Equity!$D:$D,Equity!$B:$B,$A25,Equity!$A:$A,"Amit")) | E25: =IF($A25="","",SUMIFS(Equity!$D:$D,Equity!$B:$B,$A25,Equity!$A:$A,"Priya")) | F25: =IF($A25="","",SUMIFS(Equity!$D:$D,Equity!$B:$B,$A25,Equity!$A:$A,"Rahul")) | G25: =IF($A25="","",SUMIF(Equity!$B:$B,$A25,Equity!$I:$I))
... C28: =IF($A28="","",SUMIF(Equity!$B:$B,$A28,Equity!$D:$D)) | D28: =IF($A28="","",SUMIFS(Equity!$D:$D,Equity!$B:$B,$A28,Equity!$A:$A,"Amit")) | E28: =IF($A28="","",SUMIFS(Equity!$D:$D,Equity!$B:$B,$A28,Equity!$A:$A,"Priya")) | F28: =IF($A28="","",SUMIFS(Equity!$D:$D,Equity!$B:$B,$A28,Equity!$A:$A,"Rahul")) | G28: =IF($A28="","",SUMIF(Equity!$B:$B,$A28,Equity!$I:$I))
B29: TOTAL | G29: =SUM(G4:G28) -> 766750

Sheet Guide
A1: HOW TO USE THIS TRACKER
A4: This one workbook tracks the whole family's net worth across asset classes.
A5: The Dashboard adds everything up automatically with formulas — you never edit formulas.
A7: ADD A NEW PERSON
A8: - Type their name in the Owner column of any asset sheet (Equity, MutualFunds, etc.).
A9: - Add the same name into an empty yellow 'Person' cell on the Dashboard (rows 6-15).
A10: That's it — their totals appear and roll into the family total and charts.
A12: ADD A HOLDING
A13: - Equity: add a row on Equity - Owner, then PICK the Scrip from the dropdown
A14: (ISIN fills in from Stock_Master), Qty, Avg cost. 'Cost date' drives the per-stock
A15: XIRR - pre-set to 31-Jan-2018 (FMV grandfathering) or the IPO date for post-2018
A16: listings; replace with your actual purchase date for precision.
... A62: blank after entering a name, it did not match the master - re-pick from the list.
